Workbook

Sheet READ ME
A1: Engine Ventures — New Deal Pipeline, ADVANCED-STAGE COHORT (rescoped 2026-09-02)
A3: Scope: every company appearing on a New Deal Meeting slide from 2025-10-14 through 2026-08-31 that reached Preliminary Diligence, Deep Diligence, Negotiate/Offer, or Legal Diligence at least once. Companies whose furthest stage was NewCo/Fellows, Hold/Nurture, or Meetings This Week were removed from this file on 2026-09-02, at the request of the deal team, to focus this database on companies past a first meeting. See the rescope log below for what was cut.
A4: 43 weekly meetings · 187 distinct companies in this file (was 481 pre-rescope, 498 pre-dedup) · built 2026-09-01, deduplicated & enriched 2026-09-02, rescoped to advanced-stage-only 2026-09-02.
A6: SOURCES AND PRECEDENCE
A7: 1. New Deal Meeting slides (PDF, 1,018 pages) — defines the population and ALL stage history.
A8: 2. Affinity export (581 records) — enrichment only. Never used to add a company.
A9: 3. Public sources — used only to fill gaps on advanced-stage companies; cited per row.
A11: Slides are the spine because Affinity is not a record of what was discussed: 103 of its
A12: 581 records were never contacted, and a January bulk import of 51 Swiss companies would
A13: distort any geographic analysis run off Affinity alone.
A15: HOW 'DISCUSSED' IS DEFINED
A16: discussed_in_new_deal_meeting = TRUE when the company name is BOLD on a meeting slide.
... A81: Data Dictionary — every field defined with its source.

Sheet Companies
A1: company_id | B1: company_name | C1: website | D1: discussed_in_new_deal_meeting | E1: discussion_dates | F1: first_discussion_date | G1: last_discussion_date | H1: times_discussed | I1: furthest_stage_on_slides | J1: date_reached_furthest_stage | K1: latest_stage_on_slides | L1: reached_prelim_diligence | M1: date_prelim_diligence | N1: reached_deep_diligence | O1: date_deep_diligence | P1: reached_negotiate_offer | Q1: date_negotiate_offer | R1: reached_legal | S1: date_legal | T1: slide_appearances | U1: first_slide_date | V1: last_slide_date | W1: working_group_final | X1: working_group_source | Y1: thesis_area_slides | Z1: stage | AA1: round_size_usd | AB1: hq_city | AC1: hq_state_province | AD1: hq_country | AE1: hq_region | AF1: affinity_status | AG1: interest | AH1: score_team | AI1: score_tech | AJ1: score_oppt | AK1: owner_name | AL1: owner_email | AM1: in_affinity | AN1: affinity_match_method | AO1: affinity_organization_id | AP1: affinity_row_id | AQ1: affinity_date_added | AR1: first_meeting | AS1: last_meeting | AT1: name_variants_on_slides | AU1: enriched_from_public | AV1: public_source | AW1: enrichment_priority | AX1: enrichment_gaps | AY1: needs_website | AZ1: needs_geography | BA1: needs_stage | BB1: needs_round_size | BC1: needs_owner | BD1: description
A2: EV0001 | B2: Bristol Superlight | C2: bristolsuperlight.com | D2: =TRUE() -> TRUE | E2: 2025-11-24; 2025-12-01; 2025-12-08; 2025-12-15; 2026-01-05; 2026-01-12; 2026-01-20; 2026-01-26; 2026-02-02; 2026-02-09; 2026-02-17; 2026-02-23; 2026-03-02; 2026-03-09; 2026-03-16; 2026-03-23; 2026-03-30; 2026-04-06; 2026-04-13; 2026-04-20; 2026-05-04; 2026-05-11; 2026-05-18 | F2: 45985 | G2: 46160 | H2: 23 | I2: Legal Diligence / Def Docs | J2: 46006 | K2: Legal Diligence / Def Docs | L2: =TRUE() -> TRUE | M2: 45957 | N2: =TRUE() -> TRUE | O2: 45985 | P2: =TRUE() -> TRUE | Q2: 45999 | R2: =TRUE() -> TRUE | S2: 46006 | T2: 27 | U2: 45957 | V2: 46160 | W2: Climate; Systems | X2: Affinity | Y2: Energy & Climate | Z2: Series A | AA2: 15000000 | AC2: England | AD2: United Kingdom | AE2: International | AF2: Invested | AG2: 1. Very High | AH2: '+++ | AI2: '+++ | AJ2: '++ | AK2: Rachel Field | AL2: rachel@engineventures.com | AM2: =TRUE() -> TRUE | AN2: name | AO2: 285295012 | AP2: 222880477 | AQ2: 10/22/2025 | AR2: 10/22/2025 | AS2: 08/14/2026 | AU2: =FALSE() -> FALSE | AW2: P4 - acceptable | AX2: 0 | AY2: =FALSE() -> FALSE | AZ2: =FALSE() -> FALSE | BA2: =FALSE() -> FALSE | BB2: =FALSE() -> FALSE | BC2: =FALSE() -> FALSE | BD2: Bristol Superlight is an automotive technology company based in Hampshire, United Kingdom, specializing in innovative logistics vehicle design. Their primary focus is developing plug-in hybrid trucks with advanced engineering features, including a lighter and stronger chassis constructed from composites and aluminum. The company employs a unique production system that enables efficient manufacturing of multiple vehicle variants, with a key emphasis on creating digital-first vehicles that reduce energy costs and optimize cargo transportation solutions for the modern logistics industry.
A3: EV0002 | B3: CorePower Magnetics | C3: corepowermagnetics.com | D3: =TRUE() -> TRUE | E3: 2025-10-14; 2025-10-20; 2025-10-27; 2025-11-03; 2025-11-10; 2026-01-26; 2026-03-09; 2026-03-16; 2026-03-23; 2026-05-04; 2026-05-11; 2026-05-18; 2026-05-26; 2026-06-01; 2026-06-08; 2026-06-15; 2026-06-22; 2026-07-06; 2026-07-13; 2026-07-20; 2026-07-27 | F3: 45944 | G3: 46230 | H3: 21 | I3: Legal Diligence / Def Docs | J3: 46153 | K3: Legal Diligence / Def Docs | L3: =TRUE() -> TRUE | M3: 46055 | N3: =TRUE() -> TRUE | O3: 45944 | P3: =TRUE() -> TRUE | Q3: 46146 | R3: =TRUE() -> TRUE | S3: 46153 | T3: 40 | U3: 45944 | V3: 46258 | W3: Climate | X3: Slide section | Y3: Energy & Climate | Z3: Series A | AB3: Pittsburgh | AC3: Pennsylvania | AD3: United States | AE3: United States | AM3: =FALSE() -> FALSE | AT3: Corepower Magnetics | AU3: 1 | AV3: Company site + CMU spinout announcement + PitchBook (founded 2020, CMU spinout); Scott Institute for Energy Innovation (CMU), Nov 2024: company was raising Series A funding, on top of a $2.5M pre-seed (2022) and non-dilutive DOE/ARPA-E grants. Current round size not confirmed in public sources. | AW3: P1 - advanced stage, incomplete | AX3: 2 | AY3: 0 | AZ3: 0 | BA3: 0 | BB3: 1 | BC3: 1
A4: EV0003 | B4: DG Matrix | C4: dgmatrix.com | D4: =TRUE() -> TRUE | E4: 2025-10-14; 2025-10-20; 2025-10-27; 2025-11-03; 2025-11-10; 2025-11-17; 2025-11-24; 2025-12-01; 2025-12-08; 2025-12-15; 2026-01-05; 2026-01-12; 2026-01-20; 2026-01-26; 2026-02-02; 2026-02-09; 2026-02-17 | F4: 45944 | G4: 46070 | H4: 17 | I4: Legal Diligence / Def Docs | J4: 45992 | K4: Legal Diligence / Def Docs | L4: =FALSE() -> FALSE | N4: =TRUE() -> TRUE | O4: 45944 | P4: =TRUE() -> TRUE | Q4: 45950 | R4: =TRUE() -> TRUE | S4: 45992 | T4: 17 | U4: 45944 | V4: 46070 | X4: MISSING | Z4: Series A | AA4: 60000000 | AB4: Morrisville | AC4: North Carolina | AD4: United States | AE4: United States | AK4: Michael Kearney | AM4: =FALSE() -> FALSE | AU4: 1 | AV4: BusinessWire 2026-02-18: $60M Series A led by Engine Ventures. NOTE: Crunchbase lists Raleigh, Tracxn lists Tempe - sources conflict, HQ per company press release; BusinessWire 2026-02-18 / Engine Ventures site: DG Matrix's $60M Series A (Feb 2026) was led by Engine Ventures, quoting Michael Kearney, General Partner -- likely deal owner, not confirmed against internal CRM. | AW4: P4 - acceptable | AX4: 0 | AY4: 0 | AZ4: 0 | BA4: 0 | BB4: 0 | BC4: 0
A5: EV0004 | B5: Alithia | C5: alithiapower.com | D5: =TRUE() -> TRUE | E5: 2026-05-11; 2026-05-26; 2026-06-01; 2026-06-08; 2026-06-15; 2026-06-22; 2026-07-06; 2026-07-13; 2026-07-20; 2026-07-27; 2026-08-24 | F5: 46153 | G5: 46258 | H5: 11 | I5: Deep Diligence | J5: 46168 | K5: Hold / Nurture | L5: =TRUE() -> TRUE | M5: 46146 | N5: =TRUE() -> TRUE | O5: 46168 | P5: =FALSE() -> FALSE | R5: =FALSE() -> FALSE | T5: 17 | U5: 46146 | V5: 46265 | W5: Systems | X5: Affinity | Y5: Autonomous Systems | Z5: Seed | AA5: 3000000 | AB5: Holly Springs | AC5: North Carolina | AD5: United States | AE5: United States | AF5: Deep Diligence | AG5: 1. Very High | AK5: Alaina Hartnett | AL5: alaina.hartnett@engineventures.com | AM5: =TRUE() -> TRUE | AN5: fuzzy | AO5: 292973343 | AP5: 238737706 | AQ5: 04/15/2026 | AR5: 04/15/2026 | AS5: 08/10/2026 | AU5: =TRUE() -> TRUE | AV5: Company site + ISES profile: Raleigh-Durham NC, founded Jan 2023, vertical GaN power electronics | AW5: P4 - acceptable | AX5: 0 | AY5: =FALSE() -> FALSE | AZ5: =FALSE() -> FALSE | BA5: =FALSE() -> FALSE | BB5: =FALSE() -> FALSE | BC5: =FALSE() -> FALSE | BD5: Alithia Power is a seed-stage technology company developing advanced vertical GaN (Gallium Nitride) power electronics for electrification markets. Founded in 2023 and based in Raleigh, NC, the company focuses on creating innovative power diodes and transistors with a compact design. Their vertiGAN™ technology aims to improve power system efficiency for electric vehicles, industrial motors, and renewable energy applications, emphasizing sustainable and high-performance power devices that can operate at high voltages with reduced reliance on traditional semiconductor chips.
A6: EV0005 | B6: Ovelle | C6: ovelle.bio | D6: =TRUE() -> TRUE | E6: 2026-02-23; 2026-03-09; 2026-03-16; 2026-03-23; 2026-03-30; 2026-04-06; 2026-04-13; 2026-04-20 | F6: 46076 | G6: 46132 | H6: 8 | I6: Legal Diligence / Def Docs | J6: 46111 | K6: Legal Diligence / Def Docs | L6: =TRUE() -> TRUE | M6: 45944 | N6: =TRUE() -> TRUE | O6: 46097 | P6: =TRUE() -> TRUE | Q6: 46104 | R6: =TRUE() -> TRUE | S6: 46111 | T6: 26 | U6: 45944 | V6: 46132 | W6: Health | X6: Affinity | Y6: Human Health | Z6: Seed | AA6: 10000000 | AB6: Boston | AC6: Massachusetts | AD6: United States | AE6: United States | AF6: Loss | AK6: Rachel Field | AL6: rachel@engineventures.com | AM6: =TRUE() -> TRUE | AN6: name | AO6: 300600234 | AP6: 218554332 | AQ6: 09/17/2025 | AR6: 09/17/2025 | AS6: 04/10/2026 | AU6: =FALSE() -> FALSE | AW6: P4 - acceptable | AX6: 0 | AY6: =FALSE() -> FALSE | AZ6: =FALSE() -> FALSE | BA6: =FALSE() -> FALSE | BB6: =FALSE() -> FALSE | BC6: =FALSE() -> FALSE | BD6: Ovelle is a pioneering biotechnology startup revolutionizing reproductive medicine through advanced in vitro gametogenesis (IVG) research. The company specializes in developing innovative fertility treatments by producing eggs from somatic cells using sophisticated computational methods and cellular manipulation techniques. Their groundbreaking approach aims to make fertility treatments more accessible, affordable, and less invasive by leveraging cutting-edge technologies like induced pluripotent stem cells and advanced genetic engineering.
A7: EV0006 | B7: Ayo Electronics | C7: ayoelectronics.com | D7: =TRUE() -> TRUE | E7: 2026-03-02; 2026-03-09; 2026-03-16; 2026-03-23; 2026-03-30; 2026-04-06 | F7: 46083 | G7: 46118 | H7: 6 | I7: Legal Diligence / Def Docs | J7: 46111 | K7: Legal Diligence / Def Docs | L7: =FALSE() -> FALSE | N7: =TRUE() -> TRUE | O7: 46083 | P7: =TRUE() -> TRUE | Q7: 46090 | R7: =TRUE() -> TRUE | S7: 46111 | T7: 6 | U7: 46083 | V7: 46118 | W7: Systems | X7: Affinity | Z7: Seed | AA7: 15000000 | AB7: Somerville | AC7: Massachusetts | AD7: United States | AE7: United States | AF7: Invested | AG7: 1. Very High | AK7: Madeleine Laitz | AL7: madeleine@engineventures.com | AM7: =TRUE() -> TRUE | AN7: domain | AO7: 290076693 | AP7: 234062557 | AQ7: 02/24/2026 | AR7: 12/06/2023 | AS7: 05/28/2026 | AU7: 1 | AV7: MassTech Northeast Microelectronics Coalition grant list (2025): Ayo Electronics Inc., Somerville, MA -- fabless semiconductor / photonic AI processor company (Pillar VC portfolio). PitchBook separately lists Arlington, MA; used the more specific, more recent source. | AW7: P4 - acceptable | AX7: 0 | AY7: 0 | AZ7: 0 | BA7: 0 | BB7: 0 | BC7: 0
A8: EV0007 | B8: Numem | C8: numem.com | D8: =TRUE() -> TRUE | E8: 2026-06-15; 2026-07-27; 2026-08-03; 2026-08-10; 2026-08-24; 2026-08-31 | F8: 46188 | G8: 46265 | H8: 6 | I8: Deep Diligence | J8: 46251 | K8: Deep Diligence | L8: =TRUE() -> TRUE | M8: 46153 | N8: =TRUE() -> TRUE | O8: 46251 | P8: =FALSE() -> FALSE | R8: =FALSE() -> FALSE | T8: 15 | U8: 46146 | V8: 46265 | W8: Systems | X8: Affinity | Y8: Autonomous Systems | Z8: Seed | AA8: 10000000 | AB8: Sunnyvale | AC8: California | AD8: United States | AE8: United States | AF8: Preliminary Diligence | AG8: 1. Very High | AK8: Alaina Hartnett | AL8: alaina.hartnett@engineventures.com | AM8: =TRUE() -> TRUE | AN8: name | AO8: 156979063 | AP8: 240451326 | AQ8: 05/06/2026 | AR8: 05/05/2026 | AS8: 08/21/2026 | AU8: =FALSE() -> FALSE | AW8: P4 - acceptable | AX8: 0 | AY8: =FALSE() -> FALSE | AZ8: =FALSE() -> FALSE | BA8: =FALSE() -> FALSE | BB8: =FALSE() -> FALSE | BC8: =FALSE() -> FALSE | BD8: Numem is a semiconductor technology company headquartered in Sunnyvale, California, specializing in advanced memory solutions based on patented NuRAM (MRAM) and SmartMem technologies. The company provides innovative SOC Subsystem IP Cores and Chiplets that offer a superior alternative to traditional SRAM and eFlash, delivering 2.5x smaller area and over 20x lower leakage power. Numem's solutions target critical technology sectors including IoT, wearables, AI/Generative AI, digital security, autonomous vehicles, and data centers, enabling customers to achieve substantial reductions in system power consumption and accelerated time to market.
A9: EV0008 | B9: Coral Innovations | C9: coral-innovations.com | D9: =TRUE() -> TRUE | E9: 2026-05-11; 2026-05-18; 2026-05-26; 2026-06-01; 2026-06-15 | F9: 46153 | G9: 46188 | H9: 5 | I9: Preliminary Diligence | J9: 46153 | K9: Preliminary Diligence | L9: =TRUE() -> TRUE | M9: 46153 | N9: =FALSE() -> FALSE | P9: =FALSE() -> FALSE | R9: =FALSE() -> FALSE | T9: 7 | U9: 46153 | V9: 46195 | W9: Climate | X9: Affinity | Y9: Energy & Climate | Z9: Seed | AA9: 4000000 | AB9: Evanston | AC9: Illinois | AD9: United States | AE9: United States | AF9: Pass | AG9: 2. High | AK9: Rachel Field | AL9: rachel@engineventures.com | AM9: =TRUE() -> TRUE | AN9: name | AO9: 301369744 | AP9: 240387693 | AQ9: 05/05/2026 | AR9: 05/05/2026 | AS9: 05/22/2026 | AU9: =FALSE() -> FALSE | AW9: P4 - acceptable | AX9: 0 | AY9: =FALSE() -> FALSE | AZ9: =FALSE() -> FALSE | BA9: =FALSE() -> FALSE | BB9: =FALSE() -> FALSE | BC9: =FALSE() -> FALSE | BD9: Coral Innovations is a nanotechnology company focused on developing sustainable environmental solutions, with a primary emphasis on water remediation and protection. Utilizing breakthrough research in nanotechnology, the company creates advanced solutions for clean water access, including portable water-quality testing units and specialized filtration materials. Their mission is to address environmental challenges by providing innovative, scalable technologies that help communities improve water quality, reduce environmental harm, and support long-term sustainability.
A10: EV0009 | B10: MatNex | C10: matnex.ai | D10: =TRUE() -> TRUE | E10: 2026-07-20; 2026-08-10; 2026-08-17; 2026-08-24; 2026-08-31 | F10: 46223 | G10: 46265 | H10: 5 | I10: Deep Diligence | J10: 46251 | K10: Deep Diligence | L10: =TRUE() -> TRUE | M10: 46216 | N10: =TRUE() -> TRUE | O10: 46251 | P10: =FALSE() -> FALSE | R10: =FALSE() -> FALSE | T10: 8 | U10: 46216 | V10: 46265 | W10: Climate; Systems | X10: Affinity | Y10: AI for Science | Z10: Series A | AA10: 20000000 | AB10: Cambridge | AC10: England | AD10: United Kingdom | AE10: International | AF10: Preliminary Diligence | AG10: 1. Very High | AK10: Alaina Hartnett | AL10: alaina.hartnett@engineventures.com | AM10: =TRUE() -> TRUE | AN10: name | AO10: 300461005 | AP10: 246051999 | AQ10: 07/08/2026 | AR10: 08/13/2026 | AS10: 08/13/2026 | AU10: =FALSE() -> FALSE | AW10: P4 - acceptable | AX10: 0 | AY10: =FALSE() -> FALSE | AZ10: =FALSE() -> FALSE | BA10: =FALSE() -> FALSE | BB10: =FALSE() -> FALSE | BC10: =FALSE() -> FALSE | BD10: Matnex is an AI-driven platform specializing in accelerating materials discovery and development with a focus on low-carbon solutions. Using advanced quantum calculations and automated processes, the company works with partners to dramatically reduce the time for discovering next-generation materials from decades to months. Their core mission is to discover new materials that can significantly reduce environmental, economic, and social costs, with a particular emphasis on lowering global CO2 emissions through innovative technological approaches.
A11: EV0010 | B11: Skouria | C11: skouria.com | D11: =TRUE() -> TRUE | E11: 2025-12-15; 2026-01-12; 2026-01-20; 2026-01-26; 2026-02-02 | F11: 46006 | G11: 46055 | H11: 5 | I11: Deep Diligence | J11: 46027 | K11: Deep Diligence | L11: =TRUE() -> TRUE | M11: 45964 | N11: =TRUE() -> TRUE | O11: 46027 | P11: =FALSE() -> FALSE | R11: =FALSE() -> FALSE | T11: 22 | U11: 45957 | V11: 46118 | W11: Climate | X11: Affinity | Y11: Energy & Climate | Z11: Seed | AA11: 7000000 | AB11: Philadelphia | AC11: Pennsylvania | AD11: United States | AE11: United States | AF11: Wait | AG11: 1. Very High | AH11: '++ | AI11: '+++ | AJ11: '+++ | AK11: Alaina Hartnett | AL11: alaina.hartnett@engineventures.com | AM11: =TRUE() -> TRUE | AN11: name | AO11: 296667487 | AP11: 223105565 | AQ11: 10/24/2025 | AR11: 10/28/2025 | AS11: 03/19/2026 | AU11: =FALSE() -> FALSE | AW11: P4 - acceptable | AX11: 0 | AY11: =FALSE() -> FALSE | AZ11: =FALSE() -> FALSE | BA11: =FALSE() -> FALSE | BB11: =FALSE() -> FALSE | BC11: =FALSE() -> FALSE | BD11: Skouria is a mining technology company specializing in innovative copper extraction through Deep Brine Mining (DBM), an advanced process designed to reduce environmental impact and capital costs. The company focuses on enhancing the permeability of hydrothermal systems using geothermal and metallurgical technologies to create a more sustainable copper production model. Their approach aims to optimize copper extraction while minimizing fossil fuel dependency and environmental disruption, offering consulting services to help governments and companies navigate complex copper industry challenges.
A12: EV0011 | B12: Teragen | C12: teragenenergy.com | D12: =TRUE() -> TRUE | E12: 2025-11-03; 2025-11-10; 2025-11-17; 2025-11-24; 2025-12-01 | F12: 45964 | G12: 45992 | H12: 5 | I12: Deep Diligence | J12: 45978 | K12: Meetings This Week | L12: =TRUE() -> TRUE | M12: 45944 | N12: =TRUE() -> TRUE | O12: 45978 | P12: =FALSE() -> FALSE | R12: =FALSE() -> FALSE | T12: 17 | U12: 45944 | V12: 46265 | W12: Climate | X12: Slide section | Y12: Energy & Climate | Z12: Preseed | AA12: 6000000 | AB12: Boston | AC12: Massachusetts | AD12: United States | AE12: United States | AM12: =FALSE() -> FALSE | AU12: 1 | AV12: Teragen Energy - Boston-based; $6M oversubscribed pre-seed (Aug 2026), co-led by BEVC and Energy Capital Ventures, participation incl. MassCEC. PR Newswire 2026-08-26. Spun out of Lawrence Berkeley National Lab per The Engine profile. Name match only -- not cross-checked against internal deal records; confirm before quoting externally. | AW12: P1 - advanced stage, incomplete | AX12: 1 | AY12: 0 | AZ12: 0 | BA12: 0 | BB12: 0 | BC12: 1
A13: EV0012 | B13: Axiomatic AI | C13: axiomatic-ai.com | D13: =TRUE() -> TRUE | E13: 2025-11-24; 2025-12-01; 2025-12-08; 2025-12-15 | F13: 45985 | G13: 46006 | H13: 4 | I13: Legal Diligence / Def Docs | J13: 46006 | K13: Meetings This Week | L13: =TRUE() -> TRUE | M13: 45971 | N13: =FALSE() -> FALSE | P13: =FALSE() -> FALSE | R13: =TRUE() -> TRUE | S13: 46006 | T13: 6 | U13: 45971 | V13: 46006 | W13: Systems | X13: Affinity | Y13: Autonomous Systems | Z13: Seed | AA13: 10000000 | AB13: Boston | AC13: Massachusetts | AD13: United States | AE13: United States | AF13: Invested | AG13: 1. Very High | AK13: Madeleine Laitz | AL13: madeleine@engineventures.com | AM13: =TRUE() -> TRUE | AN13: name | AO13: 294871569 | AP13: 224903165 | AQ13: 11/12/2025 | AR13: 05/15/2025 | AS13: 08/26/2026 | AU13: =FALSE() -> FALSE | AW13: P4 - acceptable | AX13: 0 | AY13: =FALSE() -> FALSE | AZ13: =FALSE() -> FALSE | BA13: =FALSE() -> FALSE | BB13: =FALSE() -> FALSE | BC13: =FALSE() -> FALSE | BD13: Axiomatic AI is an advanced artificial intelligence platform focused on accelerating research and development in science and engineering. The company aims to achieve Mission 10X30 by developing an AI-driven engineering tool that reduces technical challenge resolution time. Their unique approach combines formal verification with deep learning to create transparent, interpretable AI models for technical applications, particularly in photonics and semiconductor hardware development. The platform generates physics-based models, extracts technical documentation data, and provides automated design verification to minimize errors and improve technology development speed.
A14: EV0013 | B14: DINYA | C14: dinyadna.com | D14: =TRUE() -> TRUE | E14: 2025-10-14; 2025-10-27; 2025-11-03; 2025-11-10 | F14: 45944 | G14: 45971 | H14: 4 | I14: Deep Diligence | J14: 45957 | K14: Deep Diligence | L14: =TRUE() -> TRUE | M14: 45944 | N14: =TRUE() -> TRUE | O14: 45957 | P14: =FALSE() -> FALSE | R14: =FALSE() -> FALSE | T14: 5 | U14: 45944 | V14: 45971 | W14: Health | X14: Affinity | Y14: Human Health | Z14: Seed | AA14: 5000000 | AB14: Cambridge | AC14: Massachusetts | AD14: United States | AE14: United States | AF14: Pass | AK14: Deepa Rao | AL14: deepa@engineventures.com | AM14: =TRUE() -> TRUE | AN14: name | AO14: 293388830 | AP14: 218051781 | AQ14: 09/10/2025 | AR14: 11/20/2023 | AS14: 10/09/2025 | AU14: =FALSE() -> FALSE | AW14: P4 - acceptable | AX14: 0 | AY14: =FALSE() -> FALSE | AZ14: =FALSE() -> FALSE | BA14: =FALSE() -> FALSE | BB14: =FALSE() -> FALSE | BC14: =FALSE() -> FALSE | BD14: DINYA DNA is a biotechnology company specializing in enzymatic DNA synthesis, focusing on delivering complex and custom DNA sequences on-demand. The company enables scientific research by providing gene-length DNA quickly and affordably, supporting researchers in developing new scientific breakthroughs. Their technology allows for the creation of gene variant libraries and offers early access programs for potential research initiatives, ultimately accelerating research and development processes across various scientific fields.
A15: EV0014 | B15: Valor | D15: =TRUE() -> TRUE | E15: 2025-10-14; 2025-10-20; 2025-10-27; 2025-11-03 | F15: 45944 | G15: 45964 | H15: 4 | I15: Deep Diligence | J15: 45944 | K15: Deep Diligence | L15: =FALSE() -> FALSE | N15: =TRUE() -> TRUE | O15: 45944 | P15: =FALSE() -> FALSE | R15: =FALSE() -> FALSE | T15: 4 | U15: 45944 | V15: 45964 | W15: Climate | X15: Affinity | Z15: Seed | AA15: 10000000 | AE15: UNKNOWN | AF15: Loss | AG15: 1. Very High | AH15: '+++ | AI15: '+++ | AJ15: '+++ | AK15: Deepa Rao | AL15: deepa@engineventures.com | AM15: =TRUE() -> TRUE | AN15: name | AO15: 306041385 | AP15: 218669372 | AQ15: 09/17/2025 | AR15: 08/17/2023 | AS15: 04/03/2025 | AU15: =FALSE() -> FALSE | AW15: P1 - advanced stage, incomplete | AX15: 2 | AY15: =TRUE() -> TRUE | AZ15: =TRUE() -> TRUE | BA15: =FALSE() -> FALSE | BB15: =FALSE() -> FALSE | BC15: =FALSE() -> FALSE
A16: EV0015 | B16: Walden Robotics | C16: waldenrobotics.com | D16: =TRUE() -> TRUE | E16: 2026-05-11; 2026-05-18; 2026-05-26; 2026-06-01 | F16: 46153 | G16: 46174 | H16: 4 | I16: Preliminary Diligence | J16: 46146 | K16: Preliminary Diligence | L16: =TRUE() -> TRUE | M16: 46146 | N16: =FALSE() -> FALSE | P16: =FALSE() -> FALSE | R16: =FALSE() -> FALSE | T16: 5 | U16: 46146 | V16: 46174 | W16: Systems | X16: Affinity | Y16: Autonomous Systems | Z16: Series A | AA16: 250000000 | AB16: Cambridge | AC16: Massachusetts | AD16: United States | AE16: United States | AF16: Pass | AG16: 2. High | AK16: Rachel Field | AL16: rachel@engineventures.com | AM16: =TRUE() -> TRUE | AN16: name | AO16: 311096645 | AP16: 239805739 | AQ16: 04/28/2026 | AR16: 06/02/2026 | AS16: 06/02/2026 | AU16: =FALSE() -> FALSE | AW16: P4 - acceptable | AX16: 0 | AY16: =FALSE() -> FALSE | AZ16: =FALSE() -> FALSE | BA16: =FALSE() -> FALSE | BB16: =FALSE() -> FALSE | BC16: =FALSE() -> FALSE | BD16: we're a full-stack physical ai company building and deploying general-purpose robots that put human ingenuity to work at industrial scale. our robots continuously learn and improve while performing real work, today. and we are working toward a future where ai and robotics expand human potential and improve quality of life for everyone. founded in 2026 by pioneers in robotics and ai from toyota research institute, mit, stanford, and amazon, walden combines large behavior models with real-world operation and its own expert teams to bring capable robots to industry today.
A17: EV0016 | B17: Mattiq | C17: mattiq.com | D17: =TRUE() -> TRUE | E17: 2026-06-01; 2026-06-15; 2026-07-13 | F17: 46174 | G17: 46216 | H17: 3 | I17: Preliminary Diligence | J17: 46160 | K17: Preliminary Diligence | L17: =TRUE() -> TRUE | M17: 46160 | N17: =FALSE() -> FALSE | P17: =FALSE() -> FALSE | R17: =FALSE() -> FALSE | T17: 10 | U17: 46160 | V17: 46230 | W17: Systems | X17: Affinity | Y17: AI for Science | Z17: Seed | AA17: 10000000 | AB17: Chicago | AC17: Illinois | AD17: United States | AE17: United States | AF17: Preliminary Diligence | AG17: 5. Propose Pass | AK17: Alaina Hartnett | AL17: alaina.hartnett@engineventures.com | AM17: =TRUE() -> TRUE | AN17: name | AO17: 289307172 | AP17: 243153771 | AQ17: 06/12/2026 | AR17: 05/12/2026 | AS17: 08/03/2026 | AU17: =FALSE() -> FALSE | AW17: P4 - acceptable | AX17: 0 | AY17: =FALSE() -> FALSE | AZ17: =FALSE() -> FALSE | BA17: =FALSE() -> FALSE | BB17: =FALSE() -> FALSE | BC17: =FALSE() -> FALSE | BD17: Mattiq is an advanced clean chemistry company that leverages materials science and artificial intelligence to develop innovative electrochemical solutions for decarbonization. The company focuses on reinventing chemical process development to produce sustainable chemicals, fuels, and plastics. By utilizing AI and advanced technologies, Mattiq designs commercially viable, scalable processes that support supply chain resilience and environmental sustainability, with a particular emphasis on eliminating fossil fuel dependence in industrial chemical and energy sectors.
A18: EV0017 | B18: Attune Neurosci | C18: attuneneuro.com | D18: =TRUE() -> TRUE | E18: 2026-02-02; 2026-02-09 | F18: 46055 | G18: 46062 | H18: 2 | I18: Deep Diligence | J18: 46062 | K18: Deep Diligence | L18: =TRUE() -> TRUE | M18: 46006 | N18: =TRUE() -> TRUE | O18: 46062 | P18: =FALSE() -> FALSE | R18: =FALSE() -> FALSE | T18: 13 | U18: 45971 | V18: 46097 | W18: Health | X18: Affinity | Y18: Human Health | Z18: Series A | AA18: 20000000 | AB18: San Francisco | AC18: California | AD18: United States | AE18: United States | AF18: Pass | AK18: Rachel Field | AL18: rachel@engineventures.com | AM18: =TRUE() -> TRUE | AN18: fuzzy | AO18: 268186783 | AP18: 233316922 | AQ18: 02/12/2026 | AR18: 11/14/2025 | AS18: 03/27/2026 | AT18: Attune | AU18: 0 | AW18: P4 - acceptable | AX18: 0 | AY18: 0 | AZ18: 0 | BA18: 0 | BB18: 0 | BC18: 0 | BD18: Attune Neurosciences is a clinical-stage medical device company dedicated to improving human health and performance through non-invasive neurostimulation technologies. The company specializes in developing innovative neurological solutions, with a primary focus on low-intensity focused ultrasound targeting brain activity. Their research aims to enhance cognitive function and address conditions related to sleep, mental health, and overall performance. Attune Neurosciences develops clinically-proven products for patient, government, and industrial applications, seeking to provide cutting-edge neurological interventions without pharmaceutical approaches.
A19: EV0018 | B19: Cetos Water | C19: cetoswater.com | D19: =TRUE() -> TRUE | E19: 2026-05-26; 2026-06-01 | F19: 46168 | G19: 46174 | H19: 2 | I19: Preliminary Diligence | J19: 46062 | K19: Preliminary Diligence | L19: =TRUE() -> TRUE | M19: 46062 | N19: =FALSE() -> FALSE | P19: =FALSE() -> FALSE | R19: =FALSE() -> FALSE | T19: 19 | U19: 46055 | V19: 46265 | W19: Climate | X19: Affinity | Y19: Energy & Climate | Z19: Seed | AA19: 7000000 | AB19: New York | AC19: New York | AD19: United States | AE19: United States | AF19: Preliminary Diligence | AG19: 2. High | AK19: Alaina Hartnett | AL19: alaina.hartnett@engineventures.com | AM19: =TRUE() -> TRUE | AN19: name | AO19: 310756116 | AP19: 232338029 | AQ19: 02/03/2026 | AR19: 02/03/2026 | AS19: 08/05/2026 | AT19: Cetos Water / Kira; Water: Cetos Water / Kira | AU19: 0 | AW19: P4 - acceptable | AX19: 0 | AY19: 0 | AZ19: 0 | BA19: 0 | BB19: 0 | BC19: 0 | BD19: Cetos Water is an innovative water treatment technology company specializing in advanced desalination solutions for high-salinity wastewater streams. Their membrane-less and non-evaporative solvent technology can process water up to 10x more concentrated than seawater, enabling efficient treatment of complex industrial wastewater. The company serves multiple industries including lithium production, desalination plants, thermoelectric power, mining, and geothermal energy, with a mission to transform wastewater from an environmental challenge into a sustainable freshwater solution. Their technology supports customizable water recovery outcomes, including Zero Liquid Discharge (ZLD), addressing the critical issue of untreated wastewater discharge while providing cost-effective and energy-efficient water reclamation.
A20: EV0019 | B20: CloverLeaf | C20: cloverleafbio.com | D20: =TRUE() -> TRUE | E20: 2025-12-08; 2025-12-15 | F20: 45999 | G20: 46006 | H20: 2 | I20: Deep Diligence | J20: 46006 | K20: Deep Diligence | L20: =TRUE() -> TRUE | M20: 45978 | N20: =TRUE() -> TRUE | O20: 46006 | P20: =FALSE() -> FALSE | R20: =FALSE() -> FALSE | T20: 7 | U20: 45978 | V20: 46034 | W20: Health | X20: Affinity | Y20: Human Health | Z20: Seed | AA20: 12000000 | AB20: New Haven | AC20: Connecticut | AD20: United States | AE20: United States | AF20: Pass | AG20: 1. Very High | AK20: Dan Resnicow | AL20: dan@engineventures.com | AM20: =TRUE() -> TRUE | AN20: fuzzy | AO20: 291510341 | AP20: 230900570 | AQ20: 12/15/2025 | AR20: 10/30/2025 | AS20: 12/19/2025 | AU20: =FALSE() -> FALSE | AW20: P4 - acceptable | AX20: 0 | AY20: =FALSE() -> FALSE | AZ20: =FALSE() -> FALSE | BA20: =FALSE() -> FALSE | BB20: =FALSE() -> FALSE | BC20: =FALSE() -> FALSE | BD20: Cloverleaf Bio is a biotechnology company developing innovative RNA therapeutics focused on oncology treatment. The company is pioneering a platform that creates engineered RNA therapeutic molecules capable of targeting multiple enzymes critical to cancer growth. By developing a single therapeutic molecule that can inhibit up to 25 key enzymes, Cloverleaf aims to revolutionize cancer therapy and improve patient outcomes through advanced RNA therapeutic approaches.
A21: EV0020 | B21: 1AU | C21: 1autechnologies.com | D21: =TRUE() -> TRUE | E21: 2026-04-06 | F21: 46118 | G21: 46118 | H21: 1 | I21: Preliminary Diligence | J21: 46076 | K21: Preliminary Diligence | L21: =TRUE() -> TRUE | M21: 46076 | N21: =FALSE() -> FALSE | P21: =FALSE() -> FALSE | R21: =FALSE() -> FALSE | T21: 8 | U21: 46070 | V21: 46118 | W21: Systems | X21: Slide section | Y21: Autonomous Systems | AE21: UNKNOWN | AM21: =FALSE() -> FALSE | AU21: =FALSE() -> FALSE | AW21: P1 - discussed, incomplete | AX21: 5 | AY21: =TRUE() -> TRUE | AZ21: =TRUE() -> TRUE | BA21: =TRUE() -> TRUE | BB21: =TRUE() -> TRUE | BC21: =TRUE() -> TRUE
A22: EV0021 | B22: Blisk Dynamics | C22: bliskdynamics.com | D22: =TRUE() -> TRUE | E22: 2026-08-17 | F22: 46251 | G22: 46251 | H22: 1 | I22: Preliminary Diligence | J22: 46251 | K22: Preliminary Diligence | L22: =TRUE() -> TRUE | M22: 46251 | N22: =FALSE() -> FALSE | P22: =FALSE() -> FALSE | R22: =FALSE() -> FALSE | T22: 1 | U22: 46251 | V22: 46251 | W22: Systems; Climate | X22: Affinity | Y22: Autonomous Systems | Z22: Seed | AA22: 10000000 | AE22: UNKNOWN | AF22: Pass | AG22: 2. High | AK22: Rachel Field | AL22: rachel@engineventures.com | AM22: =TRUE() -> TRUE | AN22: name | AO22: 313497404 | AP22: 249444278 | AQ22: 08/12/2026 | AR22: 08/12/2026 | AS22: 08/18/2026 | AU22: =FALSE() -> FALSE | AW22: P1 - discussed, incomplete | AX22: 1 | AY22: =FALSE() -> FALSE | AZ22: =TRUE() -> TRUE | BA22: =FALSE() -> FALSE | BB22: =FALSE() -> FALSE | BC22: =FALSE() -> FALSE
A23: EV0022 | B23: Daedalus | C23: daedalus.de | D23: =TRUE() -> TRUE | E23: 2026-06-22 | F23: 46195 | G23: 46195 | H23: 1 | I23: Preliminary Diligence | J23: 46195 | K23: Preliminary Diligence | L23: =TRUE() -> TRUE | M23: 46195 | N23: =FALSE() -> FALSE | P23: =FALSE() -> FALSE | R23: =FALSE() -> FALSE | T23: 1 | U23: 46195 | V23: 46195 | W23: Systems | X23: Affinity | Y23: Autonomous Systems | Z23: Series B | AA23: 15000000 | AB23: San Francisco | AC23: California | AD23: United States | AE23: United States | AF23: Pass | AG23: 2. High | AK23: Vinny Beranek | AL23: vinny@engineventures.com | AM23: =TRUE() -> TRUE | AN23: name | AO23: 224087181 | AP23: 243429947 | AQ23: 06/17/2026 | AR23: 05/29/2026 | AS23: 06/10/2026 | AU23: =FALSE() -> FALSE | AW23: P4 - acceptable | AX23: 0 | AY23: =FALSE() -> FALSE | AZ23: =FALSE() -> FALSE | BA23: =FALSE() -> FALSE | BB23: =FALSE() -> FALSE | BC23: =FALSE() -> FALSE | BD23: Daedalus is an advanced manufacturing technology company developing software-defined, reconfigurable factories for precision component production. Backed by prominent venture capital firms including Khosla Ventures and Y Combinator, they leverage robotics and AI to enable agile manufacturing across various industries such as machinery, aerospace, semiconductor, and energy. Their approach emphasizes real-time production control, high-precision manufacturing, and the ability to rapidly retool for different part complexities, with a goal of creating more flexible, efficient, and sustainable industrial production capabilities.
A24: EV0023 | B24: El Agente | D24: =TRUE() -> TRUE | E24: 2026-02-02 | F24: 46055 | G24: 46055 | H24: 1 | I24: Preliminary Diligence | J24: 46055 | K24: Hold / Nurture | L24: =TRUE() -> TRUE | M24: 46055 | N24: =FALSE() -> FALSE | P24: =FALSE() -> FALSE | R24: =FALSE() -> FALSE | T24: 24 | U24: 46048 | V24: 46230 | W24: Systems | X24: Affinity | Y24: Autonomous Systems | Z24: Seed | AA24: 20000000 | AE24: UNKNOWN | AF24: Wait | AG24: 2. High | AH24: '+++ | AK24: Madeleine Laitz | AL24: madeleine@engineventures.com | AM24: =TRUE() -> TRUE | AN24: name | AO24: 310577715 | AP24: 231975755 | AQ24: 01/29/2026 | AU24: =FALSE() -> FALSE | AW24: P1 - discussed, incomplete | AX24: 2 | AY24: =TRUE() -> TRUE | AZ24: =TRUE() -> TRUE | BA24: =FALSE() -> FALSE | BB24: =FALSE() -> FALSE | BC24: =FALSE() -> FALSE
A25: EV0024 | B25: ExploreTech | C25: exploretech.ai | D25: =TRUE() -> TRUE | E25: 2026-07-27 | F25: 46230 | G25: 46230 | H25: 1 | I25: Preliminary Diligence | J25: 46209 | K25: Preliminary Diligence | L25: =TRUE() -> TRUE | M25: 46209 | N25: =FALSE() -> FALSE | P25: =FALSE() -> FALSE | R25: =FALSE() -> FALSE | T25: 8 | U25: 46209 | V25: 46258 | W25: Climate | X25: Affinity | Y25: Energy & Climate | Z25: Seed | AA25: 8000000 | AB25: San Diego | AC25: California | AD25: United States | AE25: United States | AF25: Preliminary Diligence | AG25: 3. Moderate | AK25: Alaina Hartnett | AL25: alaina.hartnett@engineventures.com | AM25: =TRUE() -> TRUE | AN25: name | AO25: 291146636 | AP25: 245020597 | AQ25: 06/26/2026 | AR25: 12/09/2025 | AS25: 07/10/2026 | AU25: =FALSE() -> FALSE | AW25: P4 - acceptable | AX25: 0 | AY25: =FALSE() -> FALSE | AZ25: =FALSE() -> FALSE | BA25: =FALSE() -> FALSE | BB25: =FALSE() -> FALSE | BC25: =FALSE() -> FALSE | BD25: ExploreTech is a technology company specializing in accelerating mineral exploration through advanced computational methods. Using a combination of geophysics, geology, and cutting-edge computing technologies, the company develops algorithms that dramatically speed up mineral discovery processes. Their innovative approach leverages real-time data streams, satellite imagery, and computational modeling to enhance exploration efficiency, providing integrated hardware and software solutions that can reduce exploration timelines from years to months.
A26: EV0025 | B26: Flume | C26: flumeinternet.com | D26: =TRUE() -> TRUE | E26: 2026-03-30 | F26: 46111 | G26: 46111 | H26: 1 | I26: Preliminary Diligence | J26: 46111 | K26: Preliminary Diligence | L26: =TRUE() -> TRUE | M26: 46111 | N26: =FALSE() -> FALSE | P26: =FALSE() -> FALSE | R26: =FALSE() -> FALSE | T26: 1 | U26: 46111 | V26: 46111 | W26: Systems | X26: Affinity | Y26: Autonomous Systems | Z26: Series A | AA26: 15000000 | AB26: New York | AC26: New York | AD26: United States | AE26: United States | AF26: Pass | AG26: 1. Very High | AK26: Madeleine Laitz | AL26: madeleine@engineventures.com | AM26: =TRUE() -> TRUE | AN26: name | AO26: 263318060 | AP26: 237720127 | AQ26: 04/01/2026 | AR26: 06/13/2018 | AS26: 04/03/2026 | AU26: =FALSE() -> FALSE | AW26: P4 - acceptable | AX26: 0 | AY26: =FALSE() -> FALSE | AZ26: =FALSE() -> FALSE | BA26: =FALSE() -> FALSE | BB26: =FALSE() -> FALSE | BC26: =FALSE() -> FALSE | BD26: Flume is an asset-light fiber internet service provider focused on expanding broadband connectivity across the United States. The company specializes in providing multi-gigabit internet services to residential multifamily properties and small municipalities, leveraging under-utilized data centers and fiber infrastructure. With internet speeds ranging from 200 Mb/s to 10 Gb/s, Flume offers reliable connectivity, free installation, and proactive customer support. The company has rapidly grown its install base and aims to serve over 65,000 homes, targeting both residential and enterprise customers with a lean operational approach.
A27: EV0027 | B27: Human Bio | C27: humanbio.tech | D27: =TRUE() -> TRUE | E27: 2026-01-26 | F27: 46048 | G27: 46048 | H27: 1 | I27: Preliminary Diligence | J27: 46042 | K27: Preliminary Diligence | L27: =TRUE() -> TRUE | M27: 46042 | N27: =FALSE() -> FALSE | P27: =FALSE() -> FALSE | R27: =FALSE() -> FALSE | T27: 3 | U27: 46042 | V27: 46055 | W27: Health | X27: Affinity | Y27: Human Health | Z27: Preseed | AA27: 12000000 | AE27: UNKNOWN | AF27: Pass | AK27: Vinny Beranek | AL27: vinny@engineventures.com | AM27: =TRUE() -> TRUE | AN27: name | AO27: 310154725 | AP27: 231875973 | AQ27: 01/28/2026 | AR27: 01/16/2026 | AS27: 02/05/2026 | AU27: =FALSE() -> FALSE | AW27: P1 - discussed, incomplete | AX27: 1 | AY27: =FALSE() -> FALSE | AZ27: =TRUE() -> TRUE | BA27: =FALSE() -> FALSE | BB27: =FALSE() -> FALSE | BC27: =FALSE() -> FALSE | BD27: Developing new drugs for approved targets in novel, de-risked lead indications (“first-in-indication”), guided by human real-world data and genetics
A28: EV0028 | B28: Lila Sciences | C28: lila.ai | D28: =TRUE() -> TRUE | E28: 2026-03-02 | F28: 46083 | G28: 46083 | H28: 1 | I28: Deep Diligence | J28: 46083 | K28: Deep Diligence | L28: =TRUE() -> TRUE | M28: 45957 | N28: =TRUE() -> TRUE | O28: 46083 | P28: =FALSE() -> FALSE | R28: =FALSE() -> FALSE | T28: 4 | U28: 45957 | V28: 46083 | W28: Health | X28: Slide section | Y28: Human Health | Z28: Series B | AA28: 2000000000 | AB28: Cambridge | AC28: Massachusetts | AD28: United States | AE28: United States | AM28: =FALSE() -> FALSE | AU28: 1 | AV28: PitchBook / FinSMEs 2026-06: Cambridge MA, $550M raised to date; Bloomberg 2026-06-03: reported in talks for ~$2B Series B at ~$8.5B pre-money valuation (NOT confirmed closed as of last public reporting); prior $350M Series A closed 2026-06-04 (FinSMEs). | AW28: P1 - advanced stage, incomplete | AX28: 1 | AY28: 0 | AZ28: 0 | BA28: 0 | BB28: 0 | BC28: 1
A29: EV0029 | B29: Micrographia Bio | C29: micrographiabio.com | D29: =TRUE() -> TRUE | E29: 2025-11-03 | F29: 45964 | G29: 45964 | H29: 1 | I29: Preliminary Diligence | J29: 45957 | K29: Preliminary Diligence | L29: =TRUE() -> TRUE | M29: 45957 | N29: =FALSE() -> FALSE | P29: =FALSE() -> FALSE | R29: =FALSE() -> FALSE | T29: 8 | U29: 45957 | V29: 46006 | W29: Systems | X29: Affinity | Y29: Human Health | Z29: Seed | AB29: London | AC29: England | AD29: United Kingdom | AE29: International | AF29: Initial Evaluation | AM29: =TRUE() -> TRUE | AN29: name | AO29: 262788047 | AP29: 230015200 | AQ29: 01/08/2026 | AR29: 10/22/2025 | AS29: 11/13/2025 | AU29: 1 | AV29: Tracxn / PitchBook / Dealroom (2026): Seed-stage financing history, ~$7.8-8.0M total raised across 3 seed rounds since 2020; no Series A reported. London, UK confirmed (already on file). | AW29: P1 - discussed, incomplete | AX29: 2 | AY29: 0 | AZ29: 0 | BA29: 0 | BB29: 1 | BC29: 1 | BD29: Micrographia Bio is a life sciences company pioneering innovative drug discovery technologies through spatial proteomics. The company has developed a unique platform that combines advanced microscopy imaging with machine-intelligent computer vision to autonomously assess therapeutic mechanisms of action. By visualizing protein-protein networks in cells, their technology aims to accelerate and improve the efficiency of drug development, providing detailed insights into cellular pathways and potentially enabling faster, more accurate therapies for various diseases.
A30: EV0030 | B30: Origins AI | D30: =TRUE() -> TRUE | E30: 2026-08-03 | F30: 46237 | G30: 46237 | H30: 1 | I30: Preliminary Diligence | J30: 46237 | K30: Preliminary Diligence | L30: =TRUE() -> TRUE | M30: 46237 | N30: =FALSE() -> FALSE | P30: =FALSE() -> FALSE | R30: =FALSE() -> FALSE | T30: 1 | U30: 46237 | V30: 46237 | W30: Systems | X30: Affinity | Y30: AI for Science | Z30: Seed | AA30: 15000000 | AE30: UNKNOWN | AF30: Preliminary Diligence | AG30: 4. Low | AK30: Richard Collins | AL30: richard@engineventures.com | AM30: =TRUE() -> TRUE | AN30: name | AO30: 313514967 | AP30: 248367014 | AQ30: 07/31/2026 | AU30: =FALSE() -> FALSE | AW30: P1 - discussed, incomplete | AX30: 2 | AY30: =TRUE() -> TRUE | AZ30: =TRUE() -> TRUE | BA30: =FALSE() -> FALSE | BB30: =FALSE() -> FALSE | BC30: =FALSE() -> FALSE
A31: EV0031 | B31: Oxipital AI | C31: oxipitalai.com | D31: =TRUE() -> TRUE | E31: 2026-04-06 | F31: 46118 | G31: 46118 | H31: 1 | I31: Preliminary Diligence | J31: 46118 | K31: Preliminary Diligence | L31: =TRUE() -> TRUE | M31: 46118 | N31: =FALSE() -> FALSE | P31: =FALSE() -> FALSE | R31: =FALSE() -> FALSE | T31: 1 | U31: 46118 | V31: 46118 | W31: Systems | X31: Affinity | Y31: Autonomous Systems | Z31: Series A | AA31: 6000000 | AB31: Bedford | AC31: Massachusetts | AD31: United States | AE31: United States | AF31: Pass | AG31: 3. Moderate | AK31: Madeleine Laitz | AL31: madeleine@engineventures.com | AM31: =TRUE() -> TRUE | AN31: domain | AO31: 297882448 | AP31: 237790190 | AQ31: 04/02/2026 | AR31: 04/07/2020 | AS31: 03/31/2026 | AU31: =FALSE() -> FALSE | AW31: P4 - acceptable | AX31: 0 | AY31: =FALSE() -> FALSE | AZ31: =FALSE() -> FALSE | BA31: =FALSE() -> FALSE | BB31: =FALSE() -> FALSE | BC31: =FALSE() -> FALSE | BD31: Oxipital AI is a technology company specializing in AI-enabled machine vision solutions for robotic process automation and product inspection across critical industries including food processing, agriculture, and consumer goods production. Their platform delivers advanced visual AI technologies that enable no-code deployment of intelligent inspection systems, allowing manufacturers to automate quality control processes, monitor product characteristics in real-time, and perform automated pick and place inspections. The company focuses on enhancing manufacturing efficiency, sustainability, and operational resilience by providing actionable insights through deep object understanding and advanced visual technology.
A32: EV0032 | B32: PHNX Materials | C32: phnxmaterials.com | D32: =TRUE() -> TRUE | E32: 2025-10-27 | F32: 45957 | G32: 45957 | H32: 1 | I32: Preliminary Diligence | J32: 45944 | K32: Preliminary Diligence | L32: =TRUE() -> TRUE | M32: 45944 | N32: =FALSE() -> FALSE | P32: =FALSE() -> FALSE | R32: =FALSE() -> FALSE | T32: 4 | U32: 45944 | V32: 45964 | W32: Climate | X32: Affinity | Y32: Energy & Climate | Z32: Seed | AA32: 6000000 | AB32: San Francisco | AC32: California | AD32: United States | AE32: United States | AF32: Wait | AG32: 2. High | AK32: Deepa Rao | AL32: deepa@engineventures.com | AM32: =TRUE() -> TRUE | AN32: name | AO32: 300391587 | AP32: 220885034 | AQ32: 10/08/2025 | AR32: 10/08/2025 | AS32: 10/29/2025 | AU32: =FALSE() -> FALSE | AW32: P4 - acceptable | AX32: 0 | AY32: =FALSE() -> FALSE | AZ32: =FALSE() -> FALSE | BA32: =FALSE() -> FALSE | BB32: =FALSE() -> FALSE | BC32: =FALSE() -> FALSE | BD32: PHNX Materials is an industrial technology company that transforms landfilled coal ash into sustainable, high-performance materials using proprietary chemistry-driven processes. The company addresses the 2.9 billion tons of coal ash waste in U.S. landfills by reclaiming, refining, and reinventing it into valuable industrial inputs including ASTM-grade fly ash for concrete strengthening, strategic metals like aluminum and rare earth elements, and critical chemical compounds for domestic manufacturing. PHNX Materials' validated, scalable technology reduces carbon emissions, supports infrastructure rebuilding, and reshores critical supply chains while converting waste into essential materials for a cleaner, more resilient industrial base.
A33: EV0033 | B33: Prahelika | C33: prahelika.com | D33: =TRUE() -> TRUE | E33: 2026-08-24 | F33: 46258 | G33: 46258 | H33: 1 | I33: Preliminary Diligence | J33: 46237 | K33: Preliminary Diligence | L33: =TRUE() -> TRUE | M33: 46237 | N33: =FALSE() -> FALSE | P33: =FALSE() -> FALSE | R33: =FALSE() -> FALSE | T33: 4 | U33: 46237 | V33: 46258 | W33: Systems | X33: Affinity | Y33: Autonomous Systems | Z33: Seed | AA33: 17000000 | AE33: UNKNOWN | AF33: Preliminary Diligence | AG33: 1. Very High | AK33: Alaina Hartnett | AL33: alaina.hartnett@engineventures.com | AM33: =TRUE() -> TRUE | AN33: name | AO33: 311400320 | AP33: 250054857 | AQ33: 08/19/2026 | AR33: 04/01/2026 | AS33: 08/21/2026 | AU33: =FALSE() -> FALSE | AW33: P1 - discussed, incomplete | AX33: 1 | AY33: =FALSE() -> FALSE | AZ33: =TRUE() -> TRUE | BA33: =FALSE() -> FALSE | BB33: =FALSE() -> FALSE | BC33: =FALSE() -> FALSE
A34: EV0034 | B34: ScaleLight / TopoLight | D34: =TRUE() -> TRUE | E34: 2026-04-06 | F34: 46118 | G34: 46118 | H34: 1 | I34: Preliminary Diligence | J34: 46118 | K34: Preliminary Diligence | L34: =TRUE() -> TRUE | M34: 46118 | N34: =FALSE() -> FALSE | P34: =FALSE() -> FALSE | R34: =FALSE() -> FALSE | T34: 1 | U34: 46118 | V34: 46118 | W34: Systems | X34: Affinity | Y34: Autonomous Systems | Z34: Seed | AA34: 10000000 | AE34: UNKNOWN | AF34: Wait | AG34: 2. High | AK34: Madeleine Laitz | AL34: madeleine@engineventures.com | AM34: =TRUE() -> TRUE | AN34: fuzzy | AO34: 311517728 | AP34: 237197317 | AQ34: 03/26/2026 | AU34: =FALSE() -> FALSE | AW34: P1 - discussed, incomplete | AX34: 2 | AY34: =TRUE() -> TRUE | AZ34: =TRUE() -> TRUE | BA34: =FALSE() -> FALSE | BB34: =FALSE() -> FALSE | BC34: =FALSE() -> FALSE
A35: EV0035 | B35: /Eden Tech | C35: edentechinc.com | D35: =FALSE() -> FALSE | H35: 0 | I35: Preliminary Diligence | J35: 46070 | K35: Preliminary Diligence | L35: =TRUE() -> TRUE | M35: 46070 | N35: =FALSE() -> FALSE | P35: =FALSE() -> FALSE | R35: =FALSE() -> FALSE | T35: 1 | U35: 46070 | V35: 46070 | W35: Climate | X35: Affinity | Y35: Energy & Climate | AB35: Lockhart | AC35: Texas | AD35: United States | AE35: United States | AF35: Pre-Screen | AK35: Alaina Hartnett | AL35: alaina.hartnett@engineventures.com | AM35: =TRUE() -> TRUE | AN35: fuzzy | AO35: 278244151 | AP35: 233706001 | AQ35: 02/18/2026 | AR35: 02/10/2026 | AS35: 02/10/2026 | AU35: =FALSE() -> FALSE | AW35: P4 - acceptable | AX35: 2 | AY35: =FALSE() -> FALSE | AZ35: =FALSE() -> FALSE | BA35: =TRUE() -> TRUE | BB35: =TRUE() -> TRUE | BC35: =FALSE() -> FALSE | BD35: Eden Technologies is an innovative water technology company specializing in advanced desalination solutions. Their core product is a novel Reverse-Osmosis (RO) Centrifuge that uses centrifugal force to process brackish and saline water more efficiently. The technology aims to expand clean water access globally by increasing freshwater recovery rates up to 40% and reducing membrane fouling in desalination plants. Their approach focuses on developing cost-effective and environmentally safe water treatment technologies that improve the performance and profitability of water treatment facilities.
A36: EV0042 | B36: Adiabatic Machines | C36: adiabaticmachines.com | D36: =FALSE() -> FALSE | H36: 0 | I36: Preliminary Diligence | J36: 46230 | K36: Preliminary Diligence | L36: =TRUE() -> TRUE | M36: 46230 | N36: =FALSE() -> FALSE | P36: =FALSE() -> FALSE | R36: =FALSE() -> FALSE | T36: 18 | U36: 45978 | V36: 46265 | W36: Systems | X36: Affinity | Y36: Autonomous Systems | Z36: Preseed | AA36: 6000000 | AE36: UNKNOWN | AF36: Preliminary Diligence | AG36: 2. High | AH36: '++ | AI36: '+++ | AJ36: '+++ | AK36: Deepa Rao | AL36: deepa@engineventures.com | AM36: =TRUE() -> TRUE | AN36: name | AO36: 313217896 | AP36: 246954853 | AQ36: 07/14/2026 | AR36: 07/21/2026 | AS36: 08/11/2026 | AT36: Adiabatic machines; Machines | AU36: 0 | AW36: P4 - acceptable | AX36: 1 | AY36: 0 | AZ36: 1 | BA36: 0 | BB36: 0 | BC36: 0
A37: EV0044 | B37: Aepnus | C37: aepnus.com | D37: =FALSE() -> FALSE | H37: 0 | I37: Preliminary Diligence | J37: 45944 | K37: Preliminary Diligence | L37: =TRUE() -> TRUE | M37: 45944 | N37: =FALSE() -> FALSE | P37: =FALSE() -> FALSE | R37: =FALSE() -> FALSE | T37: 10 | U37: 45944 | V37: 46042 | W37: Climate | X37: Slide section | Y37: Energy & Climate | AE37: UNKNOWN | AM37: =FALSE() -> FALSE | AU37: =FALSE() -> FALSE | AW37: P2 - prelim dil, mostly empty | AX37: 5 | AY37: =TRUE() -> TRUE | AZ37: =TRUE() -> TRUE | BA37: =TRUE() -> TRUE | BB37: =TRUE() -> TRUE | BC37: =TRUE() -> TRUE
A38: EV0045 | B38: Aeris | D38: =FALSE() -> FALSE | H38: 0 | I38: Preliminary Diligence | J38: 45944 | K38: Preliminary Diligence | L38: =TRUE() -> TRUE | M38: 45944 | N38: =FALSE() -> FALSE | P38: =FALSE() -> FALSE | R38: =FALSE() -> FALSE | T38: 4 | U38: 45944 | V38: 45964 | W38: Systems | X38: Slide section | Y38: Autonomous Systems | AE38: UNKNOWN | AM38: =FALSE() -> FALSE | AU38: =FALSE() -> FALSE | AW38: P2 - prelim dil, mostly empty | AX38: 5 | AY38: =TRUE() -> TRUE | AZ38: =TRUE() -> TRUE | BA38: =TRUE() -> TRUE | BB38: =TRUE() -> TRUE | BC38: =TRUE() -> TRUE
A39: EV0048 | B39: Aikido Technologies | C39: aikidotechnologies.com | D39: =FALSE() -> FALSE | H39: 0 | I39: Preliminary Diligence | J39: 46223 | K39: Preliminary Diligence | L39: =TRUE() -> TRUE | M39: 46223 | N39: =FALSE() -> FALSE | P39: =FALSE() -> FALSE | R39: =FALSE() -> FALSE | T39: 7 | U39: 46216 | V39: 46258 | W39: Climate | X39: Affinity | Y39: Energy & Climate | Z39: Seed | AA39: 5000000 | AB39: San Francisco | AC39: California | AD39: United States | AE39: United States | AF39: Preliminary Diligence | AG39: 2. High | AK39: Deepa Rao | AL39: deepa@engineventures.com | AM39: =TRUE() -> TRUE | AN39: name | AO39: 287770819 | AP39: 247086373 | AQ39: 07/16/2026 | AR39: 07/13/2026 | AS39: 07/28/2026 | AU39: =FALSE() -> FALSE | AW39: P4 - acceptable | AX39: 0 | AY39: =FALSE() -> FALSE | AZ39: =FALSE() -> FALSE | BA39: =FALSE() -> FALSE | BB39: =FALSE() -> FALSE | BC39: =FALSE() -> FALSE | BD39: Aikido Technologies is an innovative renewable energy company specializing in floating offshore wind platform technology. The company develops solutions for deploying wind turbines in deep water, enabling energy providers to cost-effectively install large turbines with minimal construction time and labor. Their technology is designed to unlock local maritime infrastructure, create high-paying jobs in coastal communities, and provide low-cost, clean electricity to urban areas. By offering a versatile platform that supports efficient wind energy deployment, Aikido Technologies aims to advance sustainable energy production and support local economic development.
A40: EV0052 | B40: Alkali Labs | C40: alkalilabs.com | D40: =FALSE() -> FALSE | H40: 0 | I40: Preliminary Diligence | J40: 45944 | K40: Preliminary Diligence | L40: =TRUE() -> TRUE | M40: 45944 | N40: =FALSE() -> FALSE | P40: =FALSE() -> FALSE | R40: =FALSE() -> FALSE | T40: 2 | U40: 45944 | V40: 45950 | W40: Climate | X40: Slide section | Y40: Energy & Climate | AE40: UNKNOWN | AM40: =FALSE() -> FALSE | AU40: =FALSE() -> FALSE | AW40: P2 - prelim dil, mostly empty | AX40: 5 | AY40: =TRUE() -> TRUE | AZ40: =TRUE() -> TRUE | BA40: =TRUE() -> TRUE | BB40: =TRUE() -> TRUE | BC40: =TRUE() -> TRUE
A41: EV0055 | B41: AlumaPower | C41: alumapower.com | D41: =FALSE() -> FALSE | H41: 0 | I41: Preliminary Diligence | J41: 46070 | K41: Preliminary Diligence | L41: =TRUE() -> TRUE | M41: 46070 | N41: =FALSE() -> FALSE | P41: =FALSE() -> FALSE | R41: =FALSE() -> FALSE | T41: 2 | U41: 46062 | V41: 46070 | W41: Climate | X41: Affinity | Y41: Energy & Climate | AB41: Sarnia | AC41: Ontario | AD41: Canada | AE41: International | AF41: Initial Evaluation | AK41: Alaina Hartnett | AL41: alaina.hartnett@engineventures.com | AM41: =TRUE() -> TRUE | AN41: name | AO41: 224011994 | AP41: 233706024 | AQ41: 02/18/2026 | AR41: 02/13/2026 | AS41: 04/23/2026 | AU41: =FALSE() -> FALSE | AW41: P4 - acceptable | AX41: 2 | AY41: =FALSE() -> FALSE | AZ41: =FALSE() -> FALSE | BA41: =TRUE() -> TRUE | BB41: =TRUE() -> TRUE | BC41: =FALSE() -> FALSE | BD41: AlumaPower is an innovative energy technology company that has developed a breakthrough aluminum-air battery system, reimagined as a 'galvanic generator'. Their zero-emission technology produces approximately four times the energy density of lithium-ion batteries, utilizing recycled aluminum as fuel. The company's portable, long-duration energy sources are designed for diverse applications including micro-generation devices, cold chain refrigeration, and transportation. With a focus on environmentally superior solutions, AlumaPower partners with leading B2B companies to advance sustainable, high-performance energy generation technologies.
A42: EV0058 | B42: Amplify Computing | D42: =FALSE() -> FALSE | H42: 0 | I42: Preliminary Diligence | J42: 46034 | K42: Preliminary Diligence | L42: =TRUE() -> TRUE | M42: 46034 | N42: =FALSE() -> FALSE | P42: =FALSE() -> FALSE | R42: =FALSE() -> FALSE | T42: 6 | U42: 46034 | V42: 46070 | W42: Systems | X42: Affinity | Y42: Autonomous Systems | Z42: Seed | AA42: 5000000 | AE42: UNKNOWN | AF42: Wait | AG42: 2. High | AK42: Madeleine Laitz | AL42: madeleine@engineventures.com | AM42: =TRUE() -> TRUE | AN42: name | AO42: 310577728 | AP42: 231975766 | AQ42: 01/29/2026 | AU42: =FALSE() -> FALSE | AW42: P4 - acceptable | AX42: 2 | AY42: =TRUE() -> TRUE | AZ42: =TRUE() -> TRUE | BA42: =FALSE() -> FALSE | BB42: =FALSE() -> FALSE | BC42: =FALSE() -> FALSE
A43: EV0064 | B43: Anywhere robotics | D43: =FALSE() -> FALSE | H43: 0 | I43: Preliminary Diligence | J43: 46265 | K43: Preliminary Diligence | L43: =TRUE() -> TRUE | M43: 46265 | N43: =FALSE() -> FALSE | P43: =FALSE() -> FALSE | R43: =FALSE() -> FALSE | T43: 2 | U43: 46258 | V43: 46265 | W43: Systems | X43: Slide section | Y43: Autonomous Systems | AE43: UNKNOWN | AM43: =FALSE() -> FALSE | AT43: Anywhere Robotics | AU43: =FALSE() -> FALSE | AW43: P2 - prelim dil, mostly empty | AX43: 5 | AY43: =TRUE() -> TRUE | AZ43: =TRUE() -> TRUE | BA43: =TRUE() -> TRUE | BB43: =TRUE() -> TRUE | BC43: =TRUE() -> TRUE
A44: EV0068 | B44: Arinna | C44: arinna.xyz | D44: =FALSE() -> FALSE | H44: 0 | I44: Preliminary Diligence | J44: 46146 | K44: Preliminary Diligence | L44: =TRUE() -> TRUE | M44: 46146 | N44: =FALSE() -> FALSE | P44: =FALSE() -> FALSE | R44: =FALSE() -> FALSE | T44: 11 | U44: 46146 | V44: 46223 | W44: Systems | X44: Slide section | Y44: Autonomous Systems | AE44: UNKNOWN | AM44: =FALSE() -> FALSE | AU44: =FALSE() -> FALSE | AW44: P2 - prelim dil, mostly empty | AX44: 5 | AY44: =TRUE() -> TRUE | AZ44: =TRUE() -> TRUE | BA44: =TRUE() -> TRUE | BB44: =TRUE() -> TRUE | BC44: =TRUE() -> TRUE
A45: EV0070 | B45: Artisan Insight | C45: artisaninsight.com | D45: =FALSE() -> FALSE | H45: 0 | I45: Preliminary Diligence | J45: 45944 | K45: Preliminary Diligence | L45: =TRUE() -> TRUE | M45: 45944 | N45: =FALSE() -> FALSE | P45: =FALSE() -> FALSE | R45: =FALSE() -> FALSE | T45: 8 | U45: 45944 | V45: 45992 | W45: Systems | X45: Affinity | Y45: Autonomous Systems | Z45: Seed | AA45: 6000000 | AE45: UNKNOWN | AF45: Pass | AG45: 3. Moderate | AK45: Madeleine Laitz | AL45: madeleine@engineventures.com | AM45: =TRUE() -> TRUE | AN45: name | AO45: 298930167 | AP45: 224915928 | AQ45: 11/12/2025 | AR45: 11/10/2025 | AS45: 11/10/2025 | AT45: Artisan Insights | AU45: 0 | AW45: P4 - acceptable | AX45: 1 | AY45: 0 | AZ45: 1 | BA45: 0 | BB45: 0 | BC45: 0
A46: EV0074 | B46: Ascension | D46: =FALSE() -> FALSE | H46: 0 | I46: Preliminary Diligence | J46: 45992 | K46: Preliminary Diligence | L46: =TRUE() -> TRUE | M46: 45992 | N46: =FALSE() -> FALSE | P46: =FALSE() -> FALSE | R46: =FALSE() -> FALSE | T46: 9 | U46: 45985 | V46: 46055 | W46: Climate | X46: Affinity | Y46: Energy & Climate | AE46: UNKNOWN | AF46: Sourcing - No Outreach | AM46: =TRUE() -> TRUE | AN46: fuzzy | AO46: 310173842 | AP46: 230911437 | AQ46: 09/29/2025 | AU46: =FALSE() -> FALSE | AW46: P2 - prelim dil, mostly empty | AX46: 5 | AY46: =TRUE() -> TRUE | AZ46: =TRUE() -> TRUE | BA46: =TRUE() -> TRUE | BB46: =TRUE() -> TRUE | BC46: =TRUE() -> TRUE | BD46: Uses geothermal systems to recover rare‑earth elements sustainably from volcanic settings.
A47: EV0075 | B47: AssetCool | C47: assetcool.com | D47: =FALSE() -> FALSE | H47: 0 | I47: Preliminary Diligence | J47: 46034 | K47: Preliminary Diligence | L47: =TRUE() -> TRUE | M47: 46034 | N47: =FALSE() -> FALSE | P47: =FALSE() -> FALSE | R47: =FALSE() -> FALSE | T47: 5 | U47: 46034 | V47: 46062 | W47: Climate | X47: Affinity | Y47: Energy & Climate | Z47: Series B | AB47: Leeds | AC47: England | AD47: United Kingdom | AE47: International | AF47: Initial Evaluation | AG47: 5. Propose Pass | AK47: Alaina Hartnett | AL47: alaina.hartnett@engineventures.com | AM47: =TRUE() -> TRUE | AN47: name | AO47: 262001205 | AP47: 230014917 | AQ47: 01/08/2026 | AR47: 01/08/2026 | AS47: 01/08/2026 | AU47: =FALSE() -> FALSE | AW47: P4 - acceptable | AX47: 1 | AY47: =FALSE() -> FALSE | AZ47: =FALSE() -> FALSE | BA47: =FALSE() -> FALSE | BB47: =TRUE() -> TRUE | BC47: =FALSE() -> FALSE | BD47: AssetCool is an innovative technology company developing specialized photonic coatings and semi-autonomous application systems for overhead power lines. Their core technology increases electricity network performance by reducing energy losses, costs, and emissions through advanced nanotechnology-based coatings. The company's solutions can increase current carrying capacity by up to 45%, reduce power losses by up to 30%, and provide corrosion resistance for power transmission infrastructure, offering significant operational and financial benefits for utility and energy sectors.
A48: EV0080 | B48: Attune Neurosciences | C48: attuneneuro.com | D48: =FALSE() -> FALSE | H48: 0 | I48: Preliminary Diligence | J48: 45978 | K48: Preliminary Diligence | L48: =TRUE() -> TRUE | M48: 45978 | N48: =FALSE() -> FALSE | P48: =FALSE() -> FALSE | R48: =FALSE() -> FALSE | T48: 4 | U48: 45978 | V48: 45999 | W48: Health | X48: Slide section | Y48: Human Health | AE48: UNKNOWN | AM48: =FALSE() -> FALSE | AU48: =FALSE() -> FALSE | AW48: P2 - prelim dil, mostly empty | AX48: 5 | AY48: =TRUE() -> TRUE | AZ48: =TRUE() -> TRUE | BA48: =TRUE() -> TRUE | BB48: =TRUE() -> TRUE | BC48: =TRUE() -> TRUE
A49: EV0086 | B49: Ayo Compute | D49: =FALSE() -> FALSE | H49: 0 | I49: Preliminary Diligence | J49: 46076 | K49: Preliminary Diligence | L49: =TRUE() -> TRUE | M49: 46076 | N49: =FALSE() -> FALSE | P49: =FALSE() -> FALSE | R49: =FALSE() -> FALSE | T49: 1 | U49: 46076 | V49: 46076 | W49: Systems | X49: Slide section | Y49: Autonomous Systems | AE49: UNKNOWN | AM49: =FALSE() -> FALSE | AU49: =FALSE() -> FALSE | AW49: P2 - prelim dil, mostly empty | AX49: 5 | AY49: =TRUE() -> TRUE | AZ49: =TRUE() -> TRUE | BA49: =TRUE() -> TRUE | BB49: =TRUE() -> TRUE | BC49: =TRUE() -> TRUE
A50: EV0091 | B50: Beacon Photonics | D50: =FALSE() -> FALSE | H50: 0 | I50: Preliminary Diligence | J50: 46125 | K50: Preliminary Diligence | L50: =TRUE() -> TRUE | M50: 46125 | N50: =FALSE() -> FALSE | P50: =FALSE() -> FALSE | R50: =FALSE() -> FALSE | T50: 4 | U50: 46125 | V50: 46153 | W50: Systems | X50: Slide section | Y50: Autonomous Systems | AE50: UNKNOWN | AM50: =FALSE() -> FALSE | AU50: =FALSE() -> FALSE | AW50: P2 - prelim dil, mostly empty | AX50: 5 | AY50: =TRUE() -> TRUE | AZ50: =TRUE() -> TRUE | BA50: =TRUE() -> TRUE | BB50: =TRUE() -> TRUE | BC50: =TRUE() -> TRUE
A51: EV0094 | B51: Besxar | C51: besxar.com | D51: =FALSE() -> FALSE | H51: 0 | I51: Preliminary Diligence | J51: 46168 | K51: Preliminary Diligence | L51: =TRUE() -> TRUE | M51: 46168 | N51: =FALSE() -> FALSE | P51: =FALSE() -> FALSE | R51: =FALSE() -> FALSE | T51: 1 | U51: 46168 | V51: 46168 | W51: Systems | X51: Affinity | Y51: Autonomous Systems | Z51: Seed | AA51: 10000000 | AE51: UNKNOWN | AF51: Wait | AG51: 3. Moderate | AK51: Alaina Hartnett | AL51: alaina.hartnett@engineventures.com | AM51: =TRUE() -> TRUE | AN51: name | AO51: 307515128 | AP51: 240855184 | AQ51: 05/13/2026 | AR51: 05/12/2026 | AS51: 05/12/2026 | AU51: =FALSE() -> FALSE | AW51: P4 - acceptable | AX51: 1 | AY51: =FALSE() -> FALSE | AZ51: =TRUE() -> TRUE | BA51: =FALSE() -> FALSE | BB51: =FALSE() -> FALSE | BC51: =FALSE() -> FALSE | BD51: Besxar is pioneering a new class of space-based manufacturing to overcome the limits of terrestrial semiconductor fabrication. The company builds reusable “Fabships” that harness the ultra-high vacuum (UHV) of space to produce ultra-pure substrates and precursor materials—essential building blocks for next-generation technologies. Manufacturing in space allows purity and yield levels impossible on Earth, effectively doubling chip cost-effectiveness for these critical applications. Traditional chip factories face constraints in power, cooling, and materials. Besxar’s autonomous orbital manufacturing platforms overcome these barriers and return to Earth after each mission—not only delivering materials but also capturing insights to refine performance. Each cycle improves precision, efficiency, and reliability, making every subsequent orbital manufacturing run more effective. Besxar’s materials serve industries that demand the highest-performance semiconductors, from AI and quantum computing to nuclear technologies and defense applications. By combining space-based production with a focus on domestic resilience, Besxar is rebuilding the U.S. semiconductor base and redefining how—and where—humanity’s most critical technologies are made.
A52: EV0099 | B52: Blixt | D52: =FALSE() -> FALSE | H52: 0 | I52: Preliminary Diligence | J52: 46265 | K52: Preliminary Diligence | L52: =TRUE() -> TRUE | M52: 46265 | N52: =FALSE() -> FALSE | P52: =FALSE() -> FALSE | R52: =FALSE() -> FALSE | T52: 1 | U52: 46265 | V52: 46265 | W52: Climate | X52: Slide section | Y52: Energy & Climate | AE52: UNKNOWN | AM52: =FALSE() -> FALSE | AU52: =FALSE() -> FALSE | AW52: P2 - prelim dil, mostly empty | AX52: 5 | AY52: =TRUE() -> TRUE | AZ52: =TRUE() -> TRUE | BA52: =TRUE() -> TRUE | BB52: =TRUE() -> TRUE | BC52: =TRUE() -> TRUE
A53: EV0103 | B53: Braid Robotics | D53: =FALSE() -> FALSE | H53: 0 | I53: Preliminary Diligence | J53: 46048 | K53: Preliminary Diligence | L53: =TRUE() -> TRUE | M53: 46048 | N53: =FALSE() -> FALSE | P53: =FALSE() -> FALSE | R53: =FALSE() -> FALSE | T53: 8 | U53: 46048 | V53: 46097 | W53: Systems | X53: Affinity | Y53: Autonomous Systems | Z53: Seed | AA53: 10000000 | AE53: UNKNOWN | AF53: Pass | AG53: 3. Moderate | AK53: Madeleine Laitz | AL53: madeleine@engineventures.com | AM53: =TRUE() -> TRUE | AN53: name | AO53: 309941973 | AP53: 230066721 | AQ53: 01/09/2026 | AU53: =FALSE() -> FALSE | AW53: P4 - acceptable | AX53: 2 | AY53: =TRUE() -> TRUE | AZ53: =TRUE() -> TRUE | BA53: =FALSE() -> FALSE | BB53: =FALSE() -> FALSE | BC53: =FALSE() -> FALSE
A54: EV0106 | B54: CMatrics | D54: =FALSE() -> FALSE | H54: 0 | I54: Preliminary Diligence | J54: 46181 | K54: Hold / Nurture | L54: =TRUE() -> TRUE | M54: 46181 | N54: =FALSE() -> FALSE | P54: =FALSE() -> FALSE | R54: =FALSE() -> FALSE | T54: 5 | U54: 46174 | V54: 46209 | W54: Systems | X54: Affinity | Y54: Autonomous Systems | Z54: Series A | AA54: 20000000 | AE54: UNKNOWN | AF54: Pass | AG54: 2. High | AH54: '+ | AI54: '+++ | AJ54: '++ | AK54: Richard Collins | AL54: richard@engineventures.com | AM54: =TRUE() -> TRUE | AN54: name | AO54: 312433656 | AP54: 241997505 | AQ54: 05/29/2026 | AT54: Cmatrics | AU54: =FALSE() -> FALSE | AW54: P4 - acceptable | AX54: 2 | AY54: =TRUE() -> TRUE | AZ54: =TRUE() -> TRUE | BA54: =FALSE() -> FALSE | BB54: =FALSE() -> FALSE | BC54: =FALSE() -> FALSE
A55: EV0107 | B55: Cala | C55: calasystems.com | D55: =FALSE() -> FALSE | H55: 0 | I55: Preliminary Diligence | J55: 46188 | K55: Preliminary Diligence | L55: =TRUE() -> TRUE | M55: 46188 | N55: =FALSE() -> FALSE | P55: =FALSE() -> FALSE | R55: =FALSE() -> FALSE | T55: 3 | U55: 46188 | V55: 46209 | W55: Climate | X55: Slide section | Y55: Energy & Climate | AE55: UNKNOWN | AM55: =FALSE() -> FALSE | AU55: =FALSE() -> FALSE | AW55: P2 - prelim dil, mostly empty | AX55: 5 | AY55: =TRUE() -> TRUE | AZ55: =TRUE() -> TRUE | BA55: =TRUE() -> TRUE | BB55: =TRUE() -> TRUE | BC55: =TRUE() -> TRUE
A56: EV0108 | B56: Caladan | C56: caladan.bio | D56: =FALSE() -> FALSE | H56: 0 | I56: Preliminary Diligence | J56: 46209 | K56: Preliminary Diligence | L56: =TRUE() -> TRUE | M56: 46209 | N56: =FALSE() -> FALSE | P56: =FALSE() -> FALSE | R56: =FALSE() -> FALSE | T56: 9 | U56: 46195 | V56: 46258 | W56: Health | X56: Affinity | Y56: Human Health | Z56: Series A | AB56: Brooklyn | AC56: New York | AD56: United States | AE56: United States | AF56: Pre-Screen | AK56: Rachel Field | AL56: rachel@engineventures.com | AM56: =TRUE() -> TRUE | AN56: domain | AO56: 293412464 | AP56: 243796394 | AQ56: 06/22/2026 | AR56: 06/22/2026 | AS56: 07/07/2026 | AU56: =FALSE() -> FALSE | AW56: P4 - acceptable | AX56: 1 | AY56: =FALSE() -> FALSE | AZ56: =FALSE() -> FALSE | BA56: =FALSE() -> FALSE | BB56: =TRUE() -> TRUE | BC56: =FALSE() -> FALSE | BD56: Caladan Bio develops next-generation biomanufacturing technology, specializing in high-throughput 250mL benchtop bioreactors for synthetic biology scale-up. Their automated bioprocessing platform integrates advanced hardware and intuitive software to enable researchers and biotechnology companies to run multiple experiments simultaneously. The system provides real-time monitoring, automated data analysis, and supports early-stage R&D teams working on innovative products like alternative proteins, high-performance enzymes, sustainable materials, and next-generation therapeutics. By offering a cost-effective, user-friendly solution, Caladan Bio helps companies accelerate product development and improve overall bioprocessing efficiency.
A57: EV0122 | B57: Cetos / Kira /Eden Tech | C57: cetoswater.com; kira.eco; edentechinc.com | D57: =FALSE() -> FALSE | H57: 0 | I57: Preliminary Diligence | J57: 46104 | K57: Preliminary Diligence | L57: =TRUE() -> TRUE | M57: 46104 | N57: =FALSE() -> FALSE | P57: =FALSE() -> FALSE | R57: =FALSE() -> FALSE | T57: 3 | U57: 46104 | V57: 46118 | W57: Climate | X57: Slide section | Y57: Energy & Climate | AE57: UNKNOWN | AM57: =FALSE() -> FALSE | AT57: Cetos / Kira /Eden Tech/ | AU57: =FALSE() -> FALSE | AW57: P2 - prelim dil, mostly empty | AX57: 5 | AY57: =TRUE() -> TRUE | AZ57: =TRUE() -> TRUE | BA57: =TRUE() -> TRUE | BB57: =TRUE() -> TRUE | BC57: =TRUE() -> TRUE
A58: EV0125 | B58: ChipAdd | C58: chipadd.com | D58: =FALSE() -> FALSE | H58: 0 | I58: Preliminary Diligence | J58: 46097 | K58: Meetings This Week | L58: =TRUE() -> TRUE | M58: 46097 | N58: =FALSE() -> FALSE | P58: =FALSE() -> FALSE | R58: =FALSE() -> FALSE | T58: 1 | U58: 46097 | V58: 46097 | W58: Systems | X58: Affinity | Y58: Autonomous Systems | Z58: Seed | AE58: UNKNOWN | AF58: Initial Evaluation | AG58: 4. Low | AK58: Alaina Hartnett | AL58: alaina.hartnett@engineventures.com | AM58: =TRUE() -> TRUE | AN58: name | AO58: 311206342 | AP58: 235290071 | AQ58: 03/06/2026 | AR58: 03/06/2026 | AS58: 03/17/2026 | AU58: =FALSE() -> FALSE | AW58: P4 - acceptable | AX58: 2 | AY58: =FALSE() -> FALSE | AZ58: =TRUE() -> TRUE | BA58: =FALSE() -> FALSE | BB58: =TRUE() -> TRUE | BC58: =FALSE() -> FALSE
A59: EV0126 | B59: ChipX | D59: =FALSE() -> FALSE | H59: 0 | I59: Preliminary Diligence | J59: 45944 | K59: Preliminary Diligence | L59: =TRUE() -> TRUE | M59: 45944 | N59: =FALSE() -> FALSE | P59: =FALSE() -> FALSE | R59: =FALSE() -> FALSE | T59: 6 | U59: 45944 | V59: 45978 | W59: Systems | X59: Affinity | Y59: Autonomous Systems | Z59: Seed | AA59: 3000000 | AE59: UNKNOWN | AF59: Wait | AG59: 3. Moderate | AK59: Madeleine Laitz | AL59: madeleine@engineventures.com | AM59: =TRUE() -> TRUE | AN59: name | AO59: 308664124 | AP59: 224901692 | AQ59: 11/12/2025 | AU59: =FALSE() -> FALSE | AW59: P4 - acceptable | AX59: 2 | AY59: =TRUE() -> TRUE | AZ59: =TRUE() -> TRUE | BA59: =FALSE() -> FALSE | BB59: =FALSE() -> FALSE | BC59: =FALSE() -> FALSE
A60: EV0128 | B60: Circadian OS | C60: circadian-os.com | D60: =FALSE() -> FALSE | H60: 0 | I60: Preliminary Diligence | J60: 45950 | K60: Meetings This Week | L60: =TRUE() -> TRUE | M60: 45950 | N60: =FALSE() -> FALSE | P60: =FALSE() -> FALSE | R60: =FALSE() -> FALSE | T60: 9 | U60: 45944 | V60: 45999 | W60: Health | X60: Affinity | Y60: Human Health | Z60: Preseed | AA60: 2500000 | AB60: New York | AC60: New York | AD60: United States | AE60: United States | AF60: Pass | AK60: Rachel Field | AL60: rachel@engineventures.com | AM60: =TRUE() -> TRUE | AN60: name | AO60: 301735133 | AP60: 222537432 | AQ60: 10/17/2025 | AR60: 10/17/2025 | AS60: 11/24/2025 | AU60: =FALSE() -> FALSE | AW60: P4 - acceptable | AX60: 0 | AY60: =FALSE() -> FALSE | AZ60: =FALSE() -> FALSE | BA60: =FALSE() -> FALSE | BB60: =FALSE() -> FALSE | BC60: =FALSE() -> FALSE | BD60: Circadian OS is based on Nobel Prize-winning work out of Rockefeller University and developing the first FDA approved non-pharmacological circadian therapeutic for oncology.
A61: EV0129 | B61: Coformer.ai | C61: coformer.ai | D61: =FALSE() -> FALSE | H61: 0 | I61: Preliminary Diligence | J61: 46083 | K61: Preliminary Diligence | L61: =TRUE() -> TRUE | M61: 46083 | N61: =FALSE() -> FALSE | P61: =FALSE() -> FALSE | R61: =FALSE() -> FALSE | T61: 2 | U61: 46083 | V61: 46090 | W61: Health | X61: Affinity | Y61: Human Health | AB61: San Francisco | AC61: California | AD61: United States | AE61: United States | AF61: Pass | AK61: Vinny Beranek | AL61: vinny@engineventures.com | AM61: =TRUE() -> TRUE | AN61: fuzzy | AO61: 310734539 | AP61: 233321354 | AQ61: 02/12/2026 | AR61: 02/26/2026 | AS61: 02/26/2026 | AU61: =FALSE() -> FALSE | AW61: P4 - acceptable | AX61: 2 | AY61: =FALSE() -> FALSE | AZ61: =FALSE() -> FALSE | BA61: =TRUE() -> TRUE | BB61: =TRUE() -> TRUE | BC61: =FALSE() -> FALSE
A62: EV0130 | B62: CombustWell | D62: =FALSE() -> FALSE | H62: 0 | I62: Preliminary Diligence | J62: 46223 | K62: Preliminary Diligence | L62: =TRUE() -> TRUE | M62: 46223 | N62: =FALSE() -> FALSE | P62: =FALSE() -> FALSE | R62: =FALSE() -> FALSE | T62: 9 | U62: 46209 | V62: 46265 | W62: Climate | X62: Affinity | Y62: Energy & Climate | Z62: Seed | AA62: 10000000 | AE62: UNKNOWN | AF62: Preliminary Diligence | AG62: 3. Moderate | AH62: '++ | AI62: '++ | AJ62: '++ | AK62: Richard Collins | AL62: richard@engineventures.com | AM62: =TRUE() -> TRUE | AN62: name | AO62: 312823601 | AP62: 244268524 | AQ62: 06/24/2026 | AR62: 06/18/2026 | AS62: 06/18/2026 | AU62: =FALSE() -> FALSE | AW62: P4 - acceptable | AX62: 2 | AY62: =TRUE() -> TRUE | AZ62: =TRUE() -> TRUE | BA62: =FALSE() -> FALSE | BB62: =FALSE() -> FALSE | BC62: =FALSE() -> FALSE
A63: EV0134 | B63: CypherSonic Labs | D63: =FALSE() -> FALSE | H63: 0 | I63: Preliminary Diligence | J63: 46055 | K63: Preliminary Diligence | L63: =TRUE() -> TRUE | M63: 46055 | N63: =FALSE() -> FALSE | P63: =FALSE() -> FALSE | R63: =FALSE() -> FALSE | T63: 3 | U63: 46055 | V63: 46070 | W63: Systems | X63: Slide section | Y63: Autonomous Systems | AE63: UNKNOWN | AM63: =FALSE() -> FALSE | AU63: =FALSE() -> FALSE | AW63: P2 - prelim dil, mostly empty | AX63: 5 | AY63: =TRUE() -> TRUE | AZ63: =TRUE() -> TRUE | BA63: =TRUE() -> TRUE | BB63: =TRUE() -> TRUE | BC63: =TRUE() -> TRUE
A64: EV0135 | B64: Dario NewCo | D64: =FALSE() -> FALSE | H64: 0 | I64: Preliminary Diligence | J64: 45978 | K64: Preliminary Diligence | L64: =TRUE() -> TRUE | M64: 45978 | N64: =FALSE() -> FALSE | P64: =FALSE() -> FALSE | R64: =FALSE() -> FALSE | T64: 8 | U64: 45978 | V64: 46042 | W64: Health | X64: Slide section | Y64: Human Health | AE64: UNKNOWN | AM64: =FALSE() -> FALSE | AU64: =FALSE() -> FALSE | AW64: P2 - prelim dil, mostly empty | AX64: 5 | AY64: =TRUE() -> TRUE | AZ64: =TRUE() -> TRUE | BA64: =TRUE() -> TRUE | BB64: =TRUE() -> TRUE | BC64: =TRUE() -> TRUE
A65: EV0138 | B65: Deepankur NewCo | D65: =FALSE() -> FALSE | H65: 0 | I65: Preliminary Diligence | J65: 46146 | K65: Preliminary Diligence | L65: =TRUE() -> TRUE | M65: 46146 | N65: =FALSE() -> FALSE | P65: =FALSE() -> FALSE | R65: =FALSE() -> FALSE | T65: 9 | U65: 46146 | V65: 46209 | W65: Systems | X65: Slide section | Y65: Autonomous Systems | AE65: UNKNOWN | AM65: =FALSE() -> FALSE | AU65: =FALSE() -> FALSE | AW65: P2 - prelim dil, mostly empty | AX65: 5 | AY65: =TRUE() -> TRUE | AZ65: =TRUE() -> TRUE | BA65: =TRUE() -> TRUE | BB65: =TRUE() -> TRUE | BC65: =TRUE() -> TRUE
A66: EV0143 | B66: Drift Energy | C66: drift.energy | D66: =FALSE() -> FALSE | H66: 0 | I66: Preliminary Diligence | J66: 46209 | K66: Meetings This Week | L66: =TRUE() -> TRUE | M66: 46209 | N66: =FALSE() -> FALSE | P66: =FALSE() -> FALSE | R66: =FALSE() -> FALSE | T66: 1 | U66: 46209 | V66: 46209 | W66: Climate | X66: Slide section | Y66: Energy & Climate | AE66: UNKNOWN | AM66: =FALSE() -> FALSE | AU66: =FALSE() -> FALSE | AW66: P2 - prelim dil, mostly empty | AX66: 5 | AY66: =TRUE() -> TRUE | AZ66: =TRUE() -> TRUE | BA66: =TRUE() -> TRUE | BB66: =TRUE() -> TRUE | BC66: =TRUE() -> TRUE
A67: EV0144 | B67: Dunia.ai | C67: dunia.ai | D67: =FALSE() -> FALSE | H67: 0 | I67: Preliminary Diligence | J67: 46174 | K67: Preliminary Diligence | L67: =TRUE() -> TRUE | M67: 46174 | N67: =FALSE() -> FALSE | P67: =FALSE() -> FALSE | R67: =FALSE() -> FALSE | T67: 2 | U67: 46174 | V67: 46181 | W67: AI for Science | X67: Slide section | Y67: AI for Science | AE67: UNKNOWN | AM67: =FALSE() -> FALSE | AU67: =FALSE() -> FALSE | AW67: P2 - prelim dil, mostly empty | AX67: 5 | AY67: =TRUE() -> TRUE | AZ67: =TRUE() -> TRUE | BA67: =TRUE() -> TRUE | BB67: =TRUE() -> TRUE | BC67: =TRUE() -> TRUE
A68: EV0145 | B68: Dynamical Mind | C68: dynamicalmind.com | D68: =FALSE() -> FALSE | H68: 0 | I68: Preliminary Diligence | J68: 46230 | K68: Preliminary Diligence | L68: =TRUE() -> TRUE | M68: 46230 | N68: =FALSE() -> FALSE | P68: =FALSE() -> FALSE | R68: =FALSE() -> FALSE | T68: 4 | U68: 46223 | V68: 46244 | W68: Systems | X68: Affinity | Y68: Autonomous Systems | Z68: Seed | AA68: 35000000 | AE68: UNKNOWN | AF68: Initial Evaluation | AG68: 5. Propose Pass | AK68: Alaina Hartnett | AL68: alaina.hartnett@engineventures.com | AM68: =TRUE() -> TRUE | AN68: name | AO68: 313282361 | AP68: 248261333 | AQ68: 07/30/2026 | AR68: 07/24/2026 | AS68: 08/11/2026 | AT68: Dynamical Minds | AU68: 0 | AW68: P4 - acceptable | AX68: 1 | AY68: 0 | AZ68: 1 | BA68: 0 | BB68: 0 | BC68: 0
A69: EV0153 | B69: Ekion | C69: ekion.com.au | D69: =FALSE() -> FALSE | H69: 0 | I69: Preliminary Diligence | J69: 46076 | K69: Preliminary Diligence | L69: =TRUE() -> TRUE | M69: 46076 | N69: =FALSE() -> FALSE | P69: =FALSE() -> FALSE | R69: =FALSE() -> FALSE | T69: 2 | U69: 46070 | V69: 46076 | W69: Climate | X69: Slide section | Y69: Energy & Climate | AE69: UNKNOWN | AM69: =FALSE() -> FALSE | AU69: =FALSE() -> FALSE | AW69: P2 - prelim dil, mostly empty | AX69: 5 | AY69: =TRUE() -> TRUE | AZ69: =TRUE() -> TRUE | BA69: =TRUE() -> TRUE | BB69: =TRUE() -> TRUE | BC69: =TRUE() -> TRUE
A70: EV0155 | B70: Elementium | C70: elementium.io | D70: =FALSE() -> FALSE | H70: 0 | I70: Preliminary Diligence | J70: 46265 | K70: Preliminary Diligence | L70: =TRUE() -> TRUE | M70: 46265 | N70: =FALSE() -> FALSE | P70: =FALSE() -> FALSE | R70: =FALSE() -> FALSE | T70: 2 | U70: 46258 | V70: 46265 | W70: Climate | X70: Slide section | Y70: Energy & Climate | AE70: UNKNOWN | AM70: =FALSE() -> FALSE | AU70: =FALSE() -> FALSE | AW70: P2 - prelim dil, mostly empty | AX70: 5 | AY70: =TRUE() -> TRUE | AZ70: =TRUE() -> TRUE | BA70: =TRUE() -> TRUE | BB70: =TRUE() -> TRUE | BC70: =TRUE() -> TRUE
A71: EV0157 | B71: Emergentia | D71: =FALSE() -> FALSE | H71: 0 | I71: Preliminary Diligence | J71: 45944 | K71: Preliminary Diligence | L71: =TRUE() -> TRUE | M71: 45944 | N71: =FALSE() -> FALSE | P71: =FALSE() -> FALSE | R71: =FALSE() -> FALSE | T71: 1 | U71: 45944 | V71: 45944 | W71: Systems | X71: Affinity | Y71: Autonomous Systems | Z71: Seed | AA71: 2000000 | AE71: UNKNOWN | AF71: Pass | AG71: 4. Low | AK71: Madeleine Laitz | AL71: madeleine@engineventures.com | AM71: =TRUE() -> TRUE | AN71: name | AO71: 307254013 | AP71: 222532634 | AQ71: 10/17/2025 | AU71: =FALSE() -> FALSE | AW71: P4 - acceptable | AX71: 2 | AY71: =TRUE() -> TRUE | AZ71: =TRUE() -> TRUE | BA71: =FALSE() -> FALSE | BB71: =FALSE() -> FALSE | BC71: =FALSE() -> FALSE
A72: EV0158 | B72: EnCharge | D72: =FALSE() -> FALSE | H72: 0 | I72: Preliminary Diligence | J72: 46174 | K72: Preliminary Diligence | L72: =TRUE() -> TRUE | M72: 46174 | N72: =FALSE() -> FALSE | P72: =FALSE() -> FALSE | R72: =FALSE() -> FALSE | T72: 4 | U72: 46174 | V72: 46195 | W72: Systems | X72: Slide section | Y72: Autonomous Systems | AE72: UNKNOWN | AM72: =FALSE() -> FALSE | AU72: =FALSE() -> FALSE | AW72: P2 - prelim dil, mostly empty | AX72: 5 | AY72: =TRUE() -> TRUE | AZ72: =TRUE() -> TRUE | BA72: =TRUE() -> TRUE | BB72: =TRUE() -> TRUE | BC72: =TRUE() -> TRUE
A73: EV0159 | B73: Epia Neuro | C73: epianeuro.com | D73: =FALSE() -> FALSE | H73: 0 | I73: Preliminary Diligence | J73: 46216 | K73: Preliminary Diligence | L73: =TRUE() -> TRUE | M73: 46216 | N73: =FALSE() -> FALSE | P73: =FALSE() -> FALSE | R73: =FALSE() -> FALSE | T73: 8 | U73: 46216 | V73: 46265 | W73: Health | X73: Affinity | Y73: Human Health | AB73: Alameda | AC73: California | AD73: United States | AE73: United States | AF73: Pre-Screen | AK73: Rachel Field | AL73: rachel@engineventures.com | AM73: =TRUE() -> TRUE | AN73: name | AO73: 312423978 | AP73: 245017841 | AQ73: 06/26/2026 | AR73: 06/26/2026 | AS73: 07/16/2026 | AU73: =FALSE() -> FALSE | AW73: P4 - acceptable | AX73: 2 | AY73: =FALSE() -> FALSE | AZ73: =FALSE() -> FALSE | BA73: =TRUE() -> TRUE | BB73: =TRUE() -> TRUE | BC73: =FALSE() -> FALSE | BD73: Epia Neuro is a neural technology company developing intent-driven systems designed to restore function and independence for people living with neurological conditions. Its platform integrates implantable neural interfaces, adaptive algorithms, and assistive devices to translate neural intent into real-world action. The company’s initial focus is stroke-related motor impairment, with expansion in cognitive decline and other neurological disorders, focusing on long-term solutions for the growing aging population.
A74: EV0162 | B74: Exousia | D74: =FALSE() -> FALSE | H74: 0 | I74: Preliminary Diligence | J74: 46070 | K74: Meetings This Week | L74: =TRUE() -> TRUE | M74: 46070 | N74: =FALSE() -> FALSE | P74: =FALSE() -> FALSE | R74: =FALSE() -> FALSE | T74: 4 | U74: 46062 | V74: 46083 | W74: Systems | X74: Affinity | Y74: Autonomous Systems | Z74: Series A | AA74: 20000000 | AE74: UNKNOWN | AF74: Pass | AG74: 3. Moderate | AK74: Madeleine Laitz | AL74: madeleine@engineventures.com | AM74: =TRUE() -> TRUE | AN74: name | AO74: 309473157 | AP74: 227999108 | AQ74: 12/11/2025 | AU74: =FALSE() -> FALSE | AW74: P4 - acceptable | AX74: 2 | AY74: =TRUE() -> TRUE | AZ74: =TRUE() -> TRUE | BA74: =FALSE() -> FALSE | BB74: =FALSE() -> FALSE | BC74: =FALSE() -> FALSE
A75: EV0164 | B75: Externa | C75: xterna.bio | D75: =FALSE() -> FALSE | H75: 0 | I75: Preliminary Diligence | J75: 46265 | K75: Preliminary Diligence | L75: =TRUE() -> TRUE | M75: 46265 | N75: =FALSE() -> FALSE | P75: =FALSE() -> FALSE | R75: =FALSE() -> FALSE | T75: 1 | U75: 46265 | V75: 46265 | W75: Health | X75: Affinity | Y75: Human Health | AB75: London | AC75: England | AD75: United Kingdom | AE75: International | AF75: Sourcing - No Outreach | AM75: =TRUE() -> TRUE | AN75: fuzzy | AO75: 302244927 | AP75: 230911415 | AQ75: 09/29/2025 | AU75: =FALSE() -> FALSE | AW75: P2 - prelim dil, mostly empty | AX75: 3 | AY75: =FALSE() -> FALSE | AZ75: =FALSE() -> FALSE | BA75: =TRUE() -> TRUE | BB75: =TRUE() -> TRUE | BC75: =TRUE() -> TRUE | BD75: Xterna is a biotechnology company specializing in advanced nucleic acid technologies for targeted drug delivery. The company focuses on developing innovative solutions to address challenging and currently untreatable diseases by enhancing the effectiveness of therapeutic approaches. Their core technology involves using specialized nucleic acid techniques to enable cell-specific targeting of drugs, with support from funding programs like InnovateUK and the Science Creates Accelerator.
A76: EV0165 | B76: FAST Metals | D76: =FALSE() -> FALSE | H76: 0 | I76: Preliminary Diligence | J76: 45944 | K76: Preliminary Diligence | L76: =TRUE() -> TRUE | M76: 45944 | N76: =FALSE() -> FALSE | P76: =FALSE() -> FALSE | R76: =FALSE() -> FALSE | T76: 2 | U76: 45944 | V76: 45950 | W76: Climate | X76: Slide section | Y76: Energy & Climate | AE76: UNKNOWN | AM76: =FALSE() -> FALSE | AU76: =FALSE() -> FALSE | AW76: P2 - prelim dil, mostly empty | AX76: 5 | AY76: =TRUE() -> TRUE | AZ76: =TRUE() -> TRUE | BA76: =TRUE() -> TRUE | BB76: =TRUE() -> TRUE | BC76: =TRUE() -> TRUE
A77: EV0166 | B77: FLUIX AI | C77: fluix.ai | D77: =FALSE() -> FALSE | H77: 0 | I77: Preliminary Diligence | J77: 46062 | K77: Preliminary Diligence | L77: =TRUE() -> TRUE | M77: 46062 | N77: =FALSE() -> FALSE | P77: =FALSE() -> FALSE | R77: =FALSE() -> FALSE | T77: 2 | U77: 46055 | V77: 46062 | W77: Systems | X77: Slide section | Y77: Autonomous Systems | AE77: UNKNOWN | AM77: =FALSE() -> FALSE | AT77: FluixAI | AU77: =FALSE() -> FALSE | AW77: P2 - prelim dil, mostly empty | AX77: 5 | AY77: =TRUE() -> TRUE | AZ77: =TRUE() -> TRUE | BA77: =TRUE() -> TRUE | BB77: =TRUE() -> TRUE | BC77: =TRUE() -> TRUE
A78: EV0168 | B78: Flexnode | C78: flexnode.io | D78: =FALSE() -> FALSE | H78: 0 | I78: Preliminary Diligence | J78: 45944 | K78: Preliminary Diligence | L78: =TRUE() -> TRUE | M78: 45944 | N78: =FALSE() -> FALSE | P78: =FALSE() -> FALSE | R78: =FALSE() -> FALSE | T78: 3 | U78: 45944 | V78: 45957 | W78: Systems | X78: Affinity | Y78: Autonomous Systems | Z78: Series A | AA78: 40000000 | AB78: Bethesda | AC78: Maryland | AD78: United States | AE78: United States | AF78: Pass | AG78: 5. Propose Pass | AK78: Alaina Hartnett | AL78: alaina.hartnett@engineventures.com | AM78: =TRUE() -> TRUE | AN78: name | AO78: 281851328 | AP78: 220918740 | AQ78: 10/08/2025 | AR78: 09/17/2025 | AS78: 10/08/2025 | AU78: =FALSE() -> FALSE | AW78: P4 - acceptable | AX78: 0 | AY78: =FALSE() -> FALSE | AZ78: =FALSE() -> FALSE | BA78: =FALSE() -> FALSE | BB78: =FALSE() -> FALSE | BC78: =FALSE() -> FALSE | BD78: Flexnode is a digital infrastructure company specializing in modular, liquid-cooled micro data center (MDC) systems designed to support growing data demands. The company manufactures, deploys, and operates high-performance data center solutions that enable flexible, efficient compute access wherever power and connectivity exist. Flexnode's innovative approach focuses on reducing the physical and environmental footprint of data infrastructure by offering scalable, energy-efficient data centers that can be rapidly deployed on-site or off-site. Their modular systems are customizable, support complex IT projects, and provide advanced security protocols while emphasizing sustainability through significant reductions in material waste and water consumption.
A79: EV0169 | B79: Flip Tx | C79: fliptx.bio | D79: =FALSE() -> FALSE | H79: 0 | I79: Preliminary Diligence | J79: 45944 | K79: Preliminary Diligence | L79: =TRUE() -> TRUE | M79: 45944 | N79: =FALSE() -> FALSE | P79: =FALSE() -> FALSE | R79: =FALSE() -> FALSE | T79: 2 | U79: 45944 | V79: 45950 | W79: Health | X79: Slide section | Y79: Human Health | AE79: UNKNOWN | AM79: =FALSE() -> FALSE | AU79: =FALSE() -> FALSE | AW79: P2 - prelim dil, mostly empty | AX79: 5 | AY79: =TRUE() -> TRUE | AZ79: =TRUE() -> TRUE | BA79: =TRUE() -> TRUE | BB79: =TRUE() -> TRUE | BC79: =TRUE() -> TRUE
A80: EV0171 | B80: Flow Compute | D80: =FALSE() -> FALSE | H80: 0 | I80: Preliminary Diligence | J80: 46153 | K80: Preliminary Diligence | L80: =TRUE() -> TRUE | M80: 46153 | N80: =FALSE() -> FALSE | P80: =FALSE() -> FALSE | R80: =FALSE() -> FALSE | T80: 2 | U80: 46153 | V80: 46160 | W80: Systems | X80: Slide section | Y80: Autonomous Systems | AE80: UNKNOWN | AM80: =FALSE() -> FALSE | AU80: =FALSE() -> FALSE | AW80: P2 - prelim dil, mostly empty | AX80: 5 | AY80: =TRUE() -> TRUE | AZ80: =TRUE() -> TRUE | BA80: =TRUE() -> TRUE | BB80: =TRUE() -> TRUE | BC80: =TRUE() -> TRUE
A81: EV0174 | B81: Fluent BCI | C81: fluentbci.com | D81: =FALSE() -> FALSE | H81: 0 | I81: Preliminary Diligence | J81: 46223 | K81: Preliminary Diligence | L81: =TRUE() -> TRUE | M81: 46223 | N81: =FALSE() -> FALSE | P81: =FALSE() -> FALSE | R81: =FALSE() -> FALSE | T81: 6 | U81: 46223 | V81: 46258 | W81: Health | X81: Affinity | Y81: Human Health | Z81: Preseed | AA81: 1400000 | AB81: Melbourne | AC81: Victoria | AD81: Australia | AE81: International | AF81: Wait | AG81: 2. High | AI81: '++ | AJ81: '+++ | AK81: Deepa Rao | AL81: deepa@engineventures.com | AM81: =TRUE() -> TRUE | AN81: domain | AO81: 313251173 | AP81: 247032670 | AQ81: 07/15/2026 | AR81: 07/16/2026 | AS81: 07/16/2026 | AT81: Fluent | AU81: 0 | AW81: P4 - acceptable | AX81: 0 | AY81: 0 | AZ81: 0 | BA81: 0 | BB81: 0 | BC81: 0 | BD81: Fluent is pioneering the development of accessible brain-computer interface technology. Our mission is to seamlessly connect people with AI, enhancing communication and interaction for those with neurological conditions and ultimately transforming human-AI interaction for all.
A82: EV0175 | B82: FluidInsight | D82: =FALSE() -> FALSE | H82: 0 | I82: Preliminary Diligence | J82: 46265 | K82: Preliminary Diligence | L82: =TRUE() -> TRUE | M82: 46265 | N82: =FALSE() -> FALSE | P82: =FALSE() -> FALSE | R82: =FALSE() -> FALSE | T82: 2 | U82: 46258 | V82: 46265 | W82: Systems | X82: Slide section | Y82: Autonomous Systems | AE82: UNKNOWN | AM82: =FALSE() -> FALSE | AU82: =FALSE() -> FALSE | AW82: P2 - prelim dil, mostly empty | AX82: 5 | AY82: =TRUE() -> TRUE | AZ82: =TRUE() -> TRUE | BA82: =TRUE() -> TRUE | BB82: =TRUE() -> TRUE | BC82: =TRUE() -> TRUE
A83: EV0177 | B83: Formline Photonics | D83: =FALSE() -> FALSE | H83: 0 | I83: Preliminary Diligence | J83: 45944 | K83: Preliminary Diligence | L83: =TRUE() -> TRUE | M83: 45944 | N83: =FALSE() -> FALSE | P83: =FALSE() -> FALSE | R83: =FALSE() -> FALSE | T83: 8 | U83: 45944 | V83: 45992 | W83: Systems | X83: Slide section | Y83: Autonomous Systems | AE83: UNKNOWN | AM83: =FALSE() -> FALSE | AU83: =FALSE() -> FALSE | AW83: P2 - prelim dil, mostly empty | AX83: 5 | AY83: =TRUE() -> TRUE | AZ83: =TRUE() -> TRUE | BA83: =TRUE() -> TRUE | BB83: =TRUE() -> TRUE | BC83: =TRUE() -> TRUE
A84: EV0179 | B84: Found Industries | D84: =FALSE() -> FALSE | H84: 0 | I84: Preliminary Diligence | J84: 46070 | K84: Preliminary Diligence | L84: =TRUE() -> TRUE | M84: 46070 | N84: =FALSE() -> FALSE | P84: =FALSE() -> FALSE | R84: =FALSE() -> FALSE | T84: 5 | U84: 46062 | V84: 46097 | W84: Climate | X84: Slide section | Y84: Energy & Climate | AE84: UNKNOWN | AM84: =FALSE() -> FALSE | AU84: =FALSE() -> FALSE | AW84: P2 - prelim dil, mostly empty | AX84: 5 | AY84: =TRUE() -> TRUE | AZ84: =TRUE() -> TRUE | BA84: =TRUE() -> TRUE | BB84: =TRUE() -> TRUE | BC84: =TRUE() -> TRUE
A85: EV0180 | B85: Fusion Dynamics | C85: fusiondynamicscorporation.com | D85: =FALSE() -> FALSE | H85: 0 | I85: Preliminary Diligence | J85: 46097 | K85: Preliminary Diligence | L85: =TRUE() -> TRUE | M85: 46097 | N85: =FALSE() -> FALSE | P85: =FALSE() -> FALSE | R85: =FALSE() -> FALSE | T85: 3 | U85: 46097 | V85: 46111 | W85: Systems | X85: Affinity | Y85: Autonomous Systems | Z85: Seed | AA85: 3000000 | AE85: UNKNOWN | AF85: Pass | AG85: 3. Moderate | AK85: Alaina Hartnett | AL85: alaina.hartnett@engineventures.com | AM85: =TRUE() -> TRUE | AN85: name | AO85: 311327115 | AP85: 235558154 | AQ85: 03/11/2026 | AR85: 03/11/2026 | AS85: 03/31/2026 | AU85: =FALSE() -> FALSE | AW85: P4 - acceptable | AX85: 1 | AY85: =FALSE() -> FALSE | AZ85: =TRUE() -> TRUE | BA85: =FALSE() -> FALSE | BB85: =FALSE() -> FALSE | BC85: =FALSE() -> FALSE | BD85: Fusion Dynamics delivers silent, vibration-free solid-state thermal solutions using advanced electrohydrodynamic technology.
A86: EV0188 | B86: Graph Tx | C86: graphtx.com | D86: =FALSE() -> FALSE | H86: 0 | I86: Preliminary Diligence | J86: 46034 | K86: Preliminary Diligence | L86: =TRUE() -> TRUE | M86: 46034 | N86: =FALSE() -> FALSE | P86: =FALSE() -> FALSE | R86: =FALSE() -> FALSE | T86: 7 | U86: 46034 | V86: 46076 | W86: Health | X86: Affinity | Y86: Human Health | Z86: Seed | AA86: 20000000 | AB86: Vienna | AC86: Vienna | AD86: Austria | AE86: International | AF86: Pass | AK86: Vinny Beranek | AL86: vinny@engineventures.com | AM86: =TRUE() -> TRUE | AN86: domain | AO86: 310556780 | AP86: 231883604 | AQ86: 01/28/2026 | AR86: 09/25/2024 | AS86: 02/05/2026 | AU86: =FALSE() -> FALSE | AW86: P4 - acceptable | AX86: 0 | AY86: =FALSE() -> FALSE | AZ86: =FALSE() -> FALSE | BA86: =FALSE() -> FALSE | BB86: =FALSE() -> FALSE | BC86: =FALSE() -> FALSE | BD86: A precision immunology technology company leveraging AI-driven approaches to develop targeted therapies for immune-mediated diseases. Using advanced computational modeling and multi-omics data from patient cell samples, the company aims to create innovative treatments for complex immune conditions that currently lack adequate therapeutic options.
A87: EV0189 | B87: Gravity | C87: gravitytechnologies.com | D87: =TRUE() -> TRUE | E87: 2026-04-06 | F87: 46118 | G87: 46118 | H87: 1 | I87: Preliminary Diligence | J87: 46070 | K87: Preliminary Diligence | L87: =TRUE() -> TRUE | M87: 46070 | N87: =FALSE() -> FALSE | P87: =FALSE() -> FALSE | R87: =FALSE() -> FALSE | T87: 4 | U87: 46062 | V87: 46118 | W87: Systems; Climate | X87: Affinity | Y87: Energy & Climate | Z87: Series A | AA87: 20000000 | AB87: New York | AC87: New York | AD87: United States | AE87: United States | AF87: Pass | AG87: 1. Very High | AK87: Alaina Hartnett | AL87: alaina.hartnett@engineventures.com | AM87: =TRUE() -> TRUE | AN87: name | AO87: 120130338 | AP87: 233307669 | AQ87: 02/12/2026 | AR87: 02/10/2026 | AS87: 04/03/2026 | AT87: Flume / Gravity | AU87: 0 | AW87: P4 - acceptable | AX87: 0 | AY87: 0 | AZ87: 0 | BA87: 0 | BB87: 0 | BC87: 0 | BD87: Gravity Technologies is an electric vehicle infrastructure and energy management company focused on developing innovative EV charging solutions. Their comprehensive approach includes modular charging units with up to 500kW capacity, invisible charging systems for existing parking spaces, and a distributed energy management platform. The company aims to transform electric vehicles into grid-stabilizing power plants, offering advanced software and hardware that enables faster, more affordable charging for light, medium, and heavy-duty vehicles across private fleets and public spaces.
A88: EV0197 | B88: Heliux | D88: =FALSE() -> FALSE | H88: 0 | I88: Preliminary Diligence | J88: 45944 | K88: Preliminary Diligence | L88: =TRUE() -> TRUE | M88: 45944 | N88: =FALSE() -> FALSE | P88: =FALSE() -> FALSE | R88: =FALSE() -> FALSE | T88: 3 | U88: 45944 | V88: 45957 | W88: Systems | X88: Slide section | Y88: Autonomous Systems | AE88: UNKNOWN | AM88: =FALSE() -> FALSE | AU88: =FALSE() -> FALSE | AW88: P2 - prelim dil, mostly empty | AX88: 5 | AY88: =TRUE() -> TRUE | AZ88: =TRUE() -> TRUE | BA88: =TRUE() -> TRUE | BB88: =TRUE() -> TRUE | BC88: =TRUE() -> TRUE
A89: EV0200 | B89: HexaGAN | D89: =FALSE() -> FALSE | H89: 0 | I89: Preliminary Diligence | J89: 45978 | K89: Preliminary Diligence | L89: =TRUE() -> TRUE | M89: 45978 | N89: =FALSE() -> FALSE | P89: =FALSE() -> FALSE | R89: =FALSE() -> FALSE | T89: 5 | U89: 45978 | V89: 46006 | W89: Systems | X89: Affinity | Y89: Autonomous Systems | Z89: Seed | AA89: 5000000 | AE89: UNKNOWN | AF89: Wait | AG89: 3. Moderate | AK89: Madeleine Laitz | AL89: madeleine@engineventures.com | AM89: =TRUE() -> TRUE | AN89: name | AO89: 308664889 | AP89: 224903191 | AQ89: 11/12/2025 | AU89: =FALSE() -> FALSE | AW89: P4 - acceptable | AX89: 2 | AY89: =TRUE() -> TRUE | AZ89: =TRUE() -> TRUE | BA89: =FALSE() -> FALSE | BB89: =FALSE() -> FALSE | BC89: =FALSE() -> FALSE
A90: EV0205 | B90: Horizon Labs | D90: =FALSE() -> FALSE | H90: 0 | I90: Preliminary Diligence | J90: 46125 | K90: Preliminary Diligence | L90: =TRUE() -> TRUE | M90: 46125 | N90: =FALSE() -> FALSE | P90: =FALSE() -> FALSE | R90: =FALSE() -> FALSE | T90: 5 | U90: 46125 | V90: 46160 | W90: Systems | X90: Affinity | Y90: Autonomous Systems | Z90: Seed | AA90: 20000000 | AE90: UNKNOWN | AF90: Pass | AG90: 2. High | AK90: Madeleine Laitz | AL90: madeleine@engineventures.com | AM90: =TRUE() -> TRUE | AN90: fuzzy | AO90: 311677211 | AP90: 237925857 | AQ90: 04/06/2026 | AU90: =FALSE() -> FALSE | AW90: P4 - acceptable | AX90: 2 | AY90: =TRUE() -> TRUE | AZ90: =TRUE() -> TRUE | BA90: =FALSE() -> FALSE | BB90: =FALSE() -> FALSE | BC90: =FALSE() -> FALSE
A91: EV0207 | B91: HutanBio | C91: hutanbio.com | D91: =FALSE() -> FALSE | H91: 0 | I91: Preliminary Diligence | J91: 46223 | K91: Preliminary Diligence | L91: =TRUE() -> TRUE | M91: 46223 | N91: =FALSE() -> FALSE | P91: =FALSE() -> FALSE | R91: =FALSE() -> FALSE | T91: 8 | U91: 46216 | V91: 46265 | W91: Climate | X91: Affinity | Y91: Energy & Climate | Z91: Seed | AA91: 6700000 | AB91: Cambridge | AC91: England | AD91: United Kingdom | AE91: International | AF91: Preliminary Diligence | AK91: Deepa Rao | AL91: deepa@engineventures.com | AM91: =TRUE() -> TRUE | AN91: name | AO91: 288078088 | AP91: 246060581 | AQ91: 07/08/2026 | AR91: 07/14/2026 | AS91: 08/20/2026 | AU91: =FALSE() -> FALSE | AW91: P4 - acceptable | AX91: 0 | AY91: =FALSE() -> FALSE | AZ91: =FALSE() -> FALSE | BA91: =FALSE() -> FALSE | BB91: =FALSE() -> FALSE | BC91: =FALSE() -> FALSE | BD91: HutanBio is a technology company developing zero-carbon biofuel solutions for long-distance transportation, focusing on marine, aviation, and heavy land transport sectors. Founded in 2019 by researchers from Cambridge University, the company has developed HBx, a proprietary marine microalgae-based biofuel that can be used as a direct replacement for diesel. Their innovative approach uses CO2 and sunlight to produce a scalable, sustainable fuel that operates with existing infrastructure, aims to decarbonize transportation, and requires no fresh water or agricultural land.
A92: EV0208 | B92: Hydram | C92: hydram.is | D92: =FALSE() -> FALSE | H92: 0 | I92: Preliminary Diligence | J92: 46258 | K92: Preliminary Diligence | L92: =TRUE() -> TRUE | M92: 46258 | N92: =FALSE() -> FALSE | P92: =FALSE() -> FALSE | R92: =FALSE() -> FALSE | T92: 2 | U92: 46258 | V92: 46265 | W92: Climate | X92: Slide section | Y92: Energy & Climate | AE92: UNKNOWN | AM92: =FALSE() -> FALSE | AU92: =FALSE() -> FALSE | AW92: P2 - prelim dil, mostly empty | AX92: 5 | AY92: =TRUE() -> TRUE | AZ92: =TRUE() -> TRUE | BA92: =TRUE() -> TRUE | BB92: =TRUE() -> TRUE | BC92: =TRUE() -> TRUE
A93: EV0210 | B93: Hydron | C93: hydrondesal.com | D93: =FALSE() -> FALSE | H93: 0 | I93: Preliminary Diligence | J93: 46188 | K93: Preliminary Diligence | L93: =TRUE() -> TRUE | M93: 46188 | N93: =FALSE() -> FALSE | P93: =FALSE() -> FALSE | R93: =FALSE() -> FALSE | T93: 11 | U93: 46181 | V93: 46265 | W93: Climate | X93: Affinity | Y93: Energy & Climate | Z93: Seed | AA93: 3000000 | AB93: New York | AC93: New York | AD93: United States | AE93: United States | AF93: Preliminary Diligence | AG93: 3. Moderate | AK93: Rachel Field | AL93: rachel@engineventures.com | AM93: =TRUE() -> TRUE | AN93: fuzzy | AO93: 303067017 | AP93: 240981762 | AQ93: 05/14/2026 | AR93: 05/14/2026 | AS93: 08/12/2026 | AT93: Hydron Desal | AU93: 0 | AW93: P4 - acceptable | AX93: 0 | AY93: 0 | AZ93: 0 | BA93: 0 | BB93: 0 | BC93: 0 | BD93: Hydron is a water technology company offering innovative liquid-liquid extraction solutions for brine management, primarily serving the oil and gas industry. Their patented technology provides a cost-effective approach to desalination, significantly reducing treatment costs compared to traditional membrane and thermal technologies. The company develops custom water management solutions for various sectors including oil and gas producers, water project developers, and infrastructure owners, with a commitment to commercial readiness through pilot testing and performance guarantees.
A94: EV0216 | B94: IceBox Energy | C94: iceboxenergy.com | D94: =FALSE() -> FALSE | H94: 0 | I94: Preliminary Diligence | J94: 45944 | K94: Preliminary Diligence | L94: =TRUE() -> TRUE | M94: 45944 | N94: =FALSE() -> FALSE | P94: =FALSE() -> FALSE | R94: =FALSE() -> FALSE | T94: 2 | U94: 45944 | V94: 45950 | W94: Climate | X94: Affinity | Y94: Energy & Climate | Z94: Seed | AE94: UNKNOWN | AF94: Initial Evaluation | AG94: 4. Low | AK94: Deepa Rao | AL94: deepa@engineventures.com | AM94: =TRUE() -> TRUE | AN94: name | AO94: 301699768 | AP94: 218254273 | AQ94: 09/12/2025 | AR94: 09/12/2025 | AS94: 09/12/2025 | AU94: =FALSE() -> FALSE | AW94: P4 - acceptable | AX94: 2 | AY94: =FALSE() -> FALSE | AZ94: =TRUE() -> TRUE | BA94: =FALSE() -> FALSE | BB94: =TRUE() -> TRUE | BC94: =FALSE() -> FALSE | BD94: Icebox Energy is an innovative data center cooling technology company that provides a high-density cooling platform using a carbon dioxide loop. Their solution offers advanced cooling for high-performance computing environments, delivering exceptional cooling density and performance with low power consumption. The platform is modular, scalable, and designed to replace traditional cooling systems, providing precise temperature control for modern data centers while emphasizing energy efficiency and sustainability.
A95: EV0220 | B95: Infinimmune | C95: infinimmune.com | D95: =FALSE() -> FALSE | H95: 0 | I95: Preliminary Diligence | J95: 46083 | K95: Preliminary Diligence | L95: =TRUE() -> TRUE | M95: 46083 | N95: =FALSE() -> FALSE | P95: =FALSE() -> FALSE | R95: =FALSE() -> FALSE | T95: 18 | U95: 46083 | V95: 46216 | W95: Health | X95: Affinity | Y95: Human Health | Z95: Series A | AA95: 90000000 | AB95: Alameda | AC95: California | AD95: United States | AE95: United States | AF95: Wait | AK95: Vinny Beranek | AL95: vinny@engineventures.com | AM95: =TRUE() -> TRUE | AN95: name | AO95: 286407135 | AP95: 232413671 | AQ95: 02/04/2026 | AR95: 02/23/2026 | AS95: 02/23/2026 | AU95: =FALSE() -> FALSE | AW95: P4 - acceptable | AX95: 0 | AY95: =FALSE() -> FALSE | AZ95: =FALSE() -> FALSE | BA95: =FALSE() -> FALSE | BB95: =FALSE() -> FALSE | BC95: =FALSE() -> FALSE | BD95: Infinimmune is a biotechnology company pioneering a novel approach to antibody drug discovery and development. The company specializes in creating truly human therapeutics by developing complete human antibodies derived directly from the human immune system. Using advanced immunosequencing technology, Infinimmune identifies and validates antibodies to create novel drugs with improved safety and efficacy. Their platform focuses on developing treatments for various diseases by leveraging a comprehensive catalog of fully functional antibodies, with the goal of enhancing clinical outcomes through a holistic approach to antibody development.
A96: EV0223 | B96: Inlyte Energy | C96: inlyteenergy.com | D96: =FALSE() -> FALSE | H96: 0 | I96: Preliminary Diligence | J96: 46070 | K96: Preliminary Diligence | L96: =TRUE() -> TRUE | M96: 46070 | N96: =FALSE() -> FALSE | P96: =FALSE() -> FALSE | R96: =FALSE() -> FALSE | T96: 6 | U96: 46062 | V96: 46097 | W96: Climate | X96: Slide section | Y96: Energy & Climate | AE96: UNKNOWN | AM96: =FALSE() -> FALSE | AU96: =FALSE() -> FALSE | AW96: P2 - prelim dil, mostly empty | AX96: 5 | AY96: =TRUE() -> TRUE | AZ96: =TRUE() -> TRUE | BA96: =TRUE() -> TRUE | BB96: =TRUE() -> TRUE | BC96: =TRUE() -> TRUE
A97: EV0229 | B97: JuliaHub | C97: juliahub.com | D97: =FALSE() -> FALSE | H97: 0 | I97: Preliminary Diligence | J97: 45957 | K97: Preliminary Diligence | L97: =TRUE() -> TRUE | M97: 45957 | N97: =FALSE() -> FALSE | P97: =FALSE() -> FALSE | R97: =FALSE() -> FALSE | T97: 4 | U97: 45950 | V97: 45971 | W97: Systems | X97: Affinity | Y97: Autonomous Systems | Z97: Series A | AA97: 20000000 | AB97: Cambridge | AC97: Massachusetts | AD97: United States | AE97: United States | AF97: Pass | AG97: 5. Propose Pass | AK97: Madeleine Laitz | AL97: madeleine@engineventures.com | AM97: =TRUE() -> TRUE | AN97: name | AO97: 288108581 | AP97: 222532616 | AQ97: 10/17/2025 | AR97: 10/14/2025 | AS97: 11/07/2025 | AU97: =FALSE() -> FALSE | AW97: P4 - acceptable | AX97: 0 | AY97: =FALSE() -> FALSE | AZ97: =FALSE() -> FALSE | BA97: =FALSE() -> FALSE | BB97: =FALSE() -> FALSE | BC97: =FALSE() -> FALSE | BD97: JuliaHub is a cloud-based platform for scientific computing and modeling, built on the Julia programming language. The platform enables users to develop, deploy, and scale complex computational projects across various industries including pharmaceuticals, aerospace, automotive, and energy. It provides advanced scientific machine learning (SciML) tools, multi-physics simulation capabilities, and an FDA CFR 11-compliant environment for technical computing. JuliaHub supports high-performance computing on multiple CPU and GPU nodes with features for project tracking, code reproducibility, and enterprise-level security.
A98: EV0232 | B98: Kampto | C98: kamptotech.com | D98: =FALSE() -> FALSE | H98: 0 | I98: Preliminary Diligence | J98: 46160 | K98: Preliminary Diligence | L98: =TRUE() -> TRUE | M98: 46160 | N98: =FALSE() -> FALSE | P98: =FALSE() -> FALSE | R98: =FALSE() -> FALSE | T98: 4 | U98: 46160 | V98: 46181 | W98: Health | X98: Affinity | Y98: Human Health | AE98: UNKNOWN | AF98: Pass | AK98: Rachel Field | AL98: rachel@engineventures.com | AM98: =TRUE() -> TRUE | AN98: fuzzy | AO98: 311423561 | AP98: 240855203 | AQ98: 05/13/2026 | AU98: =FALSE() -> FALSE | AW98: P2 - prelim dil, mostly empty | AX98: 3 | AY98: =FALSE() -> FALSE | AZ98: =TRUE() -> TRUE | BA98: =TRUE() -> TRUE | BB98: =TRUE() -> TRUE | BC98: =FALSE() -> FALSE | BD98: Kampto is a deep-tech brain-computer interface company with deep expertise in hardware and software engineering. We build end-to-end BCI systems designed for real-world deployment, centered around a minimally invasive implanted chip that fits between the brain and the dura, conforms to the brain surface, and integrates an unprecedented scale of 65,536 electrodes for recording and stimulation. The system supports wireless power delivery and communication through a wearable relay station. By capturing highly diverse brain data and neural patterns at scale, Kampto unlocks the full potential of AI models running at the edge for next-generation clinical applications across epilepsy, motion, speech, and vision.
A99: EV0242 | B99: Kyber Labs | C99: kyberlabs.ai | D99: =FALSE() -> FALSE | H99: 0 | I99: Preliminary Diligence | J99: 46132 | K99: Preliminary Diligence | L99: =TRUE() -> TRUE | M99: 46132 | N99: =FALSE() -> FALSE | P99: =FALSE() -> FALSE | R99: =FALSE() -> FALSE | T99: 2 | U99: 46132 | V99: 46146 | W99: Systems | X99: Affinity | Y99: Autonomous Systems | Z99: Seed | AA99: 6000000 | AB99: New York | AC99: New York | AD99: United States | AE99: United States | AF99: Initial Evaluation | AG99: 4. Low | AK99: Alaina Hartnett | AL99: alaina.hartnett@engineventures.com | AM99: =TRUE() -> TRUE | AN99: name | AO99: 292366583 | AP99: 239363506 | AQ99: 04/21/2026 | AR99: 04/20/2026 | AS99: 04/20/2026 | AU99: =FALSE() -> FALSE | AW99: P4 - acceptable | AX99: 0 | AY99: =FALSE() -> FALSE | AZ99: =FALSE() -> FALSE | BA99: =FALSE() -> FALSE | BB99: =FALSE() -> FALSE | BC99: =FALSE() -> FALSE | BD99: Kyber Labs is an innovative robotics technology company developing novel artificial muscle fiber actuators for advanced robotic manipulation systems. Their platform focuses on creating low-cost, dexterous robots that can perform human-like tasks in complex environments. By mimicking biological muscle functionality, the company aims to address manual labor shortages through AI-controlled robotic systems that can learn through demonstrations and execute fluid, natural movements not possible with conventional actuation technologies.
A100: EV0248 | B100: Lectrolyst | C100: lectrolyst.com | D100: =FALSE() -> FALSE | H100: 0 | I100: Preliminary Diligence | J100: 46223 | K100: Preliminary Diligence | L100: =TRUE() -> TRUE | M100: 46223 | N100: =FALSE() -> FALSE | P100: =FALSE() -> FALSE | R100: =FALSE() -> FALSE | T100: 2 | U100: 46223 | V100: 46230 | W100: Climate | X100: Affinity | Y100: Energy & Climate | AB100: Wilmington | AC100: Delaware | AD100: United States | AE100: United States | AF100: Pre-Screen | AK100: Deepa Rao | AL100: deepa@engineventures.com | AM100: =TRUE() -> TRUE | AN100: name | AO100: 268334762 | AP100: 246925054 | AQ100: 07/14/2026 | AR100: 12/10/2021 | AS100: 07/17/2026 | AU100: =FALSE() -> FALSE | AW100: P4 - acceptable | AX100: 2 | AY100: =FALSE() -> FALSE | AZ100: =FALSE() -> FALSE | BA100: =TRUE() -> TRUE | BB100: =TRUE() -> TRUE | BC100: =FALSE() -> FALSE | BD100: Upcycling CO2 Into Clean Acetate for Precision Fermentation. Lectrolyst is an innovative electrochemistry company that specializes in transforming carbon dioxide and water into sustainable chemical products using renewable electricity. Their technology enables onsite, scalable chemical transformation solutions ranging from benchtop synthesis to industrial processing facilities. The company focuses on converting carbon waste into essential chemicals, with applications in areas like protein production, electro-agriculture, and sustainable manufacturing, demonstrating advanced electro-chemistry solutions that can be integrated into existing systems.
...

Sheet Discussed Companies
A1: company_id | B1: company_name | C1: times_discussed | D1: first_discussion_date | E1: last_discussion_date | F1: discussion_dates | G1: furthest_stage_on_slides | H1: date_deep_diligence | I1: date_legal | J1: stage | K1: round_size_usd | L1: working_group_final | M1: hq_city | N1: hq_state_province | O1: hq_country | P1: affinity_status | Q1: owner_name
A2: EV0001 | B2: Bristol Superlight | C2: 23 | D2: 45985 | E2: 46160 | F2: 2025-11-24; 2025-12-01; 2025-12-08; 2025-12-15; 2026-01-05; 2026-01-12; 2026-01-20; 2026-01-26; 2026-02-02; 2026-02-09; 2026-02-17; 2026-02-23; 2026-03-02; 2026-03-09; 2026-03-16; 2026-03-23; 2026-03-30; 2026-04-06; 2026-04-13; 2026-04-20; 2026-05-04; 2026-05-11; 2026-05-18 | G2: Legal Diligence / Def Docs | H2: 45985 | I2: 46006 | J2: Series A | K2: 15000000 | L2: Climate; Systems | N2: England | O2: United Kingdom | P2: Invested | Q2: Rachel Field
A3: EV0002 | B3: CorePower Magnetics | C3: 21 | D3: 45944 | E3: 46230 | F3: 2025-10-14; 2025-10-20; 2025-10-27; 2025-11-03; 2025-11-10; 2026-01-26; 2026-03-09; 2026-03-16; 2026-03-23; 2026-05-04; 2026-05-11; 2026-05-18; 2026-05-26; 2026-06-01; 2026-06-08; 2026-06-15; 2026-06-22; 2026-07-06; 2026-07-13; 2026-07-20; 2026-07-27 | G3: Legal Diligence / Def Docs | H3: 45944 | I3: 46153 | L3: Climate | M3: Pittsburgh | N3: Pennsylvania | O3: United States
A4: EV0003 | B4: DG Matrix | C4: 17 | D4: 45944 | E4: 46070 | F4: 2025-10-14; 2025-10-20; 2025-10-27; 2025-11-03; 2025-11-10; 2025-11-17; 2025-11-24; 2025-12-01; 2025-12-08; 2025-12-15; 2026-01-05; 2026-01-12; 2026-01-20; 2026-01-26; 2026-02-02; 2026-02-09; 2026-02-17 | G4: Legal Diligence / Def Docs | H4: 45944 | I4: 45992 | J4: Series A | K4: 60000000 | M4: Morrisville | N4: North Carolina | O4: United States
A5: EV0004 | B5: Alithia | C5: 11 | D5: 46153 | E5: 46258 | F5: 2026-05-11; 2026-05-26; 2026-06-01; 2026-06-08; 2026-06-15; 2026-06-22; 2026-07-06; 2026-07-13; 2026-07-20; 2026-07-27; 2026-08-24 | G5: Deep Diligence | H5: 46168 | J5: Seed | K5: 3000000 | L5: Systems | M5: Holly Springs | N5: North Carolina | O5: United States | P5: Deep Diligence | Q5: Alaina Hartnett
A6: EV0005 | B6: Ovelle | C6: 8 | D6: 46076 | E6: 46132 | F6: 2026-02-23; 2026-03-09; 2026-03-16; 2026-03-23; 2026-03-30; 2026-04-06; 2026-04-13; 2026-04-20 | G6: Legal Diligence / Def Docs | H6: 46097 | I6: 46111 | J6: Seed | K6: 10000000 | L6: Health | M6: Boston | N6: Massachusetts | O6: United States | P6: Loss | Q6: Rachel Field
A7: EV0006 | B7: Ayo Electronics | C7: 6 | D7: 46083 | E7: 46118 | F7: 2026-03-02; 2026-03-09; 2026-03-16; 2026-03-23; 2026-03-30; 2026-04-06 | G7: Legal Diligence / Def Docs | H7: 46083 | I7: 46111 | J7: Seed | K7: 15000000 | L7: Systems | P7: Invested | Q7: Madeleine Laitz
A8: EV0007 | B8: Numem | C8: 6 | D8: 46188 | E8: 46265 | F8: 2026-06-15; 2026-07-27; 2026-08-03; 2026-08-10; 2026-08-24; 2026-08-31 | G8: Deep Diligence | H8: 46251 | J8: Seed | K8: 10000000 | L8: Systems | M8: Sunnyvale | N8: California | O8: United States | P8: Preliminary Diligence | Q8: Alaina Hartnett
A9: EV0008 | B9: Coral Innovations | C9: 5 | D9: 46153 | E9: 46188 | F9: 2026-05-11; 2026-05-18; 2026-05-26; 2026-06-01; 2026-06-15 | G9: Preliminary Diligence | J9: Seed | K9: 4000000 | L9: Climate | M9: Evanston | N9: Illinois | O9: United States | P9: Pass | Q9: Rachel Field
A10: EV0009 | B10: MatNex | C10: 5 | D10: 46223 | E10: 46265 | F10: 2026-07-20; 2026-08-10; 2026-08-17; 2026-08-24; 2026-08-31 | G10: Deep Diligence | H10: 46251 | J10: Series A | K10: 20000000 | L10: Climate; Systems | M10: Cambridge | N10: England | O10: United Kingdom | P10: Preliminary Diligence | Q10: Alaina Hartnett
A11: EV0010 | B11: Skouria | C11: 5 | D11: 46006 | E11: 46055 | F11: 2025-12-15; 2026-01-12; 2026-01-20; 2026-01-26; 2026-02-02 | G11: Deep Diligence | H11: 46027 | J11: Seed | K11: 7000000 | L11: Climate | M11: Philadelphia | N11: Pennsylvania | O11: United States | P11: Wait | Q11: Alaina Hartnett
A12: EV0011 | B12: Teragen | C12: 5 | D12: 45964 | E12: 45992 | F12: 2025-11-03; 2025-11-10; 2025-11-17; 2025-11-24; 2025-12-01 | G12: Deep Diligence | H12: 45978 | L12: Climate
A13: EV0012 | B13: Axiomatic AI | C13: 4 | D13: 45985 | E13: 46006 | F13: 2025-11-24; 2025-12-01; 2025-12-08; 2025-12-15 | G13: Legal Diligence / Def Docs | I13: 46006 | J13: Seed | K13: 10000000 | L13: Systems | M13: Boston | N13: Massachusetts | O13: United States | P13: Invested | Q13: Madeleine Laitz
A14: EV0013 | B14: DINYA | C14: 4 | D14: 45944 | E14: 45971 | F14: 2025-10-14; 2025-10-27; 2025-11-03; 2025-11-10 | G14: Deep Diligence | H14: 45957 | J14: Seed | K14: 5000000 | L14: Health | M14: Cambridge | N14: Massachusetts | O14: United States | P14: Pass | Q14: Deepa Rao
A15: EV0014 | B15: Valor | C15: 4 | D15: 45944 | E15: 45964 | F15: 2025-10-14; 2025-10-20; 2025-10-27; 2025-11-03 | G15: Deep Diligence | H15: 45944 | J15: Seed | K15: 10000000 | L15: Climate | P15: Loss | Q15: Deepa Rao
A16: EV0015 | B16: Walden Robotics | C16: 4 | D16: 46153 | E16: 46174 | F16: 2026-05-11; 2026-05-18; 2026-05-26; 2026-06-01 | G16: Preliminary Diligence | J16: Series A | K16: 250000000 | L16: Systems | M16: Cambridge | N16: Massachusetts | O16: United States | P16: Pass | Q16: Rachel Field
A17: EV0016 | B17: Mattiq | C17: 3 | D17: 46174 | E17: 46216 | F17: 2026-06-01; 2026-06-15; 2026-07-13 | G17: Preliminary Diligence | J17: Seed | K17: 10000000 | L17: Systems | M17: Chicago | N17: Illinois | O17: United States | P17: Preliminary Diligence | Q17: Alaina Hartnett
A18: EV0017 | B18: Attune Neurosci | C18: 2 | D18: 46055 | E18: 46062 | F18: 2026-02-02; 2026-02-09 | G18: Deep Diligence | H18: 46062 | J18: Series A | K18: 20000000 | L18: Health | M18: San Francisco | N18: California | O18: United States | P18: Pass | Q18: Rachel Field
A19: EV0018 | B19: Cetos Water | C19: 2 | D19: 46168 | E19: 46174 | F19: 2026-05-26; 2026-06-01 | G19: Preliminary Diligence | J19: Seed | K19: 7000000 | L19: Climate | M19: New York | N19: New York | O19: United States | P19: Preliminary Diligence | Q19: Alaina Hartnett
A20: EV0019 | B20: CloverLeaf | C20: 2 | D20: 45999 | E20: 46006 | F20: 2025-12-08; 2025-12-15 | G20: Deep Diligence | H20: 46006 | J20: Seed | K20: 12000000 | L20: Health | M20: New Haven | N20: Connecticut | O20: United States | P20: Pass | Q20: Dan Resnicow
A21: EV0020 | B21: 1AU | C21: 1 | D21: 46118 | E21: 46118 | F21: 2026-04-06 | G21: Preliminary Diligence | L21: Systems
A22: EV0021 | B22: Blisk Dynamics | C22: 1 | D22: 46251 | E22: 46251 | F22: 2026-08-17 | G22: Preliminary Diligence | J22: Seed | K22: 10000000 | L22: Systems; Climate | P22: Pass | Q22: Rachel Field
A23: EV0022 | B23: Daedalus | C23: 1 | D23: 46195 | E23: 46195 | F23: 2026-06-22 | G23: Preliminary Diligence | J23: Series B | K23: 15000000 | L23: Systems | M23: San Francisco | N23: California | O23: United States | P23: Pass | Q23: Vinny Beranek
A24: EV0023 | B24: El Agente | C24: 1 | D24: 46055 | E24: 46055 | F24: 2026-02-02 | G24: Preliminary Diligence | J24: Seed | K24: 20000000 | L24: Systems | P24: Wait | Q24: Madeleine Laitz
A25: EV0024 | B25: ExploreTech | C25: 1 | D25: 46230 | E25: 46230 | F25: 2026-07-27 | G25: Preliminary Diligence | J25: Seed | K25: 8000000 | L25: Climate | M25: San Diego | N25: California | O25: United States | P25: Preliminary Diligence | Q25: Alaina Hartnett
A26: EV0025 | B26: Flume | C26: 1 | D26: 46111 | E26: 46111 | F26: 2026-03-30 | G26: Preliminary Diligence | J26: Series A | K26: 15000000 | L26: Systems | M26: New York | N26: New York | O26: United States | P26: Pass | Q26: Madeleine Laitz
A27: EV0027 | B27: Human Bio | C27: 1 | D27: 46048 | E27: 46048 | F27: 2026-01-26 | G27: Preliminary Diligence | J27: Preseed | K27: 12000000 | L27: Health | P27: Pass | Q27: Vinny Beranek
A28: EV0028 | B28: Lila Sciences | C28: 1 | D28: 46083 | E28: 46083 | F28: 2026-03-02 | G28: Deep Diligence | H28: 46083 | L28: Health | M28: Cambridge | N28: Massachusetts | O28: United States
A29: EV0029 | B29: Micrographia Bio | C29: 1 | D29: 45964 | E29: 45964 | F29: 2025-11-03 | G29: Preliminary Diligence | L29: Systems | M29: London | N29: England | O29: United Kingdom | P29: Initial Evaluation
A30: EV0030 | B30: Origins AI | C30: 1 | D30: 46237 | E30: 46237 | F30: 2026-08-03 | G30: Preliminary Diligence | J30: Seed | K30: 15000000 | L30: Systems | P30: Preliminary Diligence | Q30: Richard Collins
A31: EV0031 | B31: Oxipital AI | C31: 1 | D31: 46118 | E31: 46118 | F31: 2026-04-06 | G31: Preliminary Diligence | J31: Series A | K31: 6000000 | L31: Systems | M31: Bedford | N31: Massachusetts | O31: United States | P31: Pass | Q31: Madeleine Laitz
A32: EV0032 | B32: PHNX Materials | C32: 1 | D32: 45957 | E32: 45957 | F32: 2025-10-27 | G32: Preliminary Diligence | J32: Seed | K32: 6000000 | L32: Climate | M32: San Francisco | N32: California | O32: United States | P32: Wait | Q32: Deepa Rao
A33: EV0033 | B33: Prahelika | C33: 1 | D33: 46258 | E33: 46258 | F33: 2026-08-24 | G33: Preliminary Diligence | J33: Seed | K33: 17000000 | L33: Systems | P33: Preliminary Diligence | Q33: Alaina Hartnett
A34: EV0034 | B34: ScaleLight / TopoLight | C34: 1 | D34: 46118 | E34: 46118 | F34: 2026-04-06 | G34: Preliminary Diligence | J34: Seed | K34: 10000000 | L34: Systems | P34: Wait | Q34: Madeleine Laitz
A35: EV0189 | B35: Gravity | C35: 1 | D35: 46118 | E35: 46118 | F35: 2026-04-06 | G35: Preliminary Diligence | J35: Series A | K35: 20000000 | L35: Systems; Climate | M35: New York | N35: New York | O35: United States | P35: Pass | Q35: Alaina Hartnett

Sheet Trend Answers
A1: Trend Answers — live formulas (ADVANCED-STAGE COHORT ONLY, rescoped 2026-09-02)
A2: Every number below is a COUNTIFS against the Companies sheet. Edit Companies, these update. Do not type values here. SCOPE: this workbook was rescoped 2026-09-02 to exclude companies whose furthest stage was NewCo/Fellows, Hold/Nurture, or Meetings This Week -- i.e. companies that never advanced past a first meeting. Only Preliminary Diligence, Deep Diligence, Negotiate/Offer, and Legal Diligence/Def Docs companies remain. 294 of the prior 481 companies were removed on that basis; see READ ME for the full log.
A4: Population control totals
A5: Check these first. If they move, the row set changed and every block below reflects it.
A6: Measure | B6: Count | C6: Note
A7: Companies on slides since Oct 2025 that reached >= Preliminary Diligence | B7: =COUNTA(Companies!$B$2:$B$186) -> 185 | C7: Rescoped 2026-09-02: 294 companies whose furthest stage never left Meetings This Week / Hold-Nurture / NewCo-Fellows were removed. Was 481 pre-rescope, 498 pre-dedup.
A8: Discussed (bold on a slide) | B8: =COUNTIF(Companies!$D$2:$D$186,TRUE()) -> 34 | C8: Population A for the two-population split (unaffected by rescope -- all 34 discussed companies had already reached Prelim+)
A9: Listed only (never bold) | B9: =COUNTIF(Companies!$D$2:$D$186,FALSE()) -> 151 | C9: Population B (was 447 of 481; now 153 of 187, since the removed companies were never bold)
A10: Reached Deep Diligence | B10: =COUNTIF(Companies!$N$2:$N$186,TRUE()) -> 15
A11: Reached Legal | B11: =COUNTIF(Companies!$R$2:$R$186,TRUE()) -> 6
A14: Q1. Geography — companies that REACHED Deep Diligence since Oct 2025
A15: Cohort is reached_deep_diligence = TRUE. Affinity's current-status field shows only 2; this is the full cohort.
A16: State / Region | B16: Companies | C16: Note
A17: Massachusetts | B17: =COUNTIFS(Companies!$N$2:$N$186,TRUE(),Companies!$AC$2:$AC$186,"Massachusetts") -> 5
A18: California | B18: =COUNTIFS(Companies!$N$2:$N$186,TRUE(),Companies!$AC$2:$AC$186,"California") -> 2
A19: North Carolina | B19: =COUNTIFS(Companies!$N$2:$N$186,TRUE(),Companies!$AC$2:$AC$186,"North Carolina") -> 2
A20: Pennsylvania | B20: =COUNTIFS(Companies!$N$2:$N$186,TRUE(),Companies!$AC$2:$AC$186,"Pennsylvania") -> 2
A21: Connecticut | B21: =COUNTIFS(Companies!$N$2:$N$186,TRUE(),Companies!$AC$2:$AC$186,"Connecticut") -> 1
A22: England | B22: =COUNTIFS(Companies!$N$2:$N$186,TRUE(),Companies!$AC$2:$AC$186,"England") -> 2
A23: New York | B23: =COUNTIFS(Companies!$N$2:$N$186,TRUE(),Companies!$AC$2:$AC$186,"New York") -> 0
A24: Texas | B24: =COUNTIFS(Companies!$N$2:$N$186,TRUE(),Companies!$AC$2:$AC$186,"Texas") -> 0
A25: Washington | B25: =COUNTIFS(Companies!$N$2:$N$186,TRUE(),Companies!$AC$2:$AC$186,"Washington") -> 0
A26: Colorado | B26: =COUNTIFS(Companies!$N$2:$N$186,TRUE(),Companies!$AC$2:$AC$186,"Colorado") -> 0
A27: UNKNOWN — geography not captured | B27: =COUNTIFS(Companies!$N$2:$N$186,TRUE(),Companies!$AC$2:$AC$186,"") -> 1 | C27: Close these first. Directly weakens this chart.
A28: Total | B28: =SUM(B17:B27) -> 15
A29: Reconciles to cohort? | B29: =IF(SUM(B17:B27)=COUNTIF(Companies!$N$2:$N$186,TRUE()),"OK","MISMATCH - add a state row") -> OK
A30: Geography coverage | B30: =IF(COUNTIF(Companies!$N$2:$N$186,TRUE())=0,"n/a",1-COUNTIFS(Companies!$N$2:$N$186,TRUE(),Companies!$AC$2:$AC$186,"")/COUNTIF(Companies!$N$2:$N$186,TRUE())) -> 0.93333333 | C30: Quote this alongside the chart
A33: Q1b. Same cohort by country
A34: Country | B34: Companies | C34: Note
A35: United States | B35: =COUNTIFS(Companies!$N$2:$N$186,TRUE(),Companies!$AD$2:$AD$186,"United States") -> 12
A36: United Kingdom | B36: =COUNTIFS(Companies!$N$2:$N$186,TRUE(),Companies!$AD$2:$AD$186,"United Kingdom") -> 2
A37: Canada | B37: =COUNTIFS(Companies!$N$2:$N$186,TRUE(),Companies!$AD$2:$AD$186,"Canada") -> 0
A38: Germany | B38: =COUNTIFS(Companies!$N$2:$N$186,TRUE(),Companies!$AD$2:$AD$186,"Germany") -> 0
A39: Switzerland | B39: =COUNTIFS(Companies!$N$2:$N$186,TRUE(),Companies!$AD$2:$AD$186,"Switzerland") -> 0
A40: Israel | B40: =COUNTIFS(Companies!$N$2:$N$186,TRUE(),Companies!$AD$2:$AD$186,"Israel") -> 0
A41: France | B41: =COUNTIFS(Companies!$N$2:$N$186,TRUE(),Companies!$AD$2:$AD$186,"France") -> 0
A42: UNKNOWN | B42: =COUNTIFS(Companies!$N$2:$N$186,TRUE(),Companies!$AD$2:$AD$186,"") -> 1
A43: Total | B43: =SUM(B35:B42) -> 15
A46: Q2. Stage mix — ALL companies in this cohort (Prelim Diligence and beyond)
A47: Population A+B, rescoped 2026-09-02 to exclude Meetings-This-Week-only companies. Coverage is much better here than in the full 481-company population.
A48: Stage | B48: Companies | C48: % of known | D48: Note
A49: Preseed | B49: =COUNTIF(Companies!$Z$2:$Z$186,"Preseed") -> 14 | C49: =IF(($B$55-$B$54)=0,"",B49/($B$55-$B$54)) -> 0.12844037
A50: Seed | B50: =COUNTIF(Companies!$Z$2:$Z$186,"Seed") -> 67 | C50: =IF(($B$55-$B$54)=0,"",B50/($B$55-$B$54)) -> 0.6146789
A51: Series A | B51: =COUNTIF(Companies!$Z$2:$Z$186,"Series A") -> 23 | C51: =IF(($B$55-$B$54)=0,"",B51/($B$55-$B$54)) -> 0.21100917
A52: Series B | B52: =COUNTIF(Companies!$Z$2:$Z$186,"Series B") -> 5 | C52: =IF(($B$55-$B$54)=0,"",B52/($B$55-$B$54)) -> 0.04587156
A53: Series C | B53: =COUNTIF(Companies!$Z$2:$Z$186,"Series C") -> 0 | C53: =IF(($B$55-$B$54)=0,"",B53/($B$55-$B$54)) -> 0
A54: UNKNOWN — stage not captured | B54: =COUNTIF(Companies!$Z$2:$Z$186,"") -> 76 | C54: Recompute after rescope -- see B54/B55 for current count. Do not present UNKNOWN as a category.
A55: Total population | B55: =COUNTA(Companies!$B$2:$B$186) -> 185
A56: Stage coverage | B56: =1-COUNTIF(Companies!$Z$2:$Z$186,"")/COUNTA(Companies!$B$2:$B$186) -> 0.58918919 | C56: Quote this caveat verbatim
A59: Q2b. Stage mix — DISCUSSED companies only (bold)
A60: Coverage is much better in this population. This is the defensible version of the Series A vs Seed answer.
A61: Stage | B61: Companies | C61: % of known | D61: Note
A62: Preseed | B62: =COUNTIFS(Companies!$D$2:$D$186,TRUE(),Companies!$Z$2:$Z$186,"Preseed") -> 2 | C62: =IF((COUNTIF(Companies!$D$2:$D$186,TRUE())-COUNTIFS(Companies!$D$2:$D$186,TRUE(),Companies!$Z$2:$Z$186,""))=0,"",B62/(COUNTIF(Companies!$D$2:$D$186,TRUE())-COUNTIFS(Companies!$D$2:$D$186,TRUE(),Companies!$Z$2:$Z$186,""))) -> 0.060606061
A63: Seed | B63: =COUNTIFS(Companies!$D$2:$D$186,TRUE(),Companies!$Z$2:$Z$186,"Seed") -> 20 | C63: =IF((COUNTIF(Companies!$D$2:$D$186,TRUE())-COUNTIFS(Companies!$D$2:$D$186,TRUE(),Companies!$Z$2:$Z$186,""))=0,"",B63/(COUNTIF(Companies!$D$2:$D$186,TRUE())-COUNTIFS(Companies!$D$2:$D$186,TRUE(),Companies!$Z$2:$Z$186,""))) -> 0.60606061
A64: Series A | B64: =COUNTIFS(Companies!$D$2:$D$186,TRUE(),Companies!$Z$2:$Z$186,"Series A") -> 9 | C64: =IF((COUNTIF(Companies!$D$2:$D$186,TRUE())-COUNTIFS(Companies!$D$2:$D$186,TRUE(),Companies!$Z$2:$Z$186,""))=0,"",B64/(COUNTIF(Companies!$D$2:$D$186,TRUE())-COUNTIFS(Companies!$D$2:$D$186,TRUE(),Companies!$Z$2:$Z$186,""))) -> 0.27272727
A65: Series B | B65: =COUNTIFS(Companies!$D$2:$D$186,TRUE(),Companies!$Z$2:$Z$186,"Series B") -> 2 | C65: =IF((COUNTIF(Companies!$D$2:$D$186,TRUE())-COUNTIFS(Companies!$D$2:$D$186,TRUE(),Companies!$Z$2:$Z$186,""))=0,"",B65/(COUNTIF(Companies!$D$2:$D$186,TRUE())-COUNTIFS(Companies!$D$2:$D$186,TRUE(),Companies!$Z$2:$Z$186,""))) -> 0.060606061
A66: Series C | B66: =COUNTIFS(Companies!$D$2:$D$186,TRUE(),Companies!$Z$2:$Z$186,"Series C") -> 0 | C66: =IF((COUNTIF(Companies!$D$2:$D$186,TRUE())-COUNTIFS(Companies!$D$2:$D$186,TRUE(),Companies!$Z$2:$Z$186,""))=0,"",B66/(COUNTIF(Companies!$D$2:$D$186,TRUE())-COUNTIFS(Companies!$D$2:$D$186,TRUE(),Companies!$Z$2:$Z$186,""))) -> 0
A67: UNKNOWN | B67: =COUNTIFS(Companies!$D$2:$D$186,TRUE(),Companies!$Z$2:$Z$186,"") -> 1
A68: Total discussed | B68: =COUNTIF(Companies!$D$2:$D$186,TRUE()) -> 34
A69: Stage coverage (discussed) | B69: =1-COUNTIFS(Companies!$D$2:$D$186,TRUE(),Companies!$Z$2:$Z$186,"")/COUNTIF(Companies!$D$2:$D$186,TRUE()) -> 0.97058824
A72: Funnel — furthest stage reached on slides (sanity check only, post-rescope)
A73: NewCo/Fellows, Hold/Nurture, and Meetings This Week will read 0 by construction -- those companies were removed from this workbook on 2026-09-02. Kept for reconciliation: B75:B78 should sum to the total in row 7.
A74: Furthest stage | B74: Companies | C74: Of which discussed | D74: Note
A75: Legal Diligence / Def Docs | B75: =COUNTIF(Companies!$I$2:$I$186,"Legal Diligence / Def Docs") -> 6 | C75: =COUNTIFS(Companies!$I$2:$I$186,"Legal Diligence / Def Docs",Companies!$D$2:$D$186,TRUE()) -> 6
A76: Negotiate / Offer | B76: =COUNTIF(Companies!$I$2:$I$186,"Negotiate / Offer") -> 0 | C76: =COUNTIFS(Companies!$I$2:$I$186,"Negotiate / Offer",Companies!$D$2:$D$186,TRUE()) -> 0
A77: Deep Diligence | B77: =COUNTIF(Companies!$I$2:$I$186,"Deep Diligence") -> 10 | C77: =COUNTIFS(Companies!$I$2:$I$186,"Deep Diligence",Companies!$D$2:$D$186,TRUE()) -> 10
A78: Preliminary Diligence | B78: =COUNTIF(Companies!$I$2:$I$186,"Preliminary Diligence") -> 169 | C78: =COUNTIFS(Companies!$I$2:$I$186,"Preliminary Diligence",Companies!$D$2:$D$186,TRUE()) -> 18
A79: NewCo / Fellows | B79: =COUNTIF(Companies!$I$2:$I$186,"NewCo / Fellows") -> 0 | C79: =COUNTIFS(Companies!$I$2:$I$186,"NewCo / Fellows",Companies!$D$2:$D$186,TRUE()) -> 0
A80: Hold / Nurture | B80: =COUNTIF(Companies!$I$2:$I$186,"Hold / Nurture") -> 0 | C80: =COUNTIFS(Companies!$I$2:$I$186,"Hold / Nurture",Companies!$D$2:$D$186,TRUE()) -> 0
A81: Meetings This Week | B81: =COUNTIF(Companies!$I$2:$I$186,"Meetings This Week") -> 0 | C81: =COUNTIFS(Companies!$I$2:$I$186,"Meetings This Week",Companies!$D$2:$D$186,TRUE()) -> 0
A82: Total | B82: =SUM(B75:B81) -> 185
A83: Reconciles? | B83: =IF(SUM(B75:B81)=COUNTA(Companies!$B$2:$B$186),"OK","MISMATCH") -> OK
A86: Thesis area of the Deep Diligence cohort
A87: Multi-tagged records (e.g. 'Climate; Systems') will not match a single value — see the residual row.
A88: Working group | B88: Companies | C88: Note
A89: Health | B89: =COUNTIFS(Companies!$N$2:$N$186,TRUE(),Companies!$W$2:$W$186,"Health") -> 5
A90: Systems | B90: =COUNTIFS(Companies!$N$2:$N$186,TRUE(),Companies!$W$2:$W$186,"Systems") -> 3
A91: Climate | B91: =COUNTIFS(Companies!$N$2:$N$186,TRUE(),Companies!$W$2:$W$186,"Climate") -> 4
A92: Scale-Up | B92: =COUNTIFS(Companies!$N$2:$N$186,TRUE(),Companies!$W$2:$W$186,"Scale-Up") -> 0
A93: AI for Science | B93: =COUNTIFS(Companies!$N$2:$N$186,TRUE(),Companies!$W$2:$W$186,"AI for Science") -> 0
A94: UNKNOWN | B94: =COUNTIFS(Companies!$N$2:$N$186,TRUE(),Companies!$W$2:$W$186,"") -> 1
A95: Multi-tagged / other (residual) | B95: =COUNTIF(Companies!$N$2:$N$186,TRUE())-SUM(B89:B94) -> 2 | C95: Non-zero means dual-tagged records need a primary-group rule
A98: Caveats to carry onto every slide
A99: • Stage is unknown for a large share of the population — see the coverage % in Q2. UNKNOWN is a gap, not a finding.
A100: • RESOLVED 2026-09-02: 17 duplicate rows (32 involved) merged by shared website; population corrected 498 -> 481. Attune/Attune Neurosci, Cetos Water/Kira, Tulip Biosciences and 12 other pairs consolidated; stage-history totals (appearances, discussed flag, furthest stage) were re-derived from Stage History across all name variants for each merged company, not just copied from the surviving row. See dedup log on READ ME.
A101: • 'Discussed' currently means bold. 136 bold entries are black and 16 are dark red, and the deck legend reads Update | Discussion — confirm whether these are one category or two.
A102: • Three meeting weeks are absent (Dec 15 to Jan 5, Apr 20 to May 4, Jun 22 to Jul 6). Companies appearing only in those weeks are missing.
A103: • P1 worklist: 6 of 14 gaps closed 2026-09-02 via public-source research (Teragen, CorePower Magnetics, Lila Sciences, DG Matrix, Ayo Electronics, Micrographia Bio). DG Matrix and Ayo Electronics are now fully enriched (P1 -> P4). 12 P1 companies remain (4 advanced-stage, 8 discussed); 4 still have no Affinity record at all (CorePower Magnetics, Teragen, Lila Sciences, 1AU) -- create the records rather than matching them.
A104: • RESCOPED 2026-09-02: this workbook now excludes all companies whose furthest slide stage was NewCo/Fellows, Hold/Nurture, or Meetings This Week (294 of 481 post-dedup companies removed). A separate full-population file (including those 294) still exists if you need it -- ask before assuming a company is fully out of the pipeline; several were removed simply for not yet having a second meeting, not because they were passed on.

Sheet Stage History
A1: meeting_date | B1: name_on_slide | C1: stage_on_slide | D1: slide_section | E1: discussed_bold | F1: slide_page
A2: 45944 | B2: Aepnus | C2: Preliminary Diligence | D2: E&C | E2: =FALSE() -> FALSE | F2: 246
A3: 45944 | B3: Aeris | C3: Preliminary Diligence | D3: AS | E3: =FALSE() -> FALSE | F3: 246
A4: 45944 | B4: Alkali Labs | C4: Preliminary Diligence | D4: E&C | E4: =FALSE() -> FALSE | F4: 246
A5: 45944 | B5: Artisan Insight | C5: Preliminary Diligence | D5: AS | E5: =FALSE() -> FALSE | F5: 246
A6: 45944 | B6: ChipX | C6: Preliminary Diligence | D6: AS | E6: =FALSE() -> FALSE | F6: 246
A7: 45944 | B7: Circadian OS | C7: Meetings This Week | D7: Meetings this week | E7: =FALSE() -> FALSE | F7: 246
A8: 45944 | B8: CorePower Magnetics | C8: Deep Diligence | D8: Deep Diligence | E8: =TRUE() -> TRUE | F8: 246
A9: 45944 | B9: DG Matrix | C9: Deep Diligence | D9: Deep Diligence | E9: =TRUE() -> TRUE | F9: 246
A10: 45944 | B10: DINYA | C10: Preliminary Diligence | D10: HH | E10: =TRUE() -> TRUE | F10: 246
A11: 45944 | B11: Emergentia | C11: Preliminary Diligence | D11: AS | E11: =FALSE() -> FALSE | F11: 246
A12: 45944 | B12: FAST Metals | C12: Preliminary Diligence | D12: E&C | E12: =FALSE() -> FALSE | F12: 246
A13: 45944 | B13: Flexnode | C13: Preliminary Diligence | D13: AS | E13: =FALSE() -> FALSE | F13: 246
A14: 45944 | B14: Flip Tx | C14: Preliminary Diligence | D14: HH | E14: =FALSE() -> FALSE | F14: 246
A15: 45944 | B15: Formline Photonics | C15: Preliminary Diligence | D15: AS | E15: =FALSE() -> FALSE | F15: 246
A16: 45944 | B16: Heliux | C16: Preliminary Diligence | D16: AS | E16: =FALSE() -> FALSE | F16: 246
A17: 45944 | B17: IceBox Energy | C17: Preliminary Diligence | D17: E&C | E17: =FALSE() -> FALSE | F17: 246
A18: 45944 | B18: Mursla Bio | C18: Preliminary Diligence | D18: HH | E18: =FALSE() -> FALSE | F18: 246
A19: 45944 | B19: OceanBit | C19: Preliminary Diligence | D19: E&C | E19: =FALSE() -> FALSE | F19: 246
A20: 45944 | B20: Ovelle | C20: Preliminary Diligence | D20: HH | E20: =FALSE() -> FALSE | F20: 246
A21: 45944 | B21: Ovo Labs | C21: Preliminary Diligence | D21: HH | E21: =FALSE() -> FALSE | F21: 246
A22: 45944 | B22: PHNX Materials | C22: Preliminary Diligence | D22: E&C | E22: =FALSE() -> FALSE | F22: 246
... A27: 45944 | B27: Teragen | C27: Preliminary Diligence | D27: E&C | E27: =FALSE() -> FALSE | F27: 246
A28: 45944 | B28: Valor | C28: Deep Diligence | D28: Deep Diligence | E28: =TRUE() -> TRUE | F28: 246
A29: 45950 | B29: Aeris | C29: Preliminary Diligence | D29: AS | E29: =FALSE() -> FALSE | F29: 241
A30: 45950 | B30: Alkali Labs | C30: Preliminary Diligence | D30: E&C | E30: =FALSE() -> FALSE | F30: 241
A31: 45950 | B31: Artisan Insight | C31: Preliminary Diligence | D31: AS | E31: =FALSE() -> FALSE | F31: 241
A32: 45950 | B32: ChipX | C32: Preliminary Diligence | D32: AS | E32: =FALSE() -> FALSE | F32: 241
A33: 45950 | B33: Circadian OS | C33: Preliminary Diligence | D33: HH | E33: =FALSE() -> FALSE | F33: 241
A34: 45950 | B34: CorePower Magnetics | C34: Deep Diligence | D34: Deep Diligence | E34: =TRUE() -> TRUE | F34: 241
A35: 45950 | B35: DG Matrix | C35: Negotiate / Offer | D35: Negotiate / Offer | E35: =TRUE() -> TRUE | F35: 241
A36: 45950 | B36: DINYA | C36: Preliminary Diligence | D36: HH | E36: =FALSE() -> FALSE | F36: 241
A37: 45950 | B37: FAST Metals | C37: Preliminary Diligence | D37: E&C | E37: =FALSE() -> FALSE | F37: 241
A38: 45950 | B38: Flexnode | C38: Preliminary Diligence | D38: AS | E38: =FALSE() -> FALSE | F38: 241
A39: 45950 | B39: Flip Tx | C39: Preliminary Diligence | D39: HH | E39: =FALSE() -> FALSE | F39: 241
A40: 45950 | B40: Formline Photonics | C40: Preliminary Diligence | D40: AS | E40: =FALSE() -> FALSE | F40: 241
A41: 45950 | B41: Heliux | C41: Preliminary Diligence | D41: AS | E41: =FALSE() -> FALSE | F41: 241
A42: 45950 | B42: IceBox Energy | C42: Preliminary Diligence | D42: E&C | E42: =FALSE() -> FALSE | F42: 241
A43: 45950 | B43: JuliaHub | C43: Meetings This Week | D43: Meetings this week | E43: =FALSE() -> FALSE | F43: 241
A44: 45950 | B44: Mana Battery | C44: Preliminary Diligence | D44: E&C | E44: =FALSE() -> FALSE | F44: 241
A45: 45950 | B45: Mursla Bio | C45: Preliminary Diligence | D45: HH | E45: =FALSE() -> FALSE | F45: 241
A46: 45950 | B46: Nouxel | C46: Preliminary Diligence | D46: AS | E46: =FALSE() -> FALSE | F46: 241
A47: 45950 | B47: OceanBit | C47: Meetings This Week | D47: Meetings this week | E47: =FALSE() -> FALSE | F47: 241
... A59: 45950 | B59: Teragen | C59: Preliminary Diligence | D59: E&C | E59: =FALSE() -> FALSE | F59: 241
A60: 45950 | B60: Valor | C60: Deep Diligence | D60: Deep Diligence | E60: =TRUE() -> TRUE | F60: 241
A61: 45957 | B61: Aeris | C61: Preliminary Diligence | D61: AS | E61: =FALSE() -> FALSE | F61: 234
A62: 45957 | B62: Artisan Insight | C62: Preliminary Diligence | D62: AS | E62: =FALSE() -> FALSE | F62: 234
A63: 45957 | B63: Bristol Superlight | C63: Preliminary Diligence | D63: E&C | E63: =FALSE() -> FALSE | F63: 234
A64: 45957 | B64: ChipX | C64: Preliminary Diligence | D64: AS | E64: =FALSE() -> FALSE | F64: 234
A65: 45957 | B65: Circadian OS | C65: Preliminary Diligence | D65: HH | E65: =FALSE() -> FALSE | F65: 234
A66: 45957 | B66: CorePower Magnetics | C66: Deep Diligence | D66: Deep Diligence | E66: =TRUE() -> TRUE | F66: 234
A67: 45957 | B67: DG Matrix | C67: Negotiate / Offer | D67: Negotiate / Offer | E67: =TRUE() -> TRUE | F67: 234
A68: 45957 | B68: DINYA | C68: Deep Diligence | D68: Deep Diligence | E68: =TRUE() -> TRUE | F68: 234
A69: 45957 | B69: Flexnode | C69: Preliminary Diligence | D69: AS | E69: =FALSE() -> FALSE | F69: 234
A70: 45957 | B70: Formline Photonics | C70: Preliminary Diligence | D70: AS | E70: =FALSE() -> FALSE | F70: 234
A71: 45957 | B71: Heliux | C71: Preliminary Diligence | D71: AS | E71: =FALSE() -> FALSE | F71: 234
A72: 45957 | B72: JuliaHub | C72: Preliminary Diligence | D72: AS | E72: =FALSE() -> FALSE | F72: 234
A73: 45957 | B73: Lila Sciences | C73: Preliminary Diligence | D73: HH | E73: =FALSE() -> FALSE | F73: 234
A74: 45957 | B74: Micrographia Bio | C74: Preliminary Diligence | D74: HH | E74: =FALSE() -> FALSE | F74: 234
A75: 45957 | B75: Mursla Bio | C75: Preliminary Diligence | D75: HH | E75: =FALSE() -> FALSE | F75: 234
A76: 45957 | B76: Nouxel | C76: Preliminary Diligence | D76: AS | E76: =FALSE() -> FALSE | F76: 234
A77: 45957 | B77: OceanBit | C77: Meetings This Week | D77: Meetings this week | E77: =FALSE() -> FALSE | F77: 234
A78: 45957 | B78: OceanBit | C78: Preliminary Diligence | D78: E&C | E78: =FALSE() -> FALSE | F78: 234
A79: 45957 | B79: Ovelle | C79: Preliminary Diligence | D79: HH | E79: =FALSE() -> FALSE | F79: 234
A80: 45957 | B80: Ovo Labs | C80: Preliminary Diligence | D80: HH | E80: =FALSE() -> FALSE | F80: 234
A81: 45957 | B81: PHNX Materials | C81: Preliminary Diligence | D81: E&C | E81: =TRUE() -> TRUE | F81: 234
A82: 45957 | B82: Plaid Semi | C82: Meetings This Week | D82: Meetings this week | E82: =FALSE() -> FALSE | F82: 234
A83: 45957 | B83: Plaid Semi | C83: Preliminary Diligence | D83: AS | E83: =FALSE() -> FALSE | F83: 234
A84: 45957 | B84: Recupere | C84: Preliminary Diligence | D84: E&C | E84: =FALSE() -> FALSE | F84: 234
A85: 45957 | B85: SceniX | C85: Meetings This Week | D85: Meetings this week | E85: =FALSE() -> FALSE | F85: 234
A86: 45957 | B86: SceniX | C86: Preliminary Diligence | D86: AS | E86: =FALSE() -> FALSE | F86: 234
A87: 45957 | B87: SeamoreTech | C87: Meetings This Week | D87: Meetings this week | E87: =FALSE() -> FALSE | F87: 234
A88: 45957 | B88: SeamoreTech | C88: Preliminary Diligence | D88: E&C | E88: =FALSE() -> FALSE | F88: 234
A89: 45957 | B89: Skouria | C89: Meetings This Week | D89: Meetings this week | E89: =FALSE() -> FALSE | F89: 234
A90: 45957 | B90: Teragen | C90: Preliminary Diligence | D90: E&C | E90: =FALSE() -> FALSE | F90: 234
A91: 45957 | B91: Valor | C91: Deep Diligence | D91: Deep Diligence | E91: =TRUE() -> TRUE | F91: 234
A92: 45964 | B92: Aeris | C92: Preliminary Diligence | D92: AS | E92: =FALSE() -> FALSE | F92: 216
A93: 45964 | B93: Artisan Insight | C93: Preliminary Diligence | D93: AS | E93: =FALSE() -> FALSE | F93: 216
A94: 45964 | B94: Bristol Superlight | C94: Preliminary Diligence | D94: E&C | E94: =FALSE() -> FALSE | F94: 216
A95: 45964 | B95: ChipX | C95: Preliminary Diligence | D95: AS | E95: =FALSE() -> FALSE | F95: 216
A96: 45964 | B96: Circadian OS | C96: Preliminary Diligence | D96: HH | E96: =FALSE() -> FALSE | F96: 216
A97: 45964 | B97: CorePower Magnetics | C97: Deep Diligence | D97: Deep Diligence | E97: =TRUE() -> TRUE | F97: 216
A98: 45964 | B98: DG Matrix | C98: Negotiate / Offer | D98: Negotiate / Offer | E98: =TRUE() -> TRUE | F98: 216
A99: 45964 | B99: DINYA | C99: Deep Diligence | D99: Deep Diligence | E99: =TRUE() -> TRUE | F99: 216
A100: 45964 | B100: Formline Photonics | C100: Preliminary Diligence | D100: AS | E100: =FALSE() -> FALSE | F100: 216
A101: 45964 | B101: JuliaHub | C101: Preliminary Diligence | D101: AS | E101: =FALSE() -> FALSE | F101: 216
A102: 45964 | B102: Lila Sciences | C102: Preliminary Diligence | D102: HH | E102: =FALSE() -> FALSE | F102: 216
A103: 45964 | B103: Material Difference | C103: Preliminary Diligence | D103: E&C | E103: =FALSE() -> FALSE | F103: 216
A104: 45964 | B104: Micrographia Bio | C104: Preliminary Diligence | D104: HH | E104: =TRUE() -> TRUE | F104: 216
A105: 45964 | B105: Mursla Bio | C105: Preliminary Diligence | D105: HH | E105: =FALSE() -> FALSE | F105: 216
A106: 45964 | B106: Nouxel | C106: Preliminary Diligence | D106: AS | E106: =FALSE() -> FALSE | F106: 216
A107: 45964 | B107: Ovelle | C107: Preliminary Diligence | D107: HH | E107: =FALSE() -> FALSE | F107: 216
A108: 45964 | B108: Ovo Labs | C108: Preliminary Diligence | D108: HH | E108: =FALSE() -> FALSE | F108: 216
A109: 45964 | B109: PHNX Materials | C109: Preliminary Diligence | D109: E&C | E109: =FALSE() -> FALSE | F109: 216
A110: 45964 | B110: Plaid Semi | C110: Meetings This Week | D110: Meetings this week | E110: =FALSE() -> FALSE | F110: 216
A111: 45964 | B111: Plaid Semi | C111: Preliminary Diligence | D111: AS | E111: =FALSE() -> FALSE | F111: 216
A112: 45964 | B112: Recupere | C112: Preliminary Diligence | D112: E&C | E112: =FALSE() -> FALSE | F112: 216
A113: 45964 | B113: SceniX | C113: Meetings This Week | D113: Meetings this week | E113: =FALSE() -> FALSE | F113: 216
A114: 45964 | B114: SceniX | C114: Preliminary Diligence | D114: AS | E114: =FALSE() -> FALSE | F114: 216
A115: 45964 | B115: SeamoreTech | C115: Preliminary Diligence | D115: E&C | E115: =FALSE() -> FALSE | F115: 216
...

Sheet Enrichment Worklist
A1: company_id | B1: company_name | C1: enrichment_priority | D1: enrichment_gaps | E1: furthest_stage_on_slides | F1: discussed_in_new_deal_meeting | G1: in_affinity | H1: needs_website | I1: needs_geography | J1: needs_stage | K1: needs_round_size | L1: needs_owner | M1: website | N1: hq_country | O1: stage | P1: owner_name
A2: EV0002 | B2: CorePower Magnetics | C2: P1 - advanced stage, incomplete | D2: 2 | E2: Legal Diligence / Def Docs | F2: =TRUE() -> TRUE | G2: =FALSE() -> FALSE | H2: =FALSE() -> FALSE | I2: =FALSE() -> FALSE | J2: =FALSE() -> FALSE | K2: =TRUE() -> TRUE | L2: =TRUE() -> TRUE | M2: corepowermagnetics.com | N2: United States | O2: Series A
A3: EV0011 | B3: Teragen | C3: P1 - advanced stage, incomplete | D3: 1 | E3: Deep Diligence | F3: =TRUE() -> TRUE | G3: =FALSE() -> FALSE | H3: =FALSE() -> FALSE | I3: =FALSE() -> FALSE | J3: =FALSE() -> FALSE | K3: =FALSE() -> FALSE | L3: =TRUE() -> TRUE | M3: teragenenergy.com | N3: United States | O3: Preseed
A4: EV0014 | B4: Valor | C4: P1 - advanced stage, incomplete | D4: 2 | E4: Deep Diligence | F4: =TRUE() -> TRUE | G4: =TRUE() -> TRUE | H4: =TRUE() -> TRUE | I4: =TRUE() -> TRUE | J4: =FALSE() -> FALSE | K4: =FALSE() -> FALSE | L4: =FALSE() -> FALSE | O4: Seed | P4: Deepa Rao
A5: EV0028 | B5: Lila Sciences | C5: P1 - advanced stage, incomplete | D5: 1 | E5: Deep Diligence | F5: =TRUE() -> TRUE | G5: =FALSE() -> FALSE | H5: =FALSE() -> FALSE | I5: =FALSE() -> FALSE | J5: =FALSE() -> FALSE | K5: =FALSE() -> FALSE | L5: =TRUE() -> TRUE | M5: lila.ai | N5: United States | O5: Series B
A6: EV0020 | B6: 1AU | C6: P1 - discussed, incomplete | D6: 5 | E6: Preliminary Diligence | F6: =TRUE() -> TRUE | G6: =FALSE() -> FALSE | H6: =TRUE() -> TRUE | I6: =TRUE() -> TRUE | J6: =TRUE() -> TRUE | K6: =TRUE() -> TRUE | L6: =TRUE() -> TRUE
A7: EV0021 | B7: Blisk Dynamics | C7: P1 - discussed, incomplete | D7: 1 | E7: Preliminary Diligence | F7: =TRUE() -> TRUE | G7: =TRUE() -> TRUE | H7: =FALSE() -> FALSE | I7: =TRUE() -> TRUE | J7: =FALSE() -> FALSE | K7: =FALSE() -> FALSE | L7: =FALSE() -> FALSE | M7: bliskdynamics.com | O7: Seed | P7: Rachel Field
A8: EV0023 | B8: El Agente | C8: P1 - discussed, incomplete | D8: 2 | E8: Preliminary Diligence | F8: =TRUE() -> TRUE | G8: =TRUE() -> TRUE | H8: =TRUE() -> TRUE | I8: =TRUE() -> TRUE | J8: =FALSE() -> FALSE | K8: =FALSE() -> FALSE | L8: =FALSE() -> FALSE | O8: Seed | P8: Madeleine Laitz
A9: EV0027 | B9: Human Bio | C9: P1 - discussed, incomplete | D9: 1 | E9: Preliminary Diligence | F9: =TRUE() -> TRUE | G9: =TRUE() -> TRUE | H9: =FALSE() -> FALSE | I9: =TRUE() -> TRUE | J9: =FALSE() -> FALSE | K9: =FALSE() -> FALSE | L9: =FALSE() -> FALSE | M9: humanbio.tech | O9: Preseed | P9: Vinny Beranek
A10: EV0029 | B10: Micrographia Bio | C10: P1 - discussed, incomplete | D10: 2 | E10: Preliminary Diligence | F10: =TRUE() -> TRUE | G10: =TRUE() -> TRUE | H10: =FALSE() -> FALSE | I10: =FALSE() -> FALSE | J10: =FALSE() -> FALSE | K10: =TRUE() -> TRUE | L10: =TRUE() -> TRUE | M10: micrographiabio.com | N10: United Kingdom | O10: Seed
A11: EV0030 | B11: Origins AI | C11: P1 - discussed, incomplete | D11: 2 | E11: Preliminary Diligence | F11: =TRUE() -> TRUE | G11: =TRUE() -> TRUE | H11: =TRUE() -> TRUE | I11: =TRUE() -> TRUE | J11: =FALSE() -> FALSE | K11: =FALSE() -> FALSE | L11: =FALSE() -> FALSE | O11: Seed | P11: Richard Collins
A12: EV0033 | B12: Prahelika | C12: P1 - discussed, incomplete | D12: 1 | E12: Preliminary Diligence | F12: =TRUE() -> TRUE | G12: =TRUE() -> TRUE | H12: =FALSE() -> FALSE | I12: =TRUE() -> TRUE | J12: =FALSE() -> FALSE | K12: =FALSE() -> FALSE | L12: =FALSE() -> FALSE | M12: prahelika.com | O12: Seed | P12: Alaina Hartnett
A13: EV0034 | B13: ScaleLight / TopoLight | C13: P1 - discussed, incomplete | D13: 2 | E13: Preliminary Diligence | F13: =TRUE() -> TRUE | G13: =TRUE() -> TRUE | H13: =TRUE() -> TRUE | I13: =TRUE() -> TRUE | J13: =FALSE() -> FALSE | K13: =FALSE() -> FALSE | L13: =FALSE() -> FALSE | O13: Seed | P13: Madeleine Laitz
A14: EV0044 | B14: Aepnus | C14: P2 - prelim dil, mostly empty | D14: 5 | E14: Preliminary Diligence | F14: =FALSE() -> FALSE | G14: =FALSE() -> FALSE | H14: =TRUE() -> TRUE | I14: =TRUE() -> TRUE | J14: =TRUE() -> TRUE | K14: =TRUE() -> TRUE | L14: =TRUE() -> TRUE
A15: EV0045 | B15: Aeris | C15: P2 - prelim dil, mostly empty | D15: 5 | E15: Preliminary Diligence | F15: =FALSE() -> FALSE | G15: =FALSE() -> FALSE | H15: =TRUE() -> TRUE | I15: =TRUE() -> TRUE | J15: =TRUE() -> TRUE | K15: =TRUE() -> TRUE | L15: =TRUE() -> TRUE
A16: EV0052 | B16: Alkali Labs | C16: P2 - prelim dil, mostly empty | D16: 5 | E16: Preliminary Diligence | F16: =FALSE() -> FALSE | G16: =FALSE() -> FALSE | H16: =TRUE() -> TRUE | I16: =TRUE() -> TRUE | J16: =TRUE() -> TRUE | K16: =TRUE() -> TRUE | L16: =TRUE() -> TRUE
A17: EV0064 | B17: Anywhere robotics | C17: P2 - prelim dil, mostly empty | D17: 5 | E17: Preliminary Diligence | F17: =FALSE() -> FALSE | G17: =FALSE() -> FALSE | H17: =TRUE() -> TRUE | I17: =TRUE() -> TRUE | J17: =TRUE() -> TRUE | K17: =TRUE() -> TRUE | L17: =TRUE() -> TRUE
A18: EV0068 | B18: Arinna | C18: P2 - prelim dil, mostly empty | D18: 5 | E18: Preliminary Diligence | F18: =FALSE() -> FALSE | G18: =FALSE() -> FALSE | H18: =TRUE() -> TRUE | I18: =TRUE() -> TRUE | J18: =TRUE() -> TRUE | K18: =TRUE() -> TRUE | L18: =TRUE() -> TRUE
A19: EV0074 | B19: Ascension | C19: P2 - prelim dil, mostly empty | D19: 5 | E19: Preliminary Diligence | F19: =FALSE() -> FALSE | G19: =TRUE() -> TRUE | H19: =TRUE() -> TRUE | I19: =TRUE() -> TRUE | J19: =TRUE() -> TRUE | K19: =TRUE() -> TRUE | L19: =TRUE() -> TRUE
A20: EV0080 | B20: Attune Tx | C20: P2 - prelim dil, mostly empty | D20: 5 | E20: Preliminary Diligence | F20: =FALSE() -> FALSE | G20: =FALSE() -> FALSE | H20: =TRUE() -> TRUE | I20: =TRUE() -> TRUE | J20: =TRUE() -> TRUE | K20: =TRUE() -> TRUE | L20: =TRUE() -> TRUE
A21: EV0086 | B21: Ayo Compute | C21: P2 - prelim dil, mostly empty | D21: 5 | E21: Preliminary Diligence | F21: =FALSE() -> FALSE | G21: =FALSE() -> FALSE | H21: =TRUE() -> TRUE | I21: =TRUE() -> TRUE | J21: =TRUE() -> TRUE | K21: =TRUE() -> TRUE | L21: =TRUE() -> TRUE
A22: EV0091 | B22: Beacon Photonics | C22: P2 - prelim dil, mostly empty | D22: 5 | E22: Preliminary Diligence | F22: =FALSE() -> FALSE | G22: =FALSE() -> FALSE | H22: =TRUE() -> TRUE | I22: =TRUE() -> TRUE | J22: =TRUE() -> TRUE | K22: =TRUE() -> TRUE | L22: =TRUE() -> TRUE
A23: EV0099 | B23: Blixt | C23: P2 - prelim dil, mostly empty | D23: 5 | E23: Preliminary Diligence | F23: =FALSE() -> FALSE | G23: =FALSE() -> FALSE | H23: =TRUE() -> TRUE | I23: =TRUE() -> TRUE | J23: =TRUE() -> TRUE | K23: =TRUE() -> TRUE | L23: =TRUE() -> TRUE
A24: EV0107 | B24: Cala | C24: P2 - prelim dil, mostly empty | D24: 5 | E24: Preliminary Diligence | F24: =FALSE() -> FALSE | G24: =FALSE() -> FALSE | H24: =TRUE() -> TRUE | I24: =TRUE() -> TRUE | J24: =TRUE() -> TRUE | K24: =TRUE() -> TRUE | L24: =TRUE() -> TRUE
A25: EV0122 | B25: Cetos / Kira /Eden Tech | C25: P2 - prelim dil, mostly empty | D25: 5 | E25: Preliminary Diligence | F25: =FALSE() -> FALSE | G25: =FALSE() -> FALSE | H25: =TRUE() -> TRUE | I25: =TRUE() -> TRUE | J25: =TRUE() -> TRUE | K25: =TRUE() -> TRUE | L25: =TRUE() -> TRUE
A26: EV0134 | B26: CypherSonic Labs | C26: P2 - prelim dil, mostly empty | D26: 5 | E26: Preliminary Diligence | F26: =FALSE() -> FALSE | G26: =FALSE() -> FALSE | H26: =TRUE() -> TRUE | I26: =TRUE() -> TRUE | J26: =TRUE() -> TRUE | K26: =TRUE() -> TRUE | L26: =TRUE() -> TRUE
A27: EV0135 | B27: Dario NewCo | C27: P2 - prelim dil, mostly empty | D27: 5 | E27: Preliminary Diligence | F27: =FALSE() -> FALSE | G27: =FALSE() -> FALSE | H27: =TRUE() -> TRUE | I27: =TRUE() -> TRUE | J27: =TRUE() -> TRUE | K27: =TRUE() -> TRUE | L27: =TRUE() -> TRUE
A28: EV0138 | B28: Deepankur NewCo | C28: P2 - prelim dil, mostly empty | D28: 5 | E28: Preliminary Diligence | F28: =FALSE() -> FALSE | G28: =FALSE() -> FALSE | H28: =TRUE() -> TRUE | I28: =TRUE() -> TRUE | J28: =TRUE() -> TRUE | K28: =TRUE() -> TRUE | L28: =TRUE() -> TRUE
A29: EV0143 | B29: Drift Energy | C29: P2 - prelim dil, mostly empty | D29: 5 | E29: Preliminary Diligence | F29: =FALSE() -> FALSE | G29: =FALSE() -> FALSE | H29: =TRUE() -> TRUE | I29: =TRUE() -> TRUE | J29: =TRUE() -> TRUE | K29: =TRUE() -> TRUE | L29: =TRUE() -> TRUE
A30: EV0144 | B30: Dunia.ai | C30: P2 - prelim dil, mostly empty | D30: 5 | E30: Preliminary Diligence | F30: =FALSE() -> FALSE | G30: =FALSE() -> FALSE | H30: =TRUE() -> TRUE | I30: =TRUE() -> TRUE | J30: =TRUE() -> TRUE | K30: =TRUE() -> TRUE | L30: =TRUE() -> TRUE
A31: EV0153 | B31: Ekion | C31: P2 - prelim dil, mostly empty | D31: 5 | E31: Preliminary Diligence | F31: =FALSE() -> FALSE | G31: =FALSE() -> FALSE | H31: =TRUE() -> TRUE | I31: =TRUE() -> TRUE | J31: =TRUE() -> TRUE | K31: =TRUE() -> TRUE | L31: =TRUE() -> TRUE
... A33: EV0158 | B33: EnCharge | C33: P2 - prelim dil, mostly empty | D33: 5 | E33: Preliminary Diligence | F33: =FALSE() -> FALSE | G33: =FALSE() -> FALSE | H33: =TRUE() -> TRUE | I33: =TRUE() -> TRUE | J33: =TRUE() -> TRUE | K33: =TRUE() -> TRUE | L33: =TRUE() -> TRUE
A34: EV0164 | B34: Externa | C34: P2 - prelim dil, mostly empty | D34: 3 | E34: Preliminary Diligence | F34: =FALSE() -> FALSE | G34: =TRUE() -> TRUE | H34: =FALSE() -> FALSE | I34: =FALSE() -> FALSE | J34: =TRUE() -> TRUE | K34: =TRUE() -> TRUE | L34: =TRUE() -> TRUE | M34: xterna.bio | N34: United Kingdom
A35: EV0165 | B35: FAST Metals | C35: P2 - prelim dil, mostly empty | D35: 5 | E35: Preliminary Diligence | F35: =FALSE() -> FALSE | G35: =FALSE() -> FALSE | H35: =TRUE() -> TRUE | I35: =TRUE() -> TRUE | J35: =TRUE() -> TRUE | K35: =TRUE() -> TRUE | L35: =TRUE() -> TRUE
A36: EV0166 | B36: FLUIX AI | C36: P2 - prelim dil, mostly empty | D36: 5 | E36: Preliminary Diligence | F36: =FALSE() -> FALSE | G36: =FALSE() -> FALSE | H36: =TRUE() -> TRUE | I36: =TRUE() -> TRUE | J36: =TRUE() -> TRUE | K36: =TRUE() -> TRUE | L36: =TRUE() -> TRUE
A37: EV0169 | B37: Flip Tx | C37: P2 - prelim dil, mostly empty | D37: 5 | E37: Preliminary Diligence | F37: =FALSE() -> FALSE | G37: =FALSE() -> FALSE | H37: =TRUE() -> TRUE | I37: =TRUE() -> TRUE | J37: =TRUE() -> TRUE | K37: =TRUE() -> TRUE | L37: =TRUE() -> TRUE
A38: EV0171 | B38: Flow Compute | C38: P2 - prelim dil, mostly empty | D38: 5 | E38: Preliminary Diligence | F38: =FALSE() -> FALSE | G38: =FALSE() -> FALSE | H38: =TRUE() -> TRUE | I38: =TRUE() -> TRUE | J38: =TRUE() -> TRUE | K38: =TRUE() -> TRUE | L38: =TRUE() -> TRUE
A39: EV0175 | B39: FluidInsight | C39: P2 - prelim dil, mostly empty | D39: 5 | E39: Preliminary Diligence | F39: =FALSE() -> FALSE | G39: =FALSE() -> FALSE | H39: =TRUE() -> TRUE | I39: =TRUE() -> TRUE | J39: =TRUE() -> TRUE | K39: =TRUE() -> TRUE | L39: =TRUE() -> TRUE
A40: EV0177 | B40: Formline Photonics | C40: P2 - prelim dil, mostly empty | D40: 5 | E40: Preliminary Diligence | F40: =FALSE() -> FALSE | G40: =FALSE() -> FALSE | H40: =TRUE() -> TRUE | I40: =TRUE() -> TRUE | J40: =TRUE() -> TRUE | K40: =TRUE() -> TRUE | L40: =TRUE() -> TRUE
A41: EV0179 | B41: Found Industries | C41: P2 - prelim dil, mostly empty | D41: 5 | E41: Preliminary Diligence | F41: =FALSE() -> FALSE | G41: =FALSE() -> FALSE | H41: =TRUE() -> TRUE | I41: =TRUE() -> TRUE | J41: =TRUE() -> TRUE | K41: =TRUE() -> TRUE | L41: =TRUE() -> TRUE
A42: EV0197 | B42: Heliux | C42: P2 - prelim dil, mostly empty | D42: 5 | E42: Preliminary Diligence | F42: =FALSE() -> FALSE | G42: =FALSE() -> FALSE | H42: =TRUE() -> TRUE | I42: =TRUE() -> TRUE | J42: =TRUE() -> TRUE | K42: =TRUE() -> TRUE | L42: =TRUE() -> TRUE
A43: EV0208 | B43: Hydram | C43: P2 - prelim dil, mostly empty | D43: 5 | E43: Preliminary Diligence | F43: =FALSE() -> FALSE | G43: =FALSE() -> FALSE | H43: =TRUE() -> TRUE | I43: =TRUE() -> TRUE | J43: =TRUE() -> TRUE | K43: =TRUE() -> TRUE | L43: =TRUE() -> TRUE
A44: EV0223 | B44: Inlyte Energy | C44: P2 - prelim dil, mostly empty | D44: 5 | E44: Preliminary Diligence | F44: =FALSE() -> FALSE | G44: =FALSE() -> FALSE | H44: =TRUE() -> TRUE | I44: =TRUE() -> TRUE | J44: =TRUE() -> TRUE | K44: =TRUE() -> TRUE | L44: =TRUE() -> TRUE
A45: EV0232 | B45: Kampto | C45: P2 - prelim dil, mostly empty | D45: 3 | E45: Preliminary Diligence | F45: =FALSE() -> FALSE | G45: =TRUE() -> TRUE | H45: =FALSE() -> FALSE | I45: =TRUE() -> TRUE | J45: =TRUE() -> TRUE | K45: =TRUE() -> TRUE | L45: =FALSE() -> FALSE | M45: kamptotech.com | P45: Rachel Field
A46: EV0254 | B46: LightLogiq | C46: P2 - prelim dil, mostly empty | D46: 3 | E46: Preliminary Diligence | F46: =FALSE() -> FALSE | G46: =TRUE() -> TRUE | H46: =FALSE() -> FALSE | I46: =TRUE() -> TRUE | J46: =TRUE() -> TRUE | K46: =TRUE() -> TRUE | L46: =FALSE() -> FALSE | M46: lightlogiq.co | P46: Alaina Hartnett
A47: EV0257 | B47: Lila | C47: P2 - prelim dil, mostly empty | D47: 5 | E47: Preliminary Diligence | F47: =FALSE() -> FALSE | G47: =FALSE() -> FALSE | H47: =TRUE() -> TRUE | I47: =TRUE() -> TRUE | J47: =TRUE() -> TRUE | K47: =TRUE() -> TRUE | L47: =TRUE() -> TRUE
A48: EV0265 | B48: Mach Electric | C48: P2 - prelim dil, mostly empty | D48: 5 | E48: Preliminary Diligence | F48: =FALSE() -> FALSE | G48: =FALSE() -> FALSE | H48: =TRUE() -> TRUE | I48: =TRUE() -> TRUE | J48: =TRUE() -> TRUE | K48: =TRUE() -> TRUE | L48: =TRUE() -> TRUE
A49: EV0269 | B49: Mana Battery | C49: P2 - prelim dil, mostly empty | D49: 5 | E49: Preliminary Diligence | F49: =FALSE() -> FALSE | G49: =FALSE() -> FALSE | H49: =TRUE() -> TRUE | I49: =TRUE() -> TRUE | J49: =TRUE() -> TRUE | K49: =TRUE() -> TRUE | L49: =TRUE() -> TRUE
A50: EV0273 | B50: Matta AI | C50: P2 - prelim dil, mostly empty | D50: 5 | E50: Preliminary Diligence | F50: =FALSE() -> FALSE | G50: =FALSE() -> FALSE | H50: =TRUE() -> TRUE | I50: =TRUE() -> TRUE | J50: =TRUE() -> TRUE | K50: =TRUE() -> TRUE | L50: =TRUE() -> TRUE
A51: EV0287 | B51: Mobius Bio | C51: P2 - prelim dil, mostly empty | D51: 5 | E51: Preliminary Diligence | F51: =FALSE() -> FALSE | G51: =FALSE() -> FALSE | H51: =TRUE() -> TRUE | I51: =TRUE() -> TRUE | J51: =TRUE() -> TRUE | K51: =TRUE() -> TRUE | L51: =TRUE() -> TRUE
A52: EV0305 | B52: Neurofold | C52: P2 - prelim dil, mostly empty | D52: 3 | E52: Preliminary Diligence | F52: =FALSE() -> FALSE | G52: =TRUE() -> TRUE | H52: =FALSE() -> FALSE | I52: =TRUE() -> TRUE | J52: =TRUE() -> TRUE | K52: =TRUE() -> TRUE | L52: =FALSE() -> FALSE | M52: neurofold.com | P52: Vinny Beranek
A53: EV0309 | B53: Nimble Precision | C53: P2 - prelim dil, mostly empty | D53: 5 | E53: Preliminary Diligence | F53: =FALSE() -> FALSE | G53: =FALSE() -> FALSE | H53: =TRUE() -> TRUE | I53: =TRUE() -> TRUE | J53: =TRUE() -> TRUE | K53: =TRUE() -> TRUE | L53: =TRUE() -> TRUE
A54: EV0332 | B54: Parallel Robotics | C54: P2 - prelim dil, mostly empty | D54: 5 | E54: Preliminary Diligence | F54: =FALSE() -> FALSE | G54: =FALSE() -> FALSE | H54: =TRUE() -> TRUE | I54: =TRUE() -> TRUE | J54: =TRUE() -> TRUE | K54: =TRUE() -> TRUE | L54: =TRUE() -> TRUE
A55: EV0336 | B55: PhotonIDs | C55: P2 - prelim dil, mostly empty | D55: 5 | E55: Preliminary Diligence | F55: =FALSE() -> FALSE | G55: =FALSE() -> FALSE | H55: =TRUE() -> TRUE | I55: =TRUE() -> TRUE | J55: =TRUE() -> TRUE | K55: =TRUE() -> TRUE | L55: =TRUE() -> TRUE
A56: EV0339 | B56: Plaid Semi | C56: P2 - prelim dil, mostly empty | D56: 5 | E56: Preliminary Diligence | F56: =FALSE() -> FALSE | G56: =FALSE() -> FALSE | H56: =TRUE() -> TRUE | I56: =TRUE() -> TRUE | J56: =TRUE() -> TRUE | K56: =TRUE() -> TRUE | L56: =TRUE() -> TRUE
A57: EV0357 | B57: Qurv | C57: P2 - prelim dil, mostly empty | D57: 5 | E57: Preliminary Diligence | F57: =FALSE() -> FALSE | G57: =FALSE() -> FALSE | H57: =TRUE() -> TRUE | I57: =TRUE() -> TRUE | J57: =TRUE() -> TRUE | K57: =TRUE() -> TRUE | L57: =TRUE() -> TRUE
A58: EV0374 | B58: Resonant Thermal | C58: P2 - prelim dil, mostly empty | D58: 4 | E58: Preliminary Diligence | F58: =FALSE() -> FALSE | G58: =TRUE() -> TRUE | H58: =TRUE() -> TRUE | I58: =TRUE() -> TRUE | J58: =TRUE() -> TRUE | K58: =TRUE() -> TRUE | L58: =FALSE() -> FALSE | P58: Alaina Hartnett
A59: EV0375 | B59: Reverion | C59: P2 - prelim dil, mostly empty | D59: 5 | E59: Preliminary Diligence | F59: =FALSE() -> FALSE | G59: =FALSE() -> FALSE | H59: =TRUE() -> TRUE | I59: =TRUE() -> TRUE | J59: =TRUE() -> TRUE | K59: =TRUE() -> TRUE | L59: =TRUE() -> TRUE
A60: EV0379 | B60: Riven AI | C60: P2 - prelim dil, mostly empty | D60: 5 | E60: Preliminary Diligence | F60: =FALSE() -> FALSE | G60: =FALSE() -> FALSE | H60: =TRUE() -> TRUE | I60: =TRUE() -> TRUE | J60: =TRUE() -> TRUE | K60: =TRUE() -> TRUE | L60: =TRUE() -> TRUE
A61: EV0382 | B61: Ropirio | C61: P2 - prelim dil, mostly empty | D61: 5 | E61: Preliminary Diligence | F61: =FALSE() -> FALSE | G61: =FALSE() -> FALSE | H61: =TRUE() -> TRUE | I61: =TRUE() -> TRUE | J61: =TRUE() -> TRUE | K61: =TRUE() -> TRUE | L61: =TRUE() -> TRUE
A62: EV0384 | B62: SKIP2 NewCo | C62: P2 - prelim dil, mostly empty | D62: 5 | E62: Preliminary Diligence | F62: =FALSE() -> FALSE | G62: =FALSE() -> FALSE | H62: =TRUE() -> TRUE | I62: =TRUE() -> TRUE | J62: =TRUE() -> TRUE | K62: =TRUE() -> TRUE | L62: =TRUE() -> TRUE
A63: EV0399 | B63: Senvera Tx | C63: P2 - prelim dil, mostly empty | D63: 5 | E63: Preliminary Diligence | F63: =FALSE() -> FALSE | G63: =FALSE() -> FALSE | H63: =TRUE() -> TRUE | I63: =TRUE() -> TRUE | J63: =TRUE() -> TRUE | K63: =TRUE() -> TRUE | L63: =TRUE() -> TRUE
A64: EV0410 | B64: Soret Tech | C64: P2 - prelim dil, mostly empty | D64: 5 | E64: Preliminary Diligence | F64: =FALSE() -> FALSE | G64: =FALSE() -> FALSE | H64: =TRUE() -> TRUE | I64: =TRUE() -> TRUE | J64: =TRUE() -> TRUE | K64: =TRUE() -> TRUE | L64: =TRUE() -> TRUE
A65: EV0417 | B65: Stick Tx | C65: P2 - prelim dil, mostly empty | D65: 3 | E65: Preliminary Diligence | F65: =FALSE() -> FALSE | G65: =TRUE() -> TRUE | H65: =FALSE() -> FALSE | I65: =TRUE() -> TRUE | J65: =TRUE() -> TRUE | K65: =TRUE() -> TRUE | L65: =FALSE() -> FALSE | M65: sticktx.com | P65: Dan Resnicow
A66: EV0423 | B66: Supra | C66: P2 - prelim dil, mostly empty | D66: 5 | E66: Preliminary Diligence | F66: =FALSE() -> FALSE | G66: =FALSE() -> FALSE | H66: =TRUE() -> TRUE | I66: =TRUE() -> TRUE | J66: =TRUE() -> TRUE | K66: =TRUE() -> TRUE | L66: =TRUE() -> TRUE
A67: EV0429 | B67: THEMA Foundries | C67: P2 - prelim dil, mostly empty | D67: 5 | E67: Preliminary Diligence | F67: =FALSE() -> FALSE | G67: =FALSE() -> FALSE | H67: =TRUE() -> TRUE | I67: =TRUE() -> TRUE | J67: =TRUE() -> TRUE | K67: =TRUE() -> TRUE | L67: =TRUE() -> TRUE
A68: EV0434 | B68: Tech | C68: P2 - prelim dil, mostly empty | D68: 5 | E68: Preliminary Diligence | F68: =FALSE() -> FALSE | G68: =FALSE() -> FALSE | H68: =TRUE() -> TRUE | I68: =TRUE() -> TRUE | J68: =TRUE() -> TRUE | K68: =TRUE() -> TRUE | L68: =TRUE() -> TRUE
A69: EV0435 | B69: Tech/ Resonant Thermal | C69: P2 - prelim dil, mostly empty | D69: 4 | E69: Preliminary Diligence | F69: =FALSE() -> FALSE | G69: =TRUE() -> TRUE | H69: =TRUE() -> TRUE | I69: =TRUE() -> TRUE | J69: =TRUE() -> TRUE | K69: =TRUE() -> TRUE | L69: =FALSE() -> FALSE | P69: Alaina Hartnett
A70: EV0436 | B70: Telos | C70: P2 - prelim dil, mostly empty | D70: 5 | E70: Preliminary Diligence | F70: =FALSE() -> FALSE | G70: =FALSE() -> FALSE | H70: =TRUE() -> TRUE | I70: =TRUE() -> TRUE | J70: =TRUE() -> TRUE | K70: =TRUE() -> TRUE | L70: =TRUE() -> TRUE
A71: EV0438 | B71: Tenenbaum NewCo | C71: P2 - prelim dil, mostly empty | D71: 5 | E71: Preliminary Diligence | F71: =FALSE() -> FALSE | G71: =FALSE() -> FALSE | H71: =TRUE() -> TRUE | I71: =TRUE() -> TRUE | J71: =TRUE() -> TRUE | K71: =TRUE() -> TRUE | L71: =TRUE() -> TRUE
A72: EV0451 | B72: Titan Biosciences | C72: P2 - prelim dil, mostly empty | D72: 4 | E72: Preliminary Diligence | F72: =FALSE() -> FALSE | G72: =TRUE() -> TRUE | H72: =TRUE() -> TRUE | I72: =TRUE() -> TRUE | J72: =TRUE() -> TRUE | K72: =TRUE() -> TRUE | L72: =FALSE() -> FALSE | P72: Dan Resnicow
A73: EV0455 | B73: TriMind | C73: P2 - prelim dil, mostly empty | D73: 3 | E73: Preliminary Diligence | F73: =FALSE() -> FALSE | G73: =TRUE() -> TRUE | H73: =TRUE() -> TRUE | I73: =TRUE() -> TRUE | J73: =FALSE() -> FALSE | K73: =TRUE() -> TRUE | L73: =FALSE() -> FALSE | O73: Seed | P73: Madeleine Laitz
A74: EV0461 | B74: Tyce AI | C74: P2 - prelim dil, mostly empty | D74: 5 | E74: Preliminary Diligence | F74: =FALSE() -> FALSE | G74: =FALSE() -> FALSE | H74: =TRUE() -> TRUE | I74: =TRUE() -> TRUE | J74: =TRUE() -> TRUE | K74: =TRUE() -> TRUE | L74: =TRUE() -> TRUE
A75: EV0470 | B75: Virome Therapeutics | C75: P2 - prelim dil, mostly empty | D75: 5 | E75: Preliminary Diligence | F75: =FALSE() -> FALSE | G75: =FALSE() -> FALSE | H75: =TRUE() -> TRUE | I75: =TRUE() -> TRUE | J75: =TRUE() -> TRUE | K75: =TRUE() -> TRUE | L75: =TRUE() -> TRUE
A76: EV0472 | B76: Volantis | C76: P2 - prelim dil, mostly empty | D76: 5 | E76: Preliminary Diligence | F76: =FALSE() -> FALSE | G76: =FALSE() -> FALSE | H76: =TRUE() -> TRUE | I76: =TRUE() -> TRUE | J76: =TRUE() -> TRUE | K76: =TRUE() -> TRUE | L76: =TRUE() -> TRUE
A77: EV0474 | B77: Voya Energy | C77: P2 - prelim dil, mostly empty | D77: 5 | E77: Preliminary Diligence | F77: =FALSE() -> FALSE | G77: =FALSE() -> FALSE | H77: =TRUE() -> TRUE | I77: =TRUE() -> TRUE | J77: =TRUE() -> TRUE | K77: =TRUE() -> TRUE | L77: =TRUE() -> TRUE
A78: EV0476 | B78: Vsinc AI | C78: P2 - prelim dil, mostly empty | D78: 5 | E78: Preliminary Diligence | F78: =FALSE() -> FALSE | G78: =FALSE() -> FALSE | H78: =TRUE() -> TRUE | I78: =TRUE() -> TRUE | J78: =TRUE() -> TRUE | K78: =TRUE() -> TRUE | L78: =TRUE() -> TRUE
A79: EV0480 | B79: Water: Cetos / Kira /Eden | C79: P2 - prelim dil, mostly empty | D79: 5 | E79: Preliminary Diligence | F79: =FALSE() -> FALSE | G79: =FALSE() -> FALSE | H79: =TRUE() -> TRUE | I79: =TRUE() -> TRUE | J79: =TRUE() -> TRUE | K79: =TRUE() -> TRUE | L79: =TRUE() -> TRUE
A80: EV0481 | B80: Water: Cetos / Kira /Eden Tech | C80: P2 - prelim dil, mostly empty | D80: 5 | E80: Preliminary Diligence | F80: =FALSE() -> FALSE | G80: =FALSE() -> FALSE | H80: =TRUE() -> TRUE | I80: =TRUE() -> TRUE | J80: =TRUE() -> TRUE | K80: =TRUE() -> TRUE | L80: =TRUE() -> TRUE
A81: EV0489 | B81: Xuanhe Robotics NewCo | C81: P2 - prelim dil, mostly empty | D81: 5 | E81: Preliminary Diligence | F81: =FALSE() -> FALSE | G81: =FALSE() -> FALSE | H81: =TRUE() -> TRUE | I81: =TRUE() -> TRUE | J81: =TRUE() -> TRUE | K81: =TRUE() -> TRUE | L81: =TRUE() -> TRUE
A82: EV0035 | B82: /Eden Tech | C82: P4 - acceptable | D82: 2 | E82: Preliminary Diligence | F82: =FALSE() -> FALSE | G82: =TRUE() -> TRUE | H82: =FALSE() -> FALSE | I82: =FALSE() -> FALSE | J82: =TRUE() -> TRUE | K82: =TRUE() -> TRUE | L82: =FALSE() -> FALSE | M82: edentechinc.com | N82: United States | P82: Alaina Hartnett
A83: EV0042 | B83: Adiabatic Machines | C83: P4 - acceptable | D83: 1 | E83: Preliminary Diligence | F83: =FALSE() -> FALSE | G83: =TRUE() -> TRUE | H83: =FALSE() -> FALSE | I83: =TRUE() -> TRUE | J83: =FALSE() -> FALSE | K83: =FALSE() -> FALSE | L83: =FALSE() -> FALSE | M83: adiabaticmachines.com | O83: Preseed | P83: Deepa Rao
A84: EV0055 | B84: AlumaPower | C84: P4 - acceptable | D84: 2 | E84: Preliminary Diligence | F84: =FALSE() -> FALSE | G84: =TRUE() -> TRUE | H84: =FALSE() -> FALSE | I84: =FALSE() -> FALSE | J84: =TRUE() -> TRUE | K84: =TRUE() -> TRUE | L84: =FALSE() -> FALSE | M84: alumapower.com | N84: Canada | P84: Alaina Hartnett
A85: EV0058 | B85: Amplify Computing | C85: P4 - acceptable | D85: 2 | E85: Preliminary Diligence | F85: =FALSE() -> FALSE | G85: =TRUE() -> TRUE | H85: =TRUE() -> TRUE | I85: =TRUE() -> TRUE | J85: =FALSE() -> FALSE | K85: =FALSE() -> FALSE | L85: =FALSE() -> FALSE | O85: Seed | P85: Madeleine Laitz
A86: EV0070 | B86: Artisan Insight | C86: P4 - acceptable | D86: 1 | E86: Preliminary Diligence | F86: =FALSE() -> FALSE | G86: =TRUE() -> TRUE | H86: =FALSE() -> FALSE | I86: =TRUE() -> TRUE | J86: =FALSE() -> FALSE | K86: =FALSE() -> FALSE | L86: =FALSE() -> FALSE | M86: artisaninsight.com | O86: Seed | P86: Madeleine Laitz
A87: EV0075 | B87: AssetCool | C87: P4 - acceptable | D87: 1 | E87: Preliminary Diligence | F87: =FALSE() -> FALSE | G87: =TRUE() -> TRUE | H87: =FALSE() -> FALSE | I87: =FALSE() -> FALSE | J87: =FALSE() -> FALSE | K87: =TRUE() -> TRUE | L87: =FALSE() -> FALSE | M87: assetcool.com | N87: United Kingdom | O87: Series B | P87: Alaina Hartnett
A88: EV0094 | B88: Besxar | C88: P4 - acceptable | D88: 1 | E88: Preliminary Diligence | F88: =FALSE() -> FALSE | G88: =TRUE() -> TRUE | H88: =FALSE() -> FALSE | I88: =TRUE() -> TRUE | J88: =FALSE() -> FALSE | K88: =FALSE() -> FALSE | L88: =FALSE() -> FALSE | M88: besxar.com | O88: Seed | P88: Alaina Hartnett
A89: EV0103 | B89: Braid Robotics | C89: P4 - acceptable | D89: 2 | E89: Preliminary Diligence | F89: =FALSE() -> FALSE | G89: =TRUE() -> TRUE | H89: =TRUE() -> TRUE | I89: =TRUE() -> TRUE | J89: =FALSE() -> FALSE | K89: =FALSE() -> FALSE | L89: =FALSE() -> FALSE | O89: Seed | P89: Madeleine Laitz
A90: EV0106 | B90: CMatrics | C90: P4 - acceptable | D90: 2 | E90: Preliminary Diligence | F90: =FALSE() -> FALSE | G90: =TRUE() -> TRUE | H90: =TRUE() -> TRUE | I90: =TRUE() -> TRUE | J90: =FALSE() -> FALSE | K90: =FALSE() -> FALSE | L90: =FALSE() -> FALSE | O90: Series A | P90: Richard Collins
A91: EV0108 | B91: Caladan | C91: P4 - acceptable | D91: 1 | E91: Preliminary Diligence | F91: =FALSE() -> FALSE | G91: =TRUE() -> TRUE | H91: =FALSE() -> FALSE | I91: =FALSE() -> FALSE | J91: =FALSE() -> FALSE | K91: =TRUE() -> TRUE | L91: =FALSE() -> FALSE | M91: caladan.bio | N91: United States | O91: Series A | P91: Rachel Field
A92: EV0125 | B92: ChipAdd | C92: P4 - acceptable | D92: 2 | E92: Preliminary Diligence | F92: =FALSE() -> FALSE | G92: =TRUE() -> TRUE | H92: =FALSE() -> FALSE | I92: =TRUE() -> TRUE | J92: =FALSE() -> FALSE | K92: =TRUE() -> TRUE | L92: =FALSE() -> FALSE | M92: chipadd.com | O92: Seed | P92: Alaina Hartnett
A93: EV0126 | B93: ChipX | C93: P4 - acceptable | D93: 2 | E93: Preliminary Diligence | F93: =FALSE() -> FALSE | G93: =TRUE() -> TRUE | H93: =TRUE() -> TRUE | I93: =TRUE() -> TRUE | J93: =FALSE() -> FALSE | K93: =FALSE() -> FALSE | L93: =FALSE() -> FALSE | O93: Seed | P93: Madeleine Laitz
A94: EV0129 | B94: Coformer.ai | C94: P4 - acceptable | D94: 2 | E94: Preliminary Diligence | F94: =FALSE() -> FALSE | G94: =TRUE() -> TRUE | H94: =FALSE() -> FALSE | I94: =FALSE() -> FALSE | J94: =TRUE() -> TRUE | K94: =TRUE() -> TRUE | L94: =FALSE() -> FALSE | M94: coformer.ai | N94: United States | P94: Vinny Beranek
A95: EV0130 | B95: CombustWell | C95: P4 - acceptable | D95: 2 | E95: Preliminary Diligence | F95: =FALSE() -> FALSE | G95: =TRUE() -> TRUE | H95: =TRUE() -> TRUE | I95: =TRUE() -> TRUE | J95: =FALSE() -> FALSE | K95: =FALSE() -> FALSE | L95: =FALSE() -> FALSE | O95: Seed | P95: Richard Collins
A96: EV0145 | B96: Dynamical Mind | C96: P4 - acceptable | D96: 1 | E96: Preliminary Diligence | F96: =FALSE() -> FALSE | G96: =TRUE() -> TRUE | H96: =FALSE() -> FALSE | I96: =TRUE() -> TRUE | J96: =FALSE() -> FALSE | K96: =FALSE() -> FALSE | L96: =FALSE() -> FALSE | M96: dynamicalmind.com | O96: Seed | P96: Alaina Hartnett
A97: EV0157 | B97: Emergentia | C97: P4 - acceptable | D97: 2 | E97: Preliminary Diligence | F97: =FALSE() -> FALSE | G97: =TRUE() -> TRUE | H97: =TRUE() -> TRUE | I97: =TRUE() -> TRUE | J97: =FALSE() -> FALSE | K97: =FALSE() -> FALSE | L97: =FALSE() -> FALSE | O97: Seed | P97: Madeleine Laitz
A98: EV0159 | B98: Epia Neuro | C98: P4 - acceptable | D98: 2 | E98: Preliminary Diligence | F98: =FALSE() -> FALSE | G98: =TRUE() -> TRUE | H98: =FALSE() -> FALSE | I98: =FALSE() -> FALSE | J98: =TRUE() -> TRUE | K98: =TRUE() -> TRUE | L98: =FALSE() -> FALSE | M98: epianeuro.com | N98: United States | P98: Rachel Field
A99: EV0162 | B99: Exousia | C99: P4 - acceptable | D99: 2 | E99: Preliminary Diligence | F99: =FALSE() -> FALSE | G99: =TRUE() -> TRUE | H99: =TRUE() -> TRUE | I99: =TRUE() -> TRUE | J99: =FALSE() -> FALSE | K99: =FALSE() -> FALSE | L99: =FALSE() -> FALSE | O99: Series A | P99: Madeleine Laitz
A100: EV0180 | B100: Fusion Dynamics | C100: P4 - acceptable | D100: 1 | E100: Preliminary Diligence | F100: =FALSE() -> FALSE | G100: =TRUE() -> TRUE | H100: =FALSE() -> FALSE | I100: =TRUE() -> TRUE | J100: =FALSE() -> FALSE | K100: =FALSE() -> FALSE | L100: =FALSE() -> FALSE | M100: fusiondynamicscorporation.com | O100: Seed | P100: Alaina Hartnett
A101: EV0200 | B101: HexaGAN | C101: P4 - acceptable | D101: 2 | E101: Preliminary Diligence | F101: =FALSE() -> FALSE | G101: =TRUE() -> TRUE | H101: =TRUE() -> TRUE | I101: =TRUE() -> TRUE | J101: =FALSE() -> FALSE | K101: =FALSE() -> FALSE | L101: =FALSE() -> FALSE | O101: Seed | P101: Madeleine Laitz
...

Sheet Data Dictionary
A1: Field | B1: Definition | C1: Source
A2: company_id | B2: Surrogate key assigned in this build. Stable within this file only. | C2: Derived
A3: company_name | B3: Canonical name — most frequent spelling across slides. | C3: Slides
A4: website | B4: Company domain. | C4: Affinity / Public
A5: discussed_in_new_deal_meeting | B5: TRUE if bold on any meeting slide since 2025-10-01. | C5: Slides (font weight)
A6: discussion_dates | B6: Semicolon-separated dates of every meeting where the name was bold. | C6: Slides
A7: first/last_discussion_date | B7: First and last bold appearance. | C7: Slides
A8: times_discussed | B8: Count of distinct meetings where bold. | C8: Slides
A9: furthest_stage_on_slides | B9: Most advanced slide column reached. Legal > Negotiate > Deep Dil > Prelim Dil > NewCo/Hold > Meetings. | C9: Slides
A10: date_reached_furthest_stage | B10: First meeting at that stage. | C10: Slides
A11: latest_stage_on_slides | B11: Stage at the most recent appearance. Differs from furthest when a deal fell back. | C11: Slides
A12: reached_* / date_* | B12: Boolean plus first date for each funnel stage. This is the transition history Affinity lacks. | C12: Slides
... A29: needs_* | B29: TRUE where that field is blank. Drives the worklist. | C29: Derived
